Workbook

Sheet Cliente
A1: Id | B1: Nome | C1: CPF-CNPJ | D1: Cidade UF | E1: Anotações Cliente | F1: Valor Total | G1: Valor Pago | H1: Valor Pendente
A2: a5d4b2e5 | B2: Adailton | F2: =SUMIFS(PedidodeVenda!E:E,PedidodeVenda!D:D,B:B) -> 0 | G2: =SUMIFS(PedidodeVenda!F:F,PedidodeVenda!D:D,B:B) -> 0 | H2: =F2-G2 -> 0
A3: a5d4b2e6 | B3: Alianca | F3: =SUMIFS(PedidodeVenda!E:E,PedidodeVenda!D:D,B:B) -> 0 | G3: =SUMIFS(PedidodeVenda!F:F,PedidodeVenda!D:D,B:B) -> 0 | H3: =F3-G3 -> 0
A4: a5d4b2e7 | B4: Alipio Gomes da Costa | C4: 211.898.624-68 | D4: São Bento da Una/PE | F4: =SUMIFS(PedidodeVenda!E:E,PedidodeVenda!D:D,B:B) -> 0 | G4: =SUMIFS(PedidodeVenda!F:F,PedidodeVenda!D:D,B:B) -> 0 | H4: =F4-G4 -> 0
A5: a5d4b2e36 | B5: André Corretor | F5: =SUMIFS(PedidodeVenda!E:E,PedidodeVenda!D:D,B:B) -> 54131.19 | G5: =SUMIFS(PedidodeVenda!F:F,PedidodeVenda!D:D,B:B) -> 54131.19 | H5: =F5-G5 -> 0
A6: a5d4b2e20 | B6: Cajazeirinhas | F6: =SUMIFS(PedidodeVenda!E:E,PedidodeVenda!D:D,B:B) -> 0 | G6: =SUMIFS(PedidodeVenda!F:F,PedidodeVenda!D:D,B:B) -> 0 | H6: =F6-G6 -> 0
A7: a5d4b2e21 | B7: Caruaru J2 | F7: =SUMIFS(PedidodeVenda!E:E,PedidodeVenda!D:D,B:B) -> 0 | G7: =SUMIFS(PedidodeVenda!F:F,PedidodeVenda!D:D,B:B) -> 0 | H7: =F7-G7 -> 0
A8: a5d4b2e22 | B8: Clodoaldo Corretor | F8: =SUMIFS(PedidodeVenda!E:E,PedidodeVenda!D:D,B:B) -> 9143744.8 | G8: =SUMIFS(PedidodeVenda!F:F,PedidodeVenda!D:D,B:B) -> 9113073.4 | H8: =F8-G8 -> 30671.34
A9: a5d4b2e23 | B9: Cooperflores | F9: =SUMIFS(PedidodeVenda!E:E,PedidodeVenda!D:D,B:B) -> 363744 | G9: =SUMIFS(PedidodeVenda!F:F,PedidodeVenda!D:D,B:B) -> 363744 | H9: =F9-G9 -> 0
A10: a5d4b2e24 | B10: Diego Atacadao Racao | F10: =SUMIFS(PedidodeVenda!E:E,PedidodeVenda!D:D,B:B) -> 4263252 | G10: =SUMIFS(PedidodeVenda!F:F,PedidodeVenda!D:D,B:B) -> 4263252 | H10: =F10-G10 -> 0
A11: a5d4b2e25 | B11: Ducampo Campina | F11: =SUMIFS(PedidodeVenda!E:E,PedidodeVenda!D:D,B:B) -> 0 | G11: =SUMIFS(PedidodeVenda!F:F,PedidodeVenda!D:D,B:B) -> 0 | H11: =F11-G11 -> 0
A12: a5d4b2e26 | B12: Fernando Vilela | F12: =SUMIFS(PedidodeVenda!E:E,PedidodeVenda!D:D,B:B) -> 0 | G12: =SUMIFS(PedidodeVenda!F:F,PedidodeVenda!D:D,B:B) -> 0 | H12: =F12-G12 -> 0
A13: a5d4b2e28 | B13: Frango Favorito Ltda | C13: 24.959.078/0023-01 | D13: Belo Jardim/PE | F13: =SUMIFS(PedidodeVenda!E:E,PedidodeVenda!D:D,B:B) -> 0 | G13: =SUMIFS(PedidodeVenda!F:F,PedidodeVenda!D:D,B:B) -> 0 | H13: =F13-G13 -> 0
A14: a5d4b2e29 | B14: Granja Canaa | F14: =SUMIFS(PedidodeVenda!E:E,PedidodeVenda!D:D,B:B) -> 2440901.7 | G14: =SUMIFS(PedidodeVenda!F:F,PedidodeVenda!D:D,B:B) -> 2440901.7 | H14: =F14-G14 -> 0
A15: a5d4b2e30 | B15: Granja Kumamoto | F15: =SUMIFS(PedidodeVenda!E:E,PedidodeVenda!D:D,B:B) -> 485105.74 | G15: =SUMIFS(PedidodeVenda!F:F,PedidodeVenda!D:D,B:B) -> 485105.74 | H15: =F15-G15 -> 0
A16: a5d4b2e31 | B16: Guaraves | F16: =SUMIFS(PedidodeVenda!E:E,PedidodeVenda!D:D,B:B) -> 2927598.8 | G16: =SUMIFS(PedidodeVenda!F:F,PedidodeVenda!D:D,B:B) -> 2927598.8 | H16: =F16-G16 -> 0
A17: a5d4b2e32 | B17: Japones | F17: =SUMIFS(PedidodeVenda!E:E,PedidodeVenda!D:D,B:B) -> 1220579.3 | G17: =SUMIFS(PedidodeVenda!F:F,PedidodeVenda!D:D,B:B) -> 1220579.3 | H17: =F17-G17 -> -2.3283064e-10
A18: a5d4b2e33 | B18: Kenichi Iwata | C18: 084.455.084-15 | D18: Tejucupapo/PE | F18: =SUMIFS(PedidodeVenda!E:E,PedidodeVenda!D:D,B:B) -> 0 | G18: =SUMIFS(PedidodeVenda!F:F,PedidodeVenda!D:D,B:B) -> 0 | H18: =F18-G18 -> 0
A19: a5d4b2e34 | B19: Matildes | F19: =SUMIFS(PedidodeVenda!E:E,PedidodeVenda!D:D,B:B) -> 0 | G19: =SUMIFS(PedidodeVenda!F:F,PedidodeVenda!D:D,B:B) -> 0 | H19: =F19-G19 -> 0
A20: a5d4b2e35 | B20: Michael Campina Grande | F20: =SUMIFS(PedidodeVenda!E:E,PedidodeVenda!D:D,B:B) -> 3358421.9 | G20: =SUMIFS(PedidodeVenda!F:F,PedidodeVenda!D:D,B:B) -> 3358421.9 | H20: =F20-G20 -> 0
A21: a5d4b2e37 | B21: Natto Alimentos | C21: 01.682.695/0001-00 | D21: Garanhuns/PE | F21: =SUMIFS(PedidodeVenda!E:E,PedidodeVenda!D:D,B:B) -> 8538483.8 | G21: =SUMIFS(PedidodeVenda!F:F,PedidodeVenda!D:D,B:B) -> 8537819.7 | H21: =F21-G21 -> 664.12
A22: a5d4b2e38 | B22: Ovos Sao Tome | F22: =SUMIFS(PedidodeVenda!E:E,PedidodeVenda!D:D,B:B) -> 1562176.2 | G22: =SUMIFS(PedidodeVenda!F:F,PedidodeVenda!D:D,B:B) -> 1456011.2 | H22: =F22-G22 -> 106165
A23: a5d4b2e39 | B23: Pesqueira | F23: =SUMIFS(PedidodeVenda!E:E,PedidodeVenda!D:D,B:B) -> 0 | G23: =SUMIFS(PedidodeVenda!F:F,PedidodeVenda!D:D,B:B) -> 0 | H23: =F23-G23 -> 0
A24: a5d4b2e40 | B24: Rei Do Ouro | F24: =SUMIFS(PedidodeVenda!E:E,PedidodeVenda!D:D,B:B) -> 1670988 | G24: =SUMIFS(PedidodeVenda!F:F,PedidodeVenda!D:D,B:B) -> 1670988 | H24: =F24-G24 -> 0
A25: a5d4b2e41 | B25: Reinaldo | F25: =SUMIFS(PedidodeVenda!E:E,PedidodeVenda!D:D,B:B) -> 489282.02 | G25: =SUMIFS(PedidodeVenda!F:F,PedidodeVenda!D:D,B:B) -> 489282.02 | H25: =F25-G25 -> 0
A26: a5d4b2e42 | B26: Rildo Roque Ferraz | C26: 22.381.240/0001-16 | D26: Sao Bento do Una/PE | F26: =SUMIFS(PedidodeVenda!E:E,PedidodeVenda!D:D,B:B) -> 2321404 | G26: =SUMIFS(PedidodeVenda!F:F,PedidodeVenda!D:D,B:B) -> 2319272.2 | H26: =F26-G26 -> 2131.83
A27: a5d4b2e43 | B27: Rural Log Pedro Falcao | F27: =SUMIFS(PedidodeVenda!E:E,PedidodeVenda!D:D,B:B) -> 0 | G27: =SUMIFS(PedidodeVenda!F:F,PedidodeVenda!D:D,B:B) -> 0 | H27: =F27-G27 -> 0
A28: a5d4b2e44 | B28: Sao Bento Branco | F28: =SUMIFS(PedidodeVenda!E:E,PedidodeVenda!D:D,B:B) -> 0 | G28: =SUMIFS(PedidodeVenda!F:F,PedidodeVenda!D:D,B:B) -> 0 | H28: =F28-G28 -> 0
A29: a5d4b2e46 | B29: São Braz S/A Industria E Comercio De Alimentos | C29: 08.811.226/0001-84 | D29: Cabedelo/PB | F29: =SUMIFS(PedidodeVenda!E:E,PedidodeVenda!D:D,B:B) -> 32158026 | G29: =SUMIFS(PedidodeVenda!F:F,PedidodeVenda!D:D,B:B) -> 31678764 | H29: =F29-G29 -> 479261.64
A30: a5d4b2e47 | B30: Sr. Pedro São Bento | F30: =SUMIFS(PedidodeVenda!E:E,PedidodeVenda!D:D,B:B) -> 0 | G30: =SUMIFS(PedidodeVenda!F:F,PedidodeVenda!D:D,B:B) -> 0 | H30: =F30-G30 -> 0
A31: a5d4b2e48 | B31: Sr. Pedro Vitoria | F31: =SUMIFS(PedidodeVenda!E:E,PedidodeVenda!D:D,B:B) -> 1103947.1 | G31: =SUMIFS(PedidodeVenda!F:F,PedidodeVenda!D:D,B:B) -> 1103947.1 | H31: =F31-G31 -> 0
A32: a5d4b2e49 | B32: Thiago Garanhuns | D32: Garanhuns/PE | F32: =SUMIFS(PedidodeVenda!E:E,PedidodeVenda!D:D,B:B) -> 703352.51 | G32: =SUMIFS(PedidodeVenda!F:F,PedidodeVenda!D:D,B:B) -> 703352.51 | H32: =F32-G32 -> 0
A33: a5d4b2e52 | B33: Vitamilho Alimentos LTDA | C33: 00.686.452/0001-79 | D33: Garanhuns/PE | F33: =SUMIFS(PedidodeVenda!E:E,PedidodeVenda!D:D,B:B) -> 5652731.7 | G33: =SUMIFS(PedidodeVenda!F:F,PedidodeVenda!D:D,B:B) -> 5652731.7 | H33: =F33-G33 -> 0
A34: ded4bf47 | B34: Ana Maria Laroche | D34: Paulista/PE | F34: =SUMIFS(PedidodeVenda!E:E,PedidodeVenda!D:D,B:B) -> 2359757.7 | G34: =SUMIFS(PedidodeVenda!F:F,PedidodeVenda!D:D,B:B) -> 2258453.6 | H34: =F34-G34 -> 101304.07
A35: 3f5ae7e1 | B35: André Timbauba | D35: Timbauba/PE | F35: =SUMIFS(PedidodeVenda!E:E,PedidodeVenda!D:D,B:B) -> 940078.7 | G35: =SUMIFS(PedidodeVenda!F:F,PedidodeVenda!D:D,B:B) -> 940078.7 | H35: =F35-G35 -> 0
A36: fc3e3b63 | B36: André Canguaretama | D36: Canguaretama/RN | F36: =SUMIFS(PedidodeVenda!E:E,PedidodeVenda!D:D,B:B) -> 192205.94 | G36: =SUMIFS(PedidodeVenda!F:F,PedidodeVenda!D:D,B:B) -> 192205.94 | H36: =F36-G36 -> 0
A37: 3b11ed5d | B37: Santa Cruz - RN | D37: Santa Cruz/RN | F37: =SUMIFS(PedidodeVenda!E:E,PedidodeVenda!D:D,B:B) -> 1095882.5 | G37: =SUMIFS(PedidodeVenda!F:F,PedidodeVenda!D:D,B:B) -> 1095882.5 | H37: =F37-G37 -> 0
A38: 96061475 | B38: Frei Damião | D38: Garanhuns/PE | F38: =SUMIFS(PedidodeVenda!E:E,PedidodeVenda!D:D,B:B) -> 2011585.4 | G38: =SUMIFS(PedidodeVenda!F:F,PedidodeVenda!D:D,B:B) -> 2010559 | H38: =F38-G38 -> 1026.4
A39: 38613a7e | B39: André Mamanguape | D39: Mamanguape/PB | F39: =SUMIFS(PedidodeVenda!E:E,PedidodeVenda!D:D,B:B) -> 495390.98 | G39: =SUMIFS(PedidodeVenda!F:F,PedidodeVenda!D:D,B:B) -> 495390.98 | H39: =F39-G39 -> 0
A40: 4540227f | B40: André Macaíbas | D40: Macaíbas/RN | F40: =SUMIFS(PedidodeVenda!E:E,PedidodeVenda!D:D,B:B) -> 1619564.1 | G40: =SUMIFS(PedidodeVenda!F:F,PedidodeVenda!D:D,B:B) -> 1619564.1 | H40: =F40-G40 -> 0
A41: 500274ab | B41: Ilario Campina Grande | D41: Campina Grande/PB | F41: =SUMIFS(PedidodeVenda!E:E,PedidodeVenda!D:D,B:B) -> 2168171.9 | G41: =SUMIFS(PedidodeVenda!F:F,PedidodeVenda!D:D,B:B) -> 2168171.9 | H41: =F41-G41 -> 0
A42: 5f21748a | B42: André Pombal | D42: Pombal/PB | F42: =SUMIFS(PedidodeVenda!E:E,PedidodeVenda!D:D,B:B) -> 70882 | G42: =SUMIFS(PedidodeVenda!F:F,PedidodeVenda!D:D,B:B) -> 70882 | H42: =F42-G42 -> 0
A43: eb11b697 | B43: Natto Branco | D43: Garanhuns/PE | F43: =SUMIFS(PedidodeVenda!E:E,PedidodeVenda!D:D,B:B) -> 1337038.7 | G43: =SUMIFS(PedidodeVenda!F:F,PedidodeVenda!D:D,B:B) -> 1337038.7 | H43: =F43-G43 -> 2.3283064e-10
A44: 274e251d | B44: Michel Campina Grande / Azevem | D44: Campina Grande/PB | F44: =SUMIFS(PedidodeVenda!E:E,PedidodeVenda!D:D,B:B) -> 760185.55 | G44: =SUMIFS(PedidodeVenda!F:F,PedidodeVenda!D:D,B:B) -> 760185.55 | H44: =F44-G44 -> -1.1641532e-10
A45: 527641ed | B45: Natto Newtinho | D45: Não Informado/PE | F45: =SUMIFS(PedidodeVenda!E:E,PedidodeVenda!D:D,B:B) -> 811173.48 | G45: =SUMIFS(PedidodeVenda!F:F,PedidodeVenda!D:D,B:B) -> 811173.48 | H45: =F45-G45 -> 0
A46: c5a43774 | B46: Andre Brejinho | D46: Brejinho/PB | F46: =SUMIFS(PedidodeVenda!E:E,PedidodeVenda!D:D,B:B) -> 80822.77 | G46: =SUMIFS(PedidodeVenda!F:F,PedidodeVenda!D:D,B:B) -> 80822.77 | H46: =F46-G46 -> 0
A47: 1f0ff4dd | B47: Andre JP | D47: João Pessoa/PB | F47: =SUMIFS(PedidodeVenda!E:E,PedidodeVenda!D:D,B:B) -> 800861.95 | G47: =SUMIFS(PedidodeVenda!F:F,PedidodeVenda!D:D,B:B) -> 650877.19 | H47: =F47-G47 -> 149984.76
A48: a039fd0c | B48: André Nova Cruz | D48: Nova Cruz/RN | F48: =SUMIFS(PedidodeVenda!E:E,PedidodeVenda!D:D,B:B) -> 212381.95 | G48: =SUMIFS(PedidodeVenda!F:F,PedidodeVenda!D:D,B:B) -> 212381.95 | H48: =F48-G48 -> 0
A49: db220e9b | B49: Julia Igarassu | D49: Igarassu/PE | F49: =SUMIFS(PedidodeVenda!E:E,PedidodeVenda!D:D,B:B) -> 789944.4 | G49: =SUMIFS(PedidodeVenda!F:F,PedidodeVenda!D:D,B:B) -> 789944.4 | H49: =F49-G49 -> -1.1641532e-10
A50: 237f5e21 | B50: Três Corações | D50: Não Informado/PE | F50: =SUMIFS(PedidodeVenda!E:E,PedidodeVenda!D:D,B:B) -> 2179096.2 | G50: =SUMIFS(PedidodeVenda!F:F,PedidodeVenda!D:D,B:B) -> 2179096.2 | H50: =F50-G50 -> 0
... A61: a017835f | B61: Andre Natal | D61: Natal/RN | F61: =SUMIFS(PedidodeVenda!E:E,PedidodeVenda!D:D,B:B) -> 95912.94 | G61: =SUMIFS(PedidodeVenda!F:F,PedidodeVenda!D:D,B:B) -> 95912.94 | H61: =F61-G61 -> 0
A62: 865b5723 | B62: Ernesto SW4 | D62: Não Informado/SE | E62: SW4 | F62: =SUMIFS(PedidodeVenda!E:E,PedidodeVenda!D:D,B:B) -> 0 | G62: =SUMIFS(PedidodeVenda!F:F,PedidodeVenda!D:D,B:B) -> 0 | H62: =F62-G62 -> 0
A63: f80fcc0f | B63: Jorge Amarok | D63: Não Informado/SE | E63: Amarok | F63: =SUMIFS(PedidodeVenda!E:E,PedidodeVenda!D:D,B:B) -> 0 | G63: =SUMIFS(PedidodeVenda!F:F,PedidodeVenda!D:D,B:B) -> 0 | H63: =F63-G63 -> 0
A64: 2ecdafaf | B64: Vanilson Caruaru | D64: Caruaru/PE | F64: =SUMIFS(PedidodeVenda!E:E,PedidodeVenda!D:D,B:B) -> 556864.28 | G64: =SUMIFS(PedidodeVenda!F:F,PedidodeVenda!D:D,B:B) -> 556864.28 | H64: =F64-G64 -> 0
A65: a1aac07b | B65: André | D65: Não Informado/RN | F65: =SUMIFS(PedidodeVenda!E:E,PedidodeVenda!D:D,B:B) -> 226603.38 | G65: =SUMIFS(PedidodeVenda!F:F,PedidodeVenda!D:D,B:B) -> 226603.38 | H65: =F65-G65 -> 0
A66: de7f68d9 | B66: Sr Pedro Bonito | D66: Bonito/PE | F66: =SUMIFS(PedidodeVenda!E:E,PedidodeVenda!D:D,B:B) -> 158812.51 | G66: =SUMIFS(PedidodeVenda!F:F,PedidodeVenda!D:D,B:B) -> 158812.51 | H66: =F66-G66 -> 0
A67: af29f5eb | B67: André Caruaru | D67: Caruaru/PE | F67: =SUMIFS(PedidodeVenda!E:E,PedidodeVenda!D:D,B:B) -> 197743.04 | G67: =SUMIFS(PedidodeVenda!F:F,PedidodeVenda!D:D,B:B) -> 197743.04 | H67: =F67-G67 -> 0
A68: 18dcec5d | B68: André Mari | D68: Não Informado/RN | F68: =SUMIFS(PedidodeVenda!E:E,PedidodeVenda!D:D,B:B) -> 237226.99 | G68: =SUMIFS(PedidodeVenda!F:F,PedidodeVenda!D:D,B:B) -> 237226.99 | H68: =F68-G68 -> 0
A69: be608b2f | B69: Felipe Aguiar | D69: Não Informado/PE | F69: =SUMIFS(PedidodeVenda!E:E,PedidodeVenda!D:D,B:B) -> 92688.65 | G69: =SUMIFS(PedidodeVenda!F:F,PedidodeVenda!D:D,B:B) -> 92688.65 | H69: =F69-G69 -> 0
A70: 950c5f30 | B70: São Braz Bahia | D70: Não Informado/BA | F70: =SUMIFS(PedidodeVenda!E:E,PedidodeVenda!D:D,B:B) -> 2964507.8 | G70: =SUMIFS(PedidodeVenda!F:F,PedidodeVenda!D:D,B:B) -> 2964859.2 | H70: =F70-G70 -> -351.41
A71: fe02fbfa | B71: Ingredion | D71: Cabo de Santo Agostinho/PE | F71: =SUMIFS(PedidodeVenda!E:E,PedidodeVenda!D:D,B:B) -> 0 | G71: =SUMIFS(PedidodeVenda!F:F,PedidodeVenda!D:D,B:B) -> 0 | H71: =F71-G71 -> 0
A72: cfe4a0b8 | B72: Igredion | D72: Cabo de Santo Agostinho/PE | F72: =SUMIFS(PedidodeVenda!E:E,PedidodeVenda!D:D,B:B) -> 0 | G72: =SUMIFS(PedidodeVenda!F:F,PedidodeVenda!D:D,B:B) -> 0 | H72: =F72-G72 -> 0
A73: 29b09467 | B73: André Santo Antonio | D73: Não Informado/RN | F73: =SUMIFS(PedidodeVenda!E:E,PedidodeVenda!D:D,B:B) -> 114474.75 | G73: =SUMIFS(PedidodeVenda!F:F,PedidodeVenda!D:D,B:B) -> 114474.75 | H73: =F73-G73 -> 0
A74: b8a696e6 | B74: Michel Pocinhos | D74: Não Informado/PE | F74: =SUMIFS(PedidodeVenda!E:E,PedidodeVenda!D:D,B:B) -> 0 | G74: =SUMIFS(PedidodeVenda!F:F,PedidodeVenda!D:D,B:B) -> 0 | H74: =F74-G74 -> 0
A75: a2daf2db | B75: Pedro Caruaru | D75: Caruaru/PE | F75: =SUMIFS(PedidodeVenda!E:E,PedidodeVenda!D:D,B:B) -> 123664.32 | G75: =SUMIFS(PedidodeVenda!F:F,PedidodeVenda!D:D,B:B) -> 123664.32 | H75: =F75-G75 -> 0
... A117: 82a5cb93 | B117: Gika Notaro | D117: Não Informado/SE | F117: =SUMIFS(PedidodeVenda!E:E,PedidodeVenda!D:D,B:B) -> 102720 | G117: =SUMIFS(PedidodeVenda!F:F,PedidodeVenda!D:D,B:B) -> 102720 | H117: =F117-G117 -> 0

Sheet Produtor
A1: Id | B1: Nome | C1: CPF-CNPJ | D1: Cidade UF | E1: Valor Total | F1: Valor Pago | G1: Valor Pendente
A2: bce7e1da53 | B2: Adalberto Gloria | D2: Nossa Senhora da Glória/SE | E2: =SUMIFS(PedidodeCompra!F:F,PedidodeCompra!D:D,B:B) -> 0 | F2: =SUMIFS(PedidodeCompra!G:G,PedidodeCompra!D:D,B:B) -> 0 | G2: =E2-F2 -> 0
A3: bce7e1da51 | B3: Adriano Aquidaba | D3: Aquidabã/SE | E3: =SUMIFS(PedidodeCompra!F:F,PedidodeCompra!D:D,B:B) -> 0 | F3: =SUMIFS(PedidodeCompra!G:G,PedidodeCompra!D:D,B:B) -> 0 | G3: =E3-F3 -> 0
A4: bce7e1da08 | B4: Alan Plantec | D4: Nossa Senhora da Glória/SE | E4: =SUMIFS(PedidodeCompra!F:F,PedidodeCompra!D:D,B:B) -> 0 | F4: =SUMIFS(PedidodeCompra!G:G,PedidodeCompra!D:D,B:B) -> 0 | G4: =E4-F4 -> 0
A5: bce7e1da60 | B5: Alexandre | D5: Nossa Senhora da Glória/SE | E5: =SUMIFS(PedidodeCompra!F:F,PedidodeCompra!D:D,B:B) -> 0 | F5: =SUMIFS(PedidodeCompra!G:G,PedidodeCompra!D:D,B:B) -> 0 | G5: =E5-F5 -> 0
A6: bce7e1da04 | B6: Andre Aparecida | D6: Oeiras/MA | E6: =SUMIFS(PedidodeCompra!F:F,PedidodeCompra!D:D,B:B) -> 0 | F6: =SUMIFS(PedidodeCompra!G:G,PedidodeCompra!D:D,B:B) -> 0 | G6: =E6-F6 -> 0
A7: bce7e1da18 | B7: Bruno Emporio | D7: Nossa Senhora da Glória/SE | E7: =SUMIFS(PedidodeCompra!F:F,PedidodeCompra!D:D,B:B) -> 0 | F7: =SUMIFS(PedidodeCompra!G:G,PedidodeCompra!D:D,B:B) -> 0 | G7: =E7-F7 -> 0
A8: bce7e1da62 | B8: Carlos Japoata | D8: Japoatã/SE | E8: =SUMIFS(PedidodeCompra!F:F,PedidodeCompra!D:D,B:B) -> 0 | F8: =SUMIFS(PedidodeCompra!G:G,PedidodeCompra!D:D,B:B) -> 0 | G8: =E8-F8 -> 0
A9: bce7e1da27 | B9: Daniel Adustina | D9: Adustina /BA | E9: =SUMIFS(PedidodeCompra!F:F,PedidodeCompra!D:D,B:B) -> 0 | F9: =SUMIFS(PedidodeCompra!G:G,PedidodeCompra!D:D,B:B) -> 0 | G9: =E9-F9 -> 0
A10: bce7e1da35 | B10: Daniel Alagoas | D10: Batalha/AL | E10: =SUMIFS(PedidodeCompra!F:F,PedidodeCompra!D:D,B:B) -> 0 | F10: =SUMIFS(PedidodeCompra!G:G,PedidodeCompra!D:D,B:B) -> 0 | G10: =E10-F10 -> 0
A11: bce7e1da09 | B11: Diogo Sobral | E11: =SUMIFS(PedidodeCompra!F:F,PedidodeCompra!D:D,B:B) -> 0 | F11: =SUMIFS(PedidodeCompra!G:G,PedidodeCompra!D:D,B:B) -> 0 | G11: =E11-F11 -> 0
A12: bce7e1da30 | B12: Ecinho | E12: =SUMIFS(PedidodeCompra!F:F,PedidodeCompra!D:D,B:B) -> 0 | F12: =SUMIFS(PedidodeCompra!G:G,PedidodeCompra!D:D,B:B) -> 0 | G12: =E12-F12 -> 0
A13: bce7e1da26 | B13: Ednilson Balsas | D13: Balsas/MA | E13: =SUMIFS(PedidodeCompra!F:F,PedidodeCompra!D:D,B:B) -> 0 | F13: =SUMIFS(PedidodeCompra!G:G,PedidodeCompra!D:D,B:B) -> 0 | G13: =E13-F13 -> 0
A14: bce7e1da22 | B14: Eduardo | E14: =SUMIFS(PedidodeCompra!F:F,PedidodeCompra!D:D,B:B) -> 0 | F14: =SUMIFS(PedidodeCompra!G:G,PedidodeCompra!D:D,B:B) -> 0 | G14: =E14-F14 -> 0
A15: bce7e1da59 | B15: Elizeu | E15: =SUMIFS(PedidodeCompra!F:F,PedidodeCompra!D:D,B:B) -> 1507330.4 | F15: =SUMIFS(PedidodeCompra!G:G,PedidodeCompra!D:D,B:B) -> 1507330.4 | G15: =E15-F15 -> -2.3283064e-10
A16: bce7e1da05 | B16: Fabiano Balsas | D16: Balsas/MA | E16: =SUMIFS(PedidodeCompra!F:F,PedidodeCompra!D:D,B:B) -> 1759954.3 | F16: =SUMIFS(PedidodeCompra!G:G,PedidodeCompra!D:D,B:B) -> 1759954.3 | G16: =E16-F16 -> 0
A17: bce7e1da31 | B17: Francisco Benjamin | E17: =SUMIFS(PedidodeCompra!F:F,PedidodeCompra!D:D,B:B) -> 1655732.9 | F17: =SUMIFS(PedidodeCompra!G:G,PedidodeCompra!D:D,B:B) -> 1655732.9 | G17: =E17-F17 -> -2.3283064e-10
A18: bce7e1da25 | B18: Gabriel Balsas | E18: =SUMIFS(PedidodeCompra!F:F,PedidodeCompra!D:D,B:B) -> 0 | F18: =SUMIFS(PedidodeCompra!G:G,PedidodeCompra!D:D,B:B) -> 0 | G18: =E18-F18 -> 0
A19: bce7e1da20 | B19: Gastura | D19: Japoatã/SE | E19: =SUMIFS(PedidodeCompra!F:F,PedidodeCompra!D:D,B:B) -> 140646.44 | F19: =SUMIFS(PedidodeCompra!G:G,PedidodeCompra!D:D,B:B) -> 140646.44 | G19: =E19-F19 -> 0
A20: bce7e1da63 | B20: George | E20: =SUMIFS(PedidodeCompra!F:F,PedidodeCompra!D:D,B:B) -> 217203.5 | F20: =SUMIFS(PedidodeCompra!G:G,PedidodeCompra!D:D,B:B) -> 217203.5 | G20: =E20-F20 -> 0
A21: bce7e1da21 | B21: George Tocantins | E21: =SUMIFS(PedidodeCompra!F:F,PedidodeCompra!D:D,B:B) -> 99054.65 | F21: =SUMIFS(PedidodeCompra!G:G,PedidodeCompra!D:D,B:B) -> 99054.65 | G21: =E21-F21 -> 0
A22: bce7e1da41 | B22: Geraldo Japoata | D22: Japoatã/SE | E22: =SUMIFS(PedidodeCompra!F:F,PedidodeCompra!D:D,B:B) -> 0 | F22: =SUMIFS(PedidodeCompra!G:G,PedidodeCompra!D:D,B:B) -> 0 | G22: =E22-F22 -> 0
A23: bce7e1da14 | B23: Guilherme Balsas | E23: =SUMIFS(PedidodeCompra!F:F,PedidodeCompra!D:D,B:B) -> 2670874.9 | F23: =SUMIFS(PedidodeCompra!G:G,PedidodeCompra!D:D,B:B) -> 2670874.9 | G23: =E23-F23 -> 0
A24: bce7e1da42 | B24: Heder Suporte | D24: Nossa Senhora da Glória/SE | E24: =SUMIFS(PedidodeCompra!F:F,PedidodeCompra!D:D,B:B) -> 0 | F24: =SUMIFS(PedidodeCompra!G:G,PedidodeCompra!D:D,B:B) -> 0 | G24: =E24-F24 -> 0
A25: bce7e1da52 | B25: Jamisson Propria | D25: Própria /SE | E25: =SUMIFS(PedidodeCompra!F:F,PedidodeCompra!D:D,B:B) -> 0 | F25: =SUMIFS(PedidodeCompra!G:G,PedidodeCompra!D:D,B:B) -> 0 | G25: =E25-F25 -> 0
A26: bce7e1da43 | B26: Jr Dede | E26: =SUMIFS(PedidodeCompra!F:F,PedidodeCompra!D:D,B:B) -> 0 | F26: =SUMIFS(PedidodeCompra!G:G,PedidodeCompra!D:D,B:B) -> 0 | G26: =E26-F26 -> 0
A27: bce7e1da11 | B27: Jr Grao | E27: =SUMIFS(PedidodeCompra!F:F,PedidodeCompra!D:D,B:B) -> 958633.62 | F27: =SUMIFS(PedidodeCompra!G:G,PedidodeCompra!D:D,B:B) -> 958633.62 | G27: =E27-F27 -> 0
A28: bce7e1da29 | B28: Kelly Itabaianinha | E28: =SUMIFS(PedidodeCompra!F:F,PedidodeCompra!D:D,B:B) -> 1325394.7 | F28: =SUMIFS(PedidodeCompra!G:G,PedidodeCompra!D:D,B:B) -> 1325394.7 | G28: =E28-F28 -> 0
A29: bce7e1da06 | B29: Lucas Bom Jesus | E29: =SUMIFS(PedidodeCompra!F:F,PedidodeCompra!D:D,B:B) -> 0 | F29: =SUMIFS(PedidodeCompra!G:G,PedidodeCompra!D:D,B:B) -> 0 | G29: =E29-F29 -> 0
A30: bce7e1da03 | B30: Lucas Sobral | D30: Buriticupu/MA | E30: =SUMIFS(PedidodeCompra!F:F,PedidodeCompra!D:D,B:B) -> 3119590.3 | F30: =SUMIFS(PedidodeCompra!G:G,PedidodeCompra!D:D,B:B) -> 2824634.4 | G30: =E30-F30 -> 294955.91
A31: bce7e1da39 | B31: Luiz Eduardo Gordinho | E31: =SUMIFS(PedidodeCompra!F:F,PedidodeCompra!D:D,B:B) -> 0 | F31: =SUMIFS(PedidodeCompra!G:G,PedidodeCompra!D:D,B:B) -> 0 | G31: =E31-F31 -> 0
A32: bce7e1da34 | B32: Luiz Eduardo Magalhaes | E32: =SUMIFS(PedidodeCompra!F:F,PedidodeCompra!D:D,B:B) -> 0 | F32: =SUMIFS(PedidodeCompra!G:G,PedidodeCompra!D:D,B:B) -> 0 | G32: =E32-F32 -> 0
A33: bce7e1da50 | B33: Maicon Faz Capanema | E33: =SUMIFS(PedidodeCompra!F:F,PedidodeCompra!D:D,B:B) -> 0 | F33: =SUMIFS(PedidodeCompra!G:G,PedidodeCompra!D:D,B:B) -> 0 | G33: =E33-F33 -> 0
A34: bce7e1da54 | B34: Maicon Lem | E34: =SUMIFS(PedidodeCompra!F:F,PedidodeCompra!D:D,B:B) -> 0 | F34: =SUMIFS(PedidodeCompra!G:G,PedidodeCompra!D:D,B:B) -> 0 | G34: =E34-F34 -> 0
A35: bce7e1da12 | B35: Marconi Balsas | D35: Balsas /MA | E35: =SUMIFS(PedidodeCompra!F:F,PedidodeCompra!D:D,B:B) -> 3604251.7 | F35: =SUMIFS(PedidodeCompra!G:G,PedidodeCompra!D:D,B:B) -> 3603099.8 | G35: =E35-F35 -> 1151.93
A36: bce7e1da61 | B36: Marcos Roco Graccho | D36: Graccho Cardoso/SE | E36: =SUMIFS(PedidodeCompra!F:F,PedidodeCompra!D:D,B:B) -> 292740.7 | F36: =SUMIFS(PedidodeCompra!G:G,PedidodeCompra!D:D,B:B) -> 292740.7 | G36: =E36-F36 -> 0
A37: bce7e1da48 | B37: Marquinhos | E37: =SUMIFS(PedidodeCompra!F:F,PedidodeCompra!D:D,B:B) -> 272020 | F37: =SUMIFS(PedidodeCompra!G:G,PedidodeCompra!D:D,B:B) -> 272020 | G37: =E37-F37 -> 0
A38: bce7e1da36 | B38: Matheus Vilar | E38: =SUMIFS(PedidodeCompra!F:F,PedidodeCompra!D:D,B:B) -> 0 | F38: =SUMIFS(PedidodeCompra!G:G,PedidodeCompra!D:D,B:B) -> 0 | G38: =E38-F38 -> 0
A39: bce7e1da64 | B39: Mikael | E39: =SUMIFS(PedidodeCompra!F:F,PedidodeCompra!D:D,B:B) -> 0 | F39: =SUMIFS(PedidodeCompra!G:G,PedidodeCompra!D:D,B:B) -> 0 | G39: =E39-F39 -> 0
A40: bce7e1da49 | B40: Milho Conde | D40: Conde/BA | E40: =SUMIFS(PedidodeCompra!F:F,PedidodeCompra!D:D,B:B) -> 675634.35 | F40: =SUMIFS(PedidodeCompra!G:G,PedidodeCompra!D:D,B:B) -> 675634.35 | G40: =E40-F40 -> -1.1641532e-10
A41: bce7e1da19 | B41: Netinho Buriti | E41: =SUMIFS(PedidodeCompra!F:F,PedidodeCompra!D:D,B:B) -> 0 | F41: =SUMIFS(PedidodeCompra!G:G,PedidodeCompra!D:D,B:B) -> 0 | G41: =E41-F41 -> 0
A42: bce7e1da55 | B42: Netinho Maranhao | E42: =SUMIFS(PedidodeCompra!F:F,PedidodeCompra!D:D,B:B) -> 0 | F42: =SUMIFS(PedidodeCompra!G:G,PedidodeCompra!D:D,B:B) -> 0 | G42: =E42-F42 -> 0
A43: bce7e1da65 | B43: Neto Batalha | D43: Batalha/AL | E43: =SUMIFS(PedidodeCompra!F:F,PedidodeCompra!D:D,B:B) -> 0 | F43: =SUMIFS(PedidodeCompra!G:G,PedidodeCompra!D:D,B:B) -> 0 | G43: =E43-F43 -> 0
A44: bce7e1da01 | B44: Newton Porto | D44: Aracaju/SE | E44: =SUMIFS(PedidodeCompra!F:F,PedidodeCompra!D:D,B:B) -> 0 | F44: =SUMIFS(PedidodeCompra!G:G,PedidodeCompra!D:D,B:B) -> 0 | G44: =E44-F44 -> 0
A45: bce7e1da15 | B45: Peterson | E45: =SUMIFS(PedidodeCompra!F:F,PedidodeCompra!D:D,B:B) -> 126724.26 | F45: =SUMIFS(PedidodeCompra!G:G,PedidodeCompra!D:D,B:B) -> 126724.26 | G45: =E45-F45 -> 0
A46: bce7e1da56 | B46: Piaui Faz Tangará | E46: =SUMIFS(PedidodeCompra!F:F,PedidodeCompra!D:D,B:B) -> 0 | F46: =SUMIFS(PedidodeCompra!G:G,PedidodeCompra!D:D,B:B) -> 0 | G46: =E46-F46 -> 0
A47: bce7e1da10 | B47: Ramon | E47: =SUMIFS(PedidodeCompra!F:F,PedidodeCompra!D:D,B:B) -> 469879.32 | F47: =SUMIFS(PedidodeCompra!G:G,PedidodeCompra!D:D,B:B) -> 469879.32 | G47: =E47-F47 -> 0
A48: bce7e1da17 | B48: Reinaldo | E48: =SUMIFS(PedidodeCompra!F:F,PedidodeCompra!D:D,B:B) -> 721774.02 | F48: =SUMIFS(PedidodeCompra!G:G,PedidodeCompra!D:D,B:B) -> 721774.02 | G48: =E48-F48 -> 0
A49: bce7e1da57 | B49: Remisson | D49: Japoatã/SE | E49: =SUMIFS(PedidodeCompra!F:F,PedidodeCompra!D:D,B:B) -> 0 | F49: =SUMIFS(PedidodeCompra!G:G,PedidodeCompra!D:D,B:B) -> 0 | G49: =E49-F49 -> 0
A50: bce7e1da45 | B50: Rodrigo Orlando | E50: =SUMIFS(PedidodeCompra!F:F,PedidodeCompra!D:D,B:B) -> 57777.56 | F50: =SUMIFS(PedidodeCompra!G:G,PedidodeCompra!D:D,B:B) -> 57777.56 | G50: =E50-F50 -> 0
A51: bce7e1da38 | B51: Rodrigo Rocha | E51: =SUMIFS(PedidodeCompra!F:F,PedidodeCompra!D:D,B:B) -> 296991.76 | F51: =SUMIFS(PedidodeCompra!G:G,PedidodeCompra!D:D,B:B) -> 296991.76 | G51: =E51-F51 -> 0
A52: bce7e1da46 | B52: Samuel | E52: =SUMIFS(PedidodeCompra!F:F,PedidodeCompra!D:D,B:B) -> 503515.7 | F52: =SUMIFS(PedidodeCompra!G:G,PedidodeCompra!D:D,B:B) -> 503515.7 | G52: =E52-F52 -> 0
A53: bce7e1da44 | B53: Santa Fe Luis Eduardo | E53: =SUMIFS(PedidodeCompra!F:F,PedidodeCompra!D:D,B:B) -> 0 | F53: =SUMIFS(PedidodeCompra!G:G,PedidodeCompra!D:D,B:B) -> 0 | G53: =E53-F53 -> 0
A54: bce7e1da47 | B54: Saymon | E54: =SUMIFS(PedidodeCompra!F:F,PedidodeCompra!D:D,B:B) -> 0 | F54: =SUMIFS(PedidodeCompra!G:G,PedidodeCompra!D:D,B:B) -> 0 | G54: =E54-F54 -> 0
A55: bce7e1da33 | B55: Tocantins | E55: =SUMIFS(PedidodeCompra!F:F,PedidodeCompra!D:D,B:B) -> 0 | F55: =SUMIFS(PedidodeCompra!G:G,PedidodeCompra!D:D,B:B) -> 0 | G55: =E55-F55 -> 0
A56: bce7e1da16 | B56: Victor Balsas | E56: =SUMIFS(PedidodeCompra!F:F,PedidodeCompra!D:D,B:B) -> 0 | F56: =SUMIFS(PedidodeCompra!G:G,PedidodeCompra!D:D,B:B) -> 0 | G56: =E56-F56 -> 0
A57: bce7e1da28 | B57: Wanderley | E57: =SUMIFS(PedidodeCompra!F:F,PedidodeCompra!D:D,B:B) -> 0 | F57: =SUMIFS(PedidodeCompra!G:G,PedidodeCompra!D:D,B:B) -> 0 | G57: =E57-F57 -> 0
A58: bce7e1da02 | B58: Wendoly Masley | D58: Nossa Senhora da Glória/SE | E58: =SUMIFS(PedidodeCompra!F:F,PedidodeCompra!D:D,B:B) -> 1801003.8 | F58: =SUMIFS(PedidodeCompra!G:G,PedidodeCompra!D:D,B:B) -> 1885104.7 | G58: =E58-F58 -> -84100.9
A59: bce7e1da23 | B59: Ze Antonio Balsas | E59: =SUMIFS(PedidodeCompra!F:F,PedidodeCompra!D:D,B:B) -> 0 | F59: =SUMIFS(PedidodeCompra!G:G,PedidodeCompra!D:D,B:B) -> 0 | G59: =E59-F59 -> 0
A60: 1756b1c5 | B60: Célio | D60: Japoatã/SE | E60: =SUMIFS(PedidodeCompra!F:F,PedidodeCompra!D:D,B:B) -> 0 | F60: =SUMIFS(PedidodeCompra!G:G,PedidodeCompra!D:D,B:B) -> 0 | G60: =E60-F60 -> 0
A61: ea876f42 | B61: Denisson José Andrade de Aragão | D61: Itabi/SE | E61: =SUMIFS(PedidodeCompra!F:F,PedidodeCompra!D:D,B:B) -> 0 | F61: =SUMIFS(PedidodeCompra!G:G,PedidodeCompra!D:D,B:B) -> 0 | G61: =E61-F61 -> 0
A62: 71c6ae3c | B62: Eudas | D62: Siriri/SE | E62: =SUMIFS(PedidodeCompra!F:F,PedidodeCompra!D:D,B:B) -> 305564.32 | F62: =SUMIFS(PedidodeCompra!G:G,PedidodeCompra!D:D,B:B) -> 305564.32 | G62: =E62-F62 -> 0
A63: 1061c3ed | B63: Clair Feira Nova | D63: Feira Nova/SE | E63: =SUMIFS(PedidodeCompra!F:F,PedidodeCompra!D:D,B:B) -> 12478.5 | F63: =SUMIFS(PedidodeCompra!G:G,PedidodeCompra!D:D,B:B) -> 12478.5 | G63: =E63-F63 -> 0
A64: d14ce0ec | B64: Gabriel Balsas/Irineu | D64: Balsas/MA | E64: =SUMIFS(PedidodeCompra!F:F,PedidodeCompra!D:D,B:B) -> 1577953.2 | F64: =SUMIFS(PedidodeCompra!G:G,PedidodeCompra!D:D,B:B) -> 1704403.2 | G64: =E64-F64 -> -126450
A65: 30899286 | B65: Gabriel Balsas - Gilmar | D65: Balsas/MA | E65: 0 | F65: 0 | G65: 0
A66: c81637cd | B66: José Nunes | D66: Aracaju/SE | E66: =SUMIFS(PedidodeCompra!F:F,PedidodeCompra!D:D,B:B) -> 376398.23 | F66: =SUMIFS(PedidodeCompra!G:G,PedidodeCompra!D:D,B:B) -> 376398.23 | G66: =E66-F66 -> 0
A67: 69bde65d | B67: Abrel | D67: Não Informado/SE | E67: =SUMIFS(PedidodeCompra!F:F,PedidodeCompra!D:D,B:B) -> 56886.9 | F67: =SUMIFS(PedidodeCompra!G:G,PedidodeCompra!D:D,B:B) -> 56886.9 | G67: =E67-F67 -> 0
A68: a5797d68 | B68: Edenilson Balsas | D68: Balsas/MA | E68: =SUMIFS(PedidodeCompra!F:F,PedidodeCompra!D:D,B:B) -> 799929.4 | F68: =SUMIFS(PedidodeCompra!G:G,PedidodeCompra!D:D,B:B) -> 799929.4 | G68: =E68-F68 -> -1.1641532e-10
A69: 37984646 | B69: Lucas LEM | D69: Não Informado/PE | E69: =SUMIFS(PedidodeCompra!F:F,PedidodeCompra!D:D,B:B) -> 47291.04 | F69: =SUMIFS(PedidodeCompra!G:G,PedidodeCompra!D:D,B:B) -> 47291.04 | G69: =E69-F69 -> 0
A70: e7d2b0aa | B70: Ze de Gerino | D70: Não Informado/SE | E70: =SUMIFS(PedidodeCompra!F:F,PedidodeCompra!D:D,B:B) -> 763594.44 | F70: =SUMIFS(PedidodeCompra!G:G,PedidodeCompra!D:D,B:B) -> 763594.44 | G70: =E70-F70 -> 0
A71: b8f1d887 | B71: Thiago Feira Nova | D71: Feira Nova/SE | E71: =SUMIFS(PedidodeCompra!F:F,PedidodeCompra!D:D,B:B) -> 816873.12 | F71: =SUMIFS(PedidodeCompra!G:G,PedidodeCompra!D:D,B:B) -> 816873.12 | G71: =E71-F71 -> -1.1641532e-10
A72: e9f2714b | B72: Carlinhos | D72: Não Informado/SE | E72: =SUMIFS(PedidodeCompra!F:F,PedidodeCompra!D:D,B:B) -> 1119077.8 | F72: =SUMIFS(PedidodeCompra!G:G,PedidodeCompra!D:D,B:B) -> 1119077.8 | G72: =E72-F72 -> 0
A73: e8cfc701 | B73: Gabriel Balsas - Pedro | D73: Balsas/MA | E73: =SUMIFS(PedidodeCompra!F:F,PedidodeCompra!D:D,B:B) -> 151510.51 | F73: =SUMIFS(PedidodeCompra!G:G,PedidodeCompra!D:D,B:B) -> 151510.51 | G73: =E73-F73 -> 0
A74: 4a2dc53a | B74: Comprovante de 4.895,00 | D74: Não Informado/SE | E74: =SUMIFS(PedidodeCompra!F:F,PedidodeCompra!D:D,B:B) -> 0 | F74: =SUMIFS(PedidodeCompra!G:G,PedidodeCompra!D:D,B:B) -> 0 | G74: =E74-F74 -> 0
A75: 32a848dc | B75: Elizabete | D75: Não Informado/SE | E75: =SUMIFS(PedidodeCompra!F:F,PedidodeCompra!D:D,B:B) -> 725656.77 | F75: =SUMIFS(PedidodeCompra!G:G,PedidodeCompra!D:D,B:B) -> 725656.77 | G75: =E75-F75 -> 0
A76: 74088c4f | B76: Gabriel Melo - Itabi | D76: Itabi/SE | E76: =SUMIFS(PedidodeCompra!F:F,PedidodeCompra!D:D,B:B) -> 841994.01 | F76: =SUMIFS(PedidodeCompra!G:G,PedidodeCompra!D:D,B:B) -> 841994.01 | G76: =E76-F76 -> -1.1641532e-10
A77: fea46c1c | B77: Alex Carira | D77: Carira/SE | E77: =SUMIFS(PedidodeCompra!F:F,PedidodeCompra!D:D,B:B) -> 355903.1 | F77: =SUMIFS(PedidodeCompra!G:G,PedidodeCompra!D:D,B:B) -> 355903.1 | G77: =E77-F77 -> 0
... A198: 3f0e7d00 | B198: Laerte Itabi | D198: Itabi/SE | E198: =SUMIFS(PedidodeCompra!F:F,PedidodeCompra!D:D,B:B) -> 697440.96 | F198: =SUMIFS(PedidodeCompra!G:G,PedidodeCompra!D:D,B:B) -> 697440.96 | G198: =E198-F198 -> 0
A199: 90af616f | B199: Alexandre Frei Paulo | E199: =SUMIFS(PedidodeCompra!F:F,PedidodeCompra!D:D,B:B) -> 190128.24 | F199: =SUMIFS(PedidodeCompra!G:G,PedidodeCompra!D:D,B:B) -> 190128.24 | G199: =E199-F199 -> 0
A200: 30bb6bd7 | B200: João LEM | D200: Balsas/MA | E200: =SUMIFS(PedidodeCompra!F:F,PedidodeCompra!D:D,B:B) -> 1601004 | F200: =SUMIFS(PedidodeCompra!G:G,PedidodeCompra!D:D,B:B) -> 1601668.4 | G200: =E200-F200 -> -664.35
A201: 8ba2c477 | B201: Ze Neto | D201: Não Informado/SE | E201: =SUMIFS(PedidodeCompra!F:F,PedidodeCompra!D:D,B:B) -> 256583.52 | F201: =SUMIFS(PedidodeCompra!G:G,PedidodeCompra!D:D,B:B) -> 256583.52 | G201: =E201-F201 -> 0
A202: 3a8d6b4d | B202: TESTE | D202: Não Informado/SE | E202: =SUMIFS(PedidodeCompra!F:F,PedidodeCompra!D:D,B:B) -> 0 | F202: =SUMIFS(PedidodeCompra!G:G,PedidodeCompra!D:D,B:B) -> 0 | G202: =E202-F202 -> 0
A203: 40fea146 | B203: Tiago São Mateus | D203: Não Informado/SE | E203: =SUMIFS(PedidodeCompra!F:F,PedidodeCompra!D:D,B:B) -> 237792.24 | F203: =SUMIFS(PedidodeCompra!G:G,PedidodeCompra!D:D,B:B) -> 237792.24 | G203: =E203-F203 -> 0
A204: 5b8befc4 | B204: Marconi Alto Parnaíba | D204: Não Informado/MA | E204: =SUMIFS(PedidodeCompra!F:F,PedidodeCompra!D:D,B:B) -> 164677.48 | F204: =SUMIFS(PedidodeCompra!G:G,PedidodeCompra!D:D,B:B) -> 164677.48 | G204: =E204-F204 -> 0
A205: 878f0a18 | B205: Cerrado Grãos | D205: Não Informado/MA | E205: =SUMIFS(PedidodeCompra!F:F,PedidodeCompra!D:D,B:B) -> 214532.52 | F205: =SUMIFS(PedidodeCompra!G:G,PedidodeCompra!D:D,B:B) -> 214532.52 | G205: =E205-F205 -> 0
A206: 6eeae50e | B206: Gabriel Carira | D206: Carira/SE | E206: =SUMIFS(PedidodeCompra!F:F,PedidodeCompra!D:D,B:B) -> 623918.42 | F206: =SUMIFS(PedidodeCompra!G:G,PedidodeCompra!D:D,B:B) -> 623918.42 | G206: =E206-F206 -> 0
A207: 18defaa6 | B207: Wendoly Amaral | D207: Não Informado/SE | E207: =SUMIFS(PedidodeCompra!F:F,PedidodeCompra!D:D,B:B) -> 256783.1 | F207: =SUMIFS(PedidodeCompra!G:G,PedidodeCompra!D:D,B:B) -> 256783.1 | G207: =E207-F207 -> 0
A208: 2a9b5ed7 | B208: Marconi Piaui | D208: Não Informado/PI | E208: =SUMIFS(PedidodeCompra!F:F,PedidodeCompra!D:D,B:B) -> 82289.62 | F208: =SUMIFS(PedidodeCompra!G:G,PedidodeCompra!D:D,B:B) -> 82289.62 | G208: =E208-F208 -> 0
A209: ba6b7e2d | B209: Eudas Cumbe | D209: Cumbe/SE | E209: =SUMIFS(PedidodeCompra!F:F,PedidodeCompra!D:D,B:B) -> 291456 | F209: =SUMIFS(PedidodeCompra!G:G,PedidodeCompra!D:D,B:B) -> 291456 | G209: =E209-F209 -> 0
A210: 8137cb64 | B210: Felipe Bosco | D210: Não Informado/SE | E210: =SUMIFS(PedidodeCompra!F:F,PedidodeCompra!D:D,B:B) -> 329035.95 | F210: =SUMIFS(PedidodeCompra!G:G,PedidodeCompra!D:D,B:B) -> 329035.95 | G210: =E210-F210 -> 0
A211: a8dd20c7 | B211: Felipe André | D211: Não Informado/SE | E211: =SUMIFS(PedidodeCompra!F:F,PedidodeCompra!D:D,B:B) -> 573474.7 | F211: =SUMIFS(PedidodeCompra!G:G,PedidodeCompra!D:D,B:B) -> 573474.7 | G211: =E211-F211 -> 0
... A213: b7e6278b | B213: DIno Lem | D213: Luis Eduardo Magalhães/BA | E213: =SUMIFS(PedidodeCompra!F:F,PedidodeCompra!D:D,B:B) -> 278207.46 | F213: =SUMIFS(PedidodeCompra!G:G,PedidodeCompra!D:D,B:B) -> 278207.46 | G213: =E213-F213 -> 0

Sheet PedidodeCompra
A1: id | B1: Data | C1: NPedidoCompra | D1: Produtor | E1: CPF-CNPJ | F1: Valor Total | G1: Valor Pago | H1: Valor Pendente | I1: Safra | J1: Status | K1: Cidade | L1: MesAno | M1: PedCxMensal | N1: Gatilho | O1: Anotações
A2: b6a01109 | B2: 45674 | C2: 1701251261 | D2: Abrel | E2: Ronaldo Silva | F2: =SUMIFS(PedComCarrinho!E:E,PedComCarrinho!G:G,C:C) -> 56886.9 | G2: =SUMIFS(PagProdutor!F:F,PagProdutor!D:D,C:C)+(SUMIFS(PagComisao!F:F,PagComisao!K:K,C:C)) -> 56886.9 | H2: =F2-G2 -> 0 | I2: Safra Sergipe - 2025 | J2: Finalizado | K2: Não Informado/SE | L2: =TEXT(B2,"MM/YYYY") -> 01/2025 | M2: =IF(B2="","",CONCATENATE("CXG-",TEXT(B2,"MMYY"))) -> CXG-0125
A3: fcc79007 | B3: 45707 | C3: 1902252793 | D3: Alex Carira | E3: Newton Porto | F3: =SUMIFS(PedComCarrinho!E:E,PedComCarrinho!G:G,C:C) -> 355903.1 | G3: =SUMIFS(PagProdutor!F:F,PagProdutor!D:D,C:C)+(SUMIFS(PagComisao!F:F,PagComisao!K:K,C:C)) -> 355903.1 | H3: =F3-G3 -> 0 | I3: Safra Sergipe - 2025 | J3: Finalizado | K3: Carira/SE | L3: =TEXT(B3,"MM/YYYY") -> 02/2025 | M3: =IF(B3="","",CONCATENATE("CXG-",TEXT(B3,"MMYY"))) -> CXG-0225 | N3: 45755.371
A4: 1cce1744 | B4: 45729 | C4: 130325400 | D4: Anne Carira | E4: Ronaldo Silva | F4: =SUMIFS(PedComCarrinho!E:E,PedComCarrinho!G:G,C:C) -> 192693.6 | G4: =SUMIFS(PagProdutor!F:F,PagProdutor!D:D,C:C)+(SUMIFS(PagComisao!F:F,PagComisao!K:K,C:C)) -> 192693.6 | H4: =F4-G4 -> 0 | I4: Safra Sergipe - 2025 | J4: Finalizado | K4: Carira/SE | L4: =TEXT(B4,"MM/YYYY") -> 03/2025 | M4: =IF(B4="","",CONCATENATE("CXG-",TEXT(B4,"MMYY"))) -> CXG-0325 | N4: 45734.484
A5: 444dfa3a | B5: 45727 | C5: 1103253731 | D5: Bira do Queijo/Gararu | E5: Newton Porto | F5: =SUMIFS(PedComCarrinho!E:E,PedComCarrinho!G:G,C:C) -> 1034643.8 | G5: =SUMIFS(PagProdutor!F:F,PagProdutor!D:D,C:C)+(SUMIFS(PagComisao!F:F,PagComisao!K:K,C:C)) -> 1034643.8 | H5: =F5-G5 -> 0 | I5: Safra Sergipe - 2025 | J5: Finalizado | K5: Gararu/SE | L5: =TEXT(B5,"MM/YYYY") -> 03/2025 | M5: =IF(B5="","",CONCATENATE("CXG-",TEXT(B5,"MMYY"))) -> CXG-0325 | N5: 45826.811 | O5: 12.000 Sacos
A6: 82cd9bd4 | B6: 45794 | C6: 190525564 | D6: Bruna Piauí | E6: Ronaldo Silva | F6: =SUMIFS(PedComCarrinho!E:E,PedComCarrinho!G:G,C:C) -> 233793.78 | G6: =SUMIFS(PagProdutor!F:F,PagProdutor!D:D,C:C)+(SUMIFS(PagComisao!F:F,PagComisao!K:K,C:C)) -> 233793.78 | H6: =F6-G6 -> 0 | I6: Safra Maranhão - 2025 | J6: Finalizado | K6: Não Informado/PI | L6: =TEXT(B6,"MM/YYYY") -> 05/2025 | M6: =IF(B6="","",CONCATENATE("CXG-",TEXT(B6,"MMYY"))) -> CXG-0525
A7: a015525b | B7: 45691 | C7: 0302252193 | D7: Carlinhos | E7: Newton Porto | F7: =SUMIFS(PedComCarrinho!E:E,PedComCarrinho!G:G,C:C) -> 576400.01 | G7: =SUMIFS(PagProdutor!F:F,PagProdutor!D:D,C:C)+(SUMIFS(PagComisao!F:F,PagComisao!K:K,C:C)) -> 576400.01 | H7: =F7-G7 -> 0 | I7: Safra Sergipe - 2025 | J7: Finalizado | K7: Não Informado/SE | L7: =TEXT(B7,"MM/YYYY") -> 02/2025 | M7: =IF(B7="","",CONCATENATE("CXG-",TEXT(B7,"MMYY"))) -> CXG-0225 | N7: 45762.411
A8: fbf2f6b3 | B8: 45748 | C8: 0104254984 | D8: Cicero | E8: Ronaldo Silva | F8: =SUMIFS(PedComCarrinho!E:E,PedComCarrinho!G:G,C:C) -> 640390 | G8: =SUMIFS(PagProdutor!F:F,PagProdutor!D:D,C:C)+(SUMIFS(PagComisao!F:F,PagComisao!K:K,C:C)) -> 640390 | H8: =F8-G8 -> 0 | I8: Safra Sergipe - 2025 | J8: Finalizado | K8: Monte Alegre Sergipe/SE | L8: =TEXT(B8,"MM/YYYY") -> 04/2025 | M8: =IF(B8="","",CONCATENATE("CXG-",TEXT(B8,"MMYY"))) -> CXG-0425 | N8: 45764.57
A9: 2eb078ac | B9: 45673 | C9: 160125555 | D9: Clair Feira Nova | E9: Ronaldo Silva | F9: =SUMIFS(PedComCarrinho!E:E,PedComCarrinho!G:G,C:C) -> 12478.5 | G9: =SUMIFS(PagProdutor!F:F,PagProdutor!D:D,C:C)+(SUMIFS(PagComisao!F:F,PagComisao!K:K,C:C)) -> 12478.5 | H9: =F9-G9 -> 0 | I9: Safra Sergipe - 2025 | J9: Finalizado | K9: Feira Nova/SE | L9: =TEXT(B9,"MM/YYYY") -> 01/2025 | M9: =IF(B9="","",CONCATENATE("CXG-",TEXT(B9,"MMYY"))) -> CXG-0125
A10: fc815116 | B10: 45699 | C10: 1102252310 | D10: Comprovante de 4.895,00 | E10: Ronaldo Silva | F10: =SUMIFS(PedComCarrinho!E:E,PedComCarrinho!G:G,C:C) -> 0 | G10: =SUMIFS(PagProdutor!F:F,PagProdutor!D:D,C:C)+(SUMIFS(PagComisao!F:F,PagComisao!K:K,C:C)) -> 0 | H10: =F10-G10 -> 0 | I10: Safra Sergipe - 2025 | J10: Finalizado | K10: Não Informado/SE | L10: =TEXT(B10,"MM/YYYY") -> 02/2025 | M10: =IF(B10="","",CONCATENATE("CXG-",TEXT(B10,"MMYY"))) -> CXG-0225
A11: 92fc0d7b | B11: 45675 | C11: 200125137 | D11: Edenilson Balsas | E11: Ronaldo Silva | F11: =SUMIFS(PedComCarrinho!E:E,PedComCarrinho!G:G,C:C) -> 230806.63 | G11: =SUMIFS(PagProdutor!F:F,PagProdutor!D:D,C:C)+(SUMIFS(PagComisao!F:F,PagComisao!K:K,C:C)) -> 230806.63 | H11: =F11-G11 -> 0 | I11: Safra Maranhão - 2025 | J11: Finalizado | K11: Balsas/MA | L11: =TEXT(B11,"MM/YYYY") -> 01/2025 | M11: =IF(B11="","",CONCATENATE("CXG-",TEXT(B11,"MMYY"))) -> CXG-0125
A12: 55529feb | B12: 45699 | C12: 1102252412 | D12: Elizabete | E12: Ronaldo Silva | F12: =SUMIFS(PedComCarrinho!E:E,PedComCarrinho!G:G,C:C) -> 193875.89 | G12: =SUMIFS(PagProdutor!F:F,PagProdutor!D:D,C:C)+(SUMIFS(PagComisao!F:F,PagComisao!K:K,C:C)) -> 193875.89 | H12: =F12-G12 -> 0 | I12: Safra Sergipe - 2025 | J12: Finalizado | K12: Não Informado/SE | L12: =TEXT(B12,"MM/YYYY") -> 02/2025 | M12: =IF(B12="","",CONCATENATE("CXG-",TEXT(B12,"MMYY"))) -> CXG-0225
A13: 0b5370b8 | B13: 45721 | C13: 0503253270 | D13: Elizeu | E13: Newton Porto | F13: =SUMIFS(PedComCarrinho!E:E,PedComCarrinho!G:G,C:C) -> 1507330.4 | G13: =SUMIFS(PagProdutor!F:F,PagProdutor!D:D,C:C)+(SUMIFS(PagComisao!F:F,PagComisao!K:K,C:C)) -> 1507330.4 | H13: =F13-G13 -> -2.3283064e-10 | I13: Safra Sergipe - 2025 | J13: Finalizado | K13: Não Informado/SE | L13: =TEXT(B13,"MM/YYYY") -> 03/2025 | M13: =IF(B13="","",CONCATENATE("CXG-",TEXT(B13,"MMYY"))) -> CXG-0325 | N13: 45727.623
A14: 48c3969e | B14: 45666 | C14: 150125254 | D14: Eudas | E14: Ronaldo Silva | F14: =SUMIFS(PedComCarrinho!E:E,PedComCarrinho!G:G,C:C) -> 305564.32 | G14: =SUMIFS(PagProdutor!F:F,PagProdutor!D:D,C:C)+(SUMIFS(PagComisao!F:F,PagComisao!K:K,C:C)) -> 305564.32 | H14: =F14-G14 -> 0 | I14: Safra Sergipe - 2025 | J14: Finalizado | K14: Siriri/SE | L14: =TEXT(B14,"MM/YYYY") -> 01/2025 | M14: =IF(B14="","",CONCATENATE("CXG-",TEXT(B14,"MMYY"))) -> CXG-0125 | N14: 45673.676
A15: 7c523a62 | B15: 45666 | C15: 160125346 | D15: Francisco Benjamin | E15: Ronaldo Silva | F15: =SUMIFS(PedComCarrinho!E:E,PedComCarrinho!G:G,C:C) -> 82041 | G15: =SUMIFS(PagProdutor!F:F,PagProdutor!D:D,C:C)+(SUMIFS(PagComisao!F:F,PagComisao!K:K,C:C)) -> 82041 | H15: =F15-G15 -> 0 | I15: Safra Sergipe - 2025 | J15: Finalizado | K15: Cristinapolis/SE | L15: =TEXT(B15,"MM/YYYY") -> 01/2025 | M15: =IF(B15="","",CONCATENATE("CXG-",TEXT(B15,"MMYY"))) -> CXG-0125 | N15: 45961.543
A16: 2f2fb276 | B16: 45673 | C16: 160125786 | D16: Gabriel Balsas - Gilmar | E16: Ronaldo Silva | F16: =SUMIFS(PedComCarrinho!E:E,PedComCarrinho!G:G,C:C) -> 133336.38 | G16: =SUMIFS(PagProdutor!F:F,PagProdutor!D:D,C:C)+(SUMIFS(PagComisao!F:F,PagComisao!K:K,C:C)) -> 133336.38 | H16: =F16-G16 -> 0 | I16: Safra Maranhão - 2025 | J16: Finalizado | K16: Balsas/MA | L16: =TEXT(B16,"MM/YYYY") -> 01/2025 | M16: =IF(B16="","",CONCATENATE("CXG-",TEXT(B16,"MMYY"))) -> CXG-0125 | N16: 45674.656
A17: 5b5451b5 | B17: 45674 | C17: 1701251075 | D17: Gabriel Balsas - Gilmar | E17: Newton Porto | F17: =SUMIFS(PedComCarrinho!E:E,PedComCarrinho!G:G,C:C) -> 629607.08 | G17: =SUMIFS(PagProdutor!F:F,PagProdutor!D:D,C:C)+(SUMIFS(PagComisao!F:F,PagComisao!K:K,C:C)) -> 629607.08 | H17: =F17-G17 -> 0 | I17: Safra Maranhão - 2025 | J17: Finalizado | K17: Balsas/MA | L17: =TEXT(B17,"MM/YYYY") -> 01/2025 | M17: =IF(B17="","",CONCATENATE("CXG-",TEXT(B17,"MMYY"))) -> CXG-0125 | N17: 45675.308 | O17: 15.000 Sc
A18: a7a959b1 | B18: 45726 | C18: 1003253515 | D18: Gabriel Balsas - Gilmar | E18: Newton Porto | F18: =SUMIFS(PedComCarrinho!E:E,PedComCarrinho!G:G,C:C) -> 694392.08 | G18: =SUMIFS(PagProdutor!F:F,PagProdutor!D:D,C:C)+(SUMIFS(PagComisao!F:F,PagComisao!K:K,C:C)) -> 694392.08 | H18: =F18-G18 -> 1.1641532e-10 | I18: Safra Maranhão - 2025 | J18: Finalizado | K18: Balsas/MA | L18: =TEXT(B18,"MM/YYYY") -> 03/2025 | M18: =IF(B18="","",CONCATENATE("CXG-",TEXT(B18,"MMYY"))) -> CXG-0325 | N18: 45733.796 | O18: 5.000 Sacos
A19: 43fe61fc | B19: 45693 | C19: 0502252287 | D19: Gabriel Balsas - Pedro | E19: Newton Porto | F19: =SUMIFS(PedComCarrinho!E:E,PedComCarrinho!G:G,C:C) -> 151510.51 | G19: =SUMIFS(PagProdutor!F:F,PagProdutor!D:D,C:C)+(SUMIFS(PagComisao!F:F,PagComisao!K:K,C:C)) -> 151510.51 | H19: =F19-G19 -> 0 | I19: Safra Maranhão - 2025 | J19: Finalizado | K19: Balsas/MA | L19: =TEXT(B19,"MM/YYYY") -> 02/2025 | M19: =IF(B19="","",CONCATENATE("CXG-",TEXT(B19,"MMYY"))) -> CXG-0225
A20: 7c5f3047 | B20: 45674 | C20: 170125830 | D20: Gabriel Balsas/Irineu | E20: Newton Porto | F20: =SUMIFS(PedComCarrinho!E:E,PedComCarrinho!G:G,C:C) -> 310557.12 | G20: =SUMIFS(PagProdutor!F:F,PagProdutor!D:D,C:C)+(SUMIFS(PagComisao!F:F,PagComisao!K:K,C:C)) -> 310557.12 | H20: =F20-G20 -> 0 | I20: Safra Maranhão - 2025 | J20: Finalizado | K20: Balsas/MA | L20: =TEXT(B20,"MM/YYYY") -> 01/2025 | M20: =IF(B20="","",CONCATENATE("CXG-",TEXT(B20,"MMYY"))) -> CXG-0125 | N20: 46034.432
A21: de87a851 | B21: 45677 | C21: 2001251462 | D21: Gabriel Balsas/Irineu | E21: Newton Porto | F21: =SUMIFS(PedComCarrinho!E:E,PedComCarrinho!G:G,C:C) -> 818752.95 | G21: =SUMIFS(PagProdutor!F:F,PagProdutor!D:D,C:C)+(SUMIFS(PagComisao!F:F,PagComisao!K:K,C:C)) -> 818752.95 | H21: =F21-G21 -> 0 | I21: Safra Maranhão - 2025 | J21: Finalizado | K21: Balsas/MA | L21: =TEXT(B21,"MM/YYYY") -> 01/2025 | M21: =IF(B21="","",CONCATENATE("CXG-",TEXT(B21,"MMYY"))) -> CXG-0125 | N21: 46034.432 | O21: 8.000 Sc
A22: 5ecd11a7 | B22: 45726 | C22: 1003253656 | D22: Gabriel Balsas/Irineu | E22: Newton Porto | F22: =SUMIFS(PedComCarrinho!E:E,PedComCarrinho!G:G,C:C) -> 448643.13 | G22: =SUMIFS(PagProdutor!F:F,PagProdutor!D:D,C:C)+(SUMIFS(PagComisao!F:F,PagComisao!K:K,C:C)) -> 448643.13 | H22: =F22-G22 -> 0 | I22: Safra Maranhão - 2025 | J22: Finalizado | K22: Balsas/MA | L22: =TEXT(B22,"MM/YYYY") -> 03/2025 | M22: =IF(B22="","",CONCATENATE("CXG-",TEXT(B22,"MMYY"))) -> CXG-0325 | N22: 46034.432
A23: bac4eaba | B23: 45751 | C23: 0404255072 | D23: Gabriel Balsas/Irineu | E23: Newton Porto | F23: =SUMIFS(PedComCarrinho!E:E,PedComCarrinho!G:G,C:C) -> 0 | G23: =SUMIFS(PagProdutor!F:F,PagProdutor!D:D,C:C)+(SUMIFS(PagComisao!F:F,PagComisao!K:K,C:C)) -> 126450 | H23: =F23-G23 -> -126450 | I23: Safra Maranhão - 2025 | J23: Finalizado | K23: Balsas/MA | L23: =TEXT(B23,"MM/YYYY") -> 04/2025 | M23: =IF(B23="","",CONCATENATE("CXG-",TEXT(B23,"MMYY"))) -> CXG-0425 | N23: 46034.432
A24: fc66466c | B24: 45799 | C24: 2205255791 | D24: Gabriel Balsas/Marcos | E24: Newton Porto | F24: =SUMIFS(PedComCarrinho!E:E,PedComCarrinho!G:G,C:C) -> 451381.76 | G24: =SUMIFS(PagProdutor!F:F,PagProdutor!D:D,C:C)+(SUMIFS(PagComisao!F:F,PagComisao!K:K,C:C)) -> 451381.76 | H24: =F24-G24 -> 0 | I24: Safra Maranhão - 2025 | J24: Finalizado | K24: Balsas/MA | L24: =TEXT(B24,"MM/YYYY") -> 05/2025 | M24: =IF(B24="","",CONCATENATE("CXG-",TEXT(B24,"MMYY"))) -> CXG-0525 | N24: 45805.449
A25: a57010c7 | B25: 45702 | C25: 140225260 | D25: Gabriel Melo - Itabi | E25: Ronaldo Silva | F25: =SUMIFS(PedComCarrinho!E:E,PedComCarrinho!G:G,C:C) -> 302174.46 | G25: =SUMIFS(PagProdutor!F:F,PagProdutor!D:D,C:C)+(SUMIFS(PagComisao!F:F,PagComisao!K:K,C:C)) -> 302174.46 | H25: =F25-G25 -> 0 | I25: Safra Sergipe - 2025 | J25: Finalizado | K25: Itabi/SE | L25: =TEXT(B25,"MM/YYYY") -> 02/2025 | M25: =IF(B25="","",CONCATENATE("CXG-",TEXT(B25,"MMYY"))) -> CXG-0225
A26: dbf9c9ce | B26: 45724 | C26: 0803253478 | D26: George | E26: Newton Porto | F26: =SUMIFS(PedComCarrinho!E:E,PedComCarrinho!G:G,C:C) -> 134313.5 | G26: =SUMIFS(PagProdutor!F:F,PagProdutor!D:D,C:C)+(SUMIFS(PagComisao!F:F,PagComisao!K:K,C:C)) -> 134313.5 | H26: =F26-G26 -> 0 | I26: Safra Sergipe - 2025 | J26: Finalizado | K26: Não Informado/SE | L26: =TEXT(B26,"MM/YYYY") -> 03/2025 | M26: =IF(B26="","",CONCATENATE("CXG-",TEXT(B26,"MMYY"))) -> CXG-0325
A27: eae571f7 | B27: 45682 | C27: 2501251862 | D27: George Tocantins | E27: Newton Porto | F27: =SUMIFS(PedComCarrinho!E:E,PedComCarrinho!G:G,C:C) -> 99054.65 | G27: =SUMIFS(PagProdutor!F:F,PagProdutor!D:D,C:C)+(SUMIFS(PagComisao!F:F,PagComisao!K:K,C:C)) -> 99054.65 | H27: =F27-G27 -> 0 | I27: Safra Tocantins - 2025 | J27: Finalizado | K27: Não informado/TO | L27: =TEXT(B27,"MM/YYYY") -> 01/2025 | M27: =IF(B27="","",CONCATENATE("CXG-",TEXT(B27,"MMYY"))) -> CXG-0125
A28: 78fd0117 | B28: 45701 | C28: 1302252597 | D28: Guilherme Balsas | E28: Newton Porto | F28: =SUMIFS(PedComCarrinho!E:E,PedComCarrinho!G:G,C:C) -> 478599.91 | G28: =SUMIFS(PagProdutor!F:F,PagProdutor!D:D,C:C)+(SUMIFS(PagComisao!F:F,PagComisao!K:K,C:C)) -> 478599.91 | H28: =F28-G28 -> -1.1641532e-10 | I28: Safra Maranhão - 2025 | J28: Finalizado | K28: Balsas/MA | L28: =TEXT(B28,"MM/YYYY") -> 02/2025 | M28: =IF(B28="","",CONCATENATE("CXG-",TEXT(B28,"MMYY"))) -> CXG-0225 | N28: 45840.713
A29: b95fcfbc | B29: 45717 | C29: 0103253196 | D29: Guilherme Balsas | E29: Newton Porto | F29: =SUMIFS(PedComCarrinho!E:E,PedComCarrinho!G:G,C:C) -> 154684.23 | G29: =SUMIFS(PagProdutor!F:F,PagProdutor!D:D,C:C)+(SUMIFS(PagComisao!F:F,PagComisao!K:K,C:C)) -> 154684.23 | H29: =F29-G29 -> 0 | I29: Safra Maranhão - 2025 | J29: Finalizado | K29: Balsas/MA | L29: =TEXT(B29,"MM/YYYY") -> 03/2025 | M29: =IF(B29="","",CONCATENATE("CXG-",TEXT(B29,"MMYY"))) -> CXG-0325 | N29: 45840.713
A30: 9b2f2c55 | B30: 45745 | C30: 2903254715 | D30: Guilherme Balsas | E30: Newton Porto | F30: =SUMIFS(PedComCarrinho!E:E,PedComCarrinho!G:G,C:C) -> 158917.61 | G30: =SUMIFS(PagProdutor!F:F,PagProdutor!D:D,C:C)+(SUMIFS(PagComisao!F:F,PagComisao!K:K,C:C)) -> 158917.61 | H30: =F30-G30 -> 0 | I30: Safra Maranhão - 2025 | J30: Finalizado | K30: Balsas/MA | L30: =TEXT(B30,"MM/YYYY") -> 03/2025 | M30: =IF(B30="","",CONCATENATE("CXG-",TEXT(B30,"MMYY"))) -> CXG-0325 | N30: 45840.713
A31: 6287be31 | B31: 45789 | C31: 1205255544 | D31: Guilherme Balsas | E31: Newton Porto | F31: =SUMIFS(PedComCarrinho!E:E,PedComCarrinho!G:G,C:C) -> 1120061.9 | G31: =SUMIFS(PagProdutor!F:F,PagProdutor!D:D,C:C)+(SUMIFS(PagComisao!F:F,PagComisao!K:K,C:C)) -> 1120061.9 | H31: =F31-G31 -> -4.6566129e-10 | I31: Safra Maranhão - 2025 | J31: Finalizado | K31: Balsas/MA | L31: =TEXT(B31,"MM/YYYY") -> 05/2025 | M31: =IF(B31="","",CONCATENATE("CXG-",TEXT(B31,"MMYY"))) -> CXG-0525 | N31: 45840.713
A32: 28831be7 | B32: 45782 | C32: 0505255299 | D32: Guilherme Piaui | E32: Newton Porto | F32: =SUMIFS(PedComCarrinho!E:E,PedComCarrinho!G:G,C:C) -> 656990.37 | G32: =SUMIFS(PagProdutor!F:F,PagProdutor!D:D,C:C)+(SUMIFS(PagComisao!F:F,PagComisao!K:K,C:C)) -> 656990.37 | H32: =F32-G32 -> -1.1641532e-10 | I32: Safra Maranhão - 2025 | J32: Finalizado | K32: São Francisco Do Piaui/PI | L32: =TEXT(B32,"MM/YYYY") -> 05/2025 | M32: =IF(B32="","",CONCATENATE("CXG-",TEXT(B32,"MMYY"))) -> CXG-0525 | N32: 45840.713
A33: 1a889c5c | B33: 45727 | C33: 1103253994 | D33: Jair | E33: Newton Porto | F33: =SUMIFS(PedComCarrinho!E:E,PedComCarrinho!G:G,C:C) -> 1209652 | G33: =SUMIFS(PagProdutor!F:F,PagProdutor!D:D,C:C)+(SUMIFS(PagComisao!F:F,PagComisao!K:K,C:C)) -> 1209652 | H33: =F33-G33 -> 0 | I33: Safra Sergipe - 2025 | J33: Finalizado | K33: Não Informado/SE | L33: =TEXT(B33,"MM/YYYY") -> 03/2025 | M33: =IF(B33="","",CONCATENATE("CXG-",TEXT(B33,"MMYY"))) -> CXG-0325 | N33: 45741.399 | O33: 15.000 Sacos
A34: f5cced4e | B34: 45674 | C34: 170125967 | D34: José Nunes | E34: Ronaldo Silva | F34: =SUMIFS(PedComCarrinho!E:E,PedComCarrinho!G:G,C:C) -> 376398.23 | G34: =SUMIFS(PagProdutor!F:F,PagProdutor!D:D,C:C)+(SUMIFS(PagComisao!F:F,PagComisao!K:K,C:C)) -> 376398.23 | H34: =F34-G34 -> 0 | I34: Safra Sergipe - 2025 | J34: Finalizado | K34: Aracaju/SE | L34: =TEXT(B34,"MM/YYYY") -> 01/2025 | M34: =IF(B34="","",CONCATENATE("CXG-",TEXT(B34,"MMYY"))) -> CXG-0125
A35: 24f54b44 | B35: 45784 | C35: 0705255335 | D35: Jr Grao | E35: Newton Porto | F35: =SUMIFS(PedComCarrinho!E:E,PedComCarrinho!G:G,C:C) -> 958633.62 | G35: =SUMIFS(PagProdutor!F:F,PagProdutor!D:D,C:C)+(SUMIFS(PagComisao!F:F,PagComisao!K:K,C:C)) -> 958633.62 | H35: =F35-G35 -> 0 | I35: Safra Maranhão - 2025 | J35: Finalizado | K35: Não Informado/MA | L35: =TEXT(B35,"MM/YYYY") -> 05/2025 | M35: =IF(B35="","",CONCATENATE("CXG-",TEXT(B35,"MMYY"))) -> CXG-0525 | N35: 45796.456
A36: 9b9b53e8 | B36: 45671 | C36: 160125470 | D36: Kelly Itabaianinha | E36: Newton Porto | F36: =SUMIFS(PedComCarrinho!E:E,PedComCarrinho!G:G,C:C) -> 917307.45 | G36: =SUMIFS(PagProdutor!F:F,PagProdutor!D:D,C:C)+(SUMIFS(PagComisao!F:F,PagComisao!K:K,C:C)) -> 917307.45 | H36: =F36-G36 -> 1.1641532e-10 | I36: Safra Sergipe - 2025 | J36: Finalizado | K36: Itabaiana/SE | L36: =TEXT(B36,"MM/YYYY") -> 01/2025 | M36: =IF(B36="","",CONCATENATE("CXG-",TEXT(B36,"MMYY"))) -> CXG-0125 | N36: 45684.359
A37: 50b52b50 | B37: 45680 | C37: 2301251745 | D37: Lucas LEM | E37: Newton Porto | F37: =SUMIFS(PedComCarrinho!E:E,PedComCarrinho!G:G,C:C) -> 47291.04 | G37: =SUMIFS(PagProdutor!F:F,PagProdutor!D:D,C:C)+(SUMIFS(PagComisao!F:F,PagComisao!K:K,C:C)) -> 47291.04 | H37: =F37-G37 -> 0 | I37: Safra Bahia - 2025 | J37: Finalizado | K37: Luis Eduardo Magalhães/BA | L37: =TEXT(B37,"MM/YYYY") -> 01/2025 | M37: =IF(B37="","",CONCATENATE("CXG-",TEXT(B37,"MMYY"))) -> CXG-0125
A38: df13086e | B38: 45674 | C38: 1701251131 | D38: Lucas Sobral | E38: Ronaldo Silva | F38: =SUMIFS(PedComCarrinho!E:E,PedComCarrinho!G:G,C:C) -> 962320.53 | G38: =SUMIFS(PagProdutor!F:F,PagProdutor!D:D,C:C)+(SUMIFS(PagComisao!F:F,PagComisao!K:K,C:C)) -> 962320.53 | H38: =F38-G38 -> 0 | I38: Safra Sergipe - 2025 | J38: Finalizado | K38: Não Informado/SE | L38: =TEXT(B38,"MM/YYYY") -> 01/2025 | M38: =IF(B38="","",CONCATENATE("CXG-",TEXT(B38,"MMYY"))) -> CXG-0125 | N38: 45870.582
A39: 1661f60f | B39: 45707 | C39: 1902252883 | D39: Luiz Médio | E39: Newton Porto | F39: =SUMIFS(PedComCarrinho!E:E,PedComCarrinho!G:G,C:C) -> 74128.77 | G39: =SUMIFS(PagProdutor!F:F,PagProdutor!D:D,C:C)+(SUMIFS(PagComisao!F:F,PagComisao!K:K,C:C)) -> 74128.77 | H39: =F39-G39 -> 0 | I39: Safra Sergipe - 2025 | J39: Finalizado | K39: Não Informado/SE | L39: =TEXT(B39,"MM/YYYY") -> 02/2025 | M39: =IF(B39="","",CONCATENATE("CXG-",TEXT(B39,"MMYY"))) -> CXG-0225
A40: 26439106 | B40: 45738 | C40: 2303254374 | D40: Marcelo Cumbe | E40: Ronaldo Silva | F40: =SUMIFS(PedComCarrinho!E:E,PedComCarrinho!G:G,C:C) -> 187120 | G40: =SUMIFS(PagProdutor!F:F,PagProdutor!D:D,C:C)+(SUMIFS(PagComisao!F:F,PagComisao!K:K,C:C)) -> 187120 | H40: =F40-G40 -> 0 | I40: Safra Sergipe - 2025 | J40: Finalizado | K40: Cumbe/SE | L40: =TEXT(B40,"MM/YYYY") -> 03/2025 | M40: =IF(B40="","",CONCATENATE("CXG-",TEXT(B40,"MMYY"))) -> CXG-0325 | N40: 45741.4
A41: ac3c0225 | B41: 45673 | C41: 160125657 | D41: Marcos Roco Graccho | E41: Ronaldo Silva | F41: =SUMIFS(PedComCarrinho!E:E,PedComCarrinho!G:G,C:C) -> 292740.7 | G41: =SUMIFS(PagProdutor!F:F,PagProdutor!D:D,C:C)+(SUMIFS(PagComisao!F:F,PagComisao!K:K,C:C)) -> 292740.7 | H41: =F41-G41 -> 0 | I41: Safra Sergipe - 2025 | J41: Finalizado | K41: Graccho Cardoso/SE | L41: =TEXT(B41,"MM/YYYY") -> 01/2025 | M41: =IF(B41="","",CONCATENATE("CXG-",TEXT(B41,"MMYY"))) -> CXG-0125 | N41: 45684.358
A42: 7d89e523 | B42: 45737 | C42: 2103254284 | D42: Messias | E42: Ronaldo Silva | F42: =SUMIFS(PedComCarrinho!E:E,PedComCarrinho!G:G,C:C) -> 269280 | G42: =SUMIFS(PagProdutor!F:F,PagProdutor!D:D,C:C)+(SUMIFS(PagComisao!F:F,PagComisao!K:K,C:C)) -> 269280 | H42: =F42-G42 -> 0 | I42: Safra Sergipe - 2025 | J42: Finalizado | K42: Não Informado/SE | L42: =TEXT(B42,"MM/YYYY") -> 03/2025 | M42: =IF(B42="","",CONCATENATE("CXG-",TEXT(B42,"MMYY"))) -> CXG-0325 | N42: 45741.4
A43: 2257f3d9 | B43: 45677 | C43: 2001251545 | D43: Milho Conde | E43: Newton Porto | F43: =SUMIFS(PedComCarrinho!E:E,PedComCarrinho!G:G,C:C) -> 675634.35 | G43: =SUMIFS(PagProdutor!F:F,PagProdutor!D:D,C:C)+(SUMIFS(PagComisao!F:F,PagComisao!K:K,C:C)) -> 675634.35 | H43: =F43-G43 -> -1.1641532e-10 | I43: Safra Bahia - 2025 | J43: Finalizado | K43: Conde/BA | L43: =TEXT(B43,"MM/YYYY") -> 01/2025 | M43: =IF(B43="","",CONCATENATE("CXG-",TEXT(B43,"MMYY"))) -> CXG-0125 | N43: 45698.626
A44: eefd15ce | B44: 45748 | C44: 0104254848 | D44: Paulinho | E44: Ronaldo Silva | F44: =SUMIFS(PedComCarrinho!E:E,PedComCarrinho!G:G,C:C) -> 2247088.9 | G44: =SUMIFS(PagProdutor!F:F,PagProdutor!D:D,C:C)+(SUMIFS(PagComisao!F:F,PagComisao!K:K,C:C)) -> 2247088.9 | H44: =F44-G44 -> -4.6566129e-10 | I44: Safra Bahia - 2025 | J44: Finalizado | K44: Não Informado/BA | L44: =TEXT(B44,"MM/YYYY") -> 04/2025 | M44: =IF(B44="","",CONCATENATE("CXG-",TEXT(B44,"MMYY"))) -> CXG-0425 | N44: 45772.47
A45: f5b9f208 | B45: 45723 | C45: 0703253399 | D45: Peterson | E45: Ronaldo Silva | F45: =SUMIFS(PedComCarrinho!E:E,PedComCarrinho!G:G,C:C) -> 126724.26 | G45: =SUMIFS(PagProdutor!F:F,PagProdutor!D:D,C:C)+(SUMIFS(PagComisao!F:F,PagComisao!K:K,C:C)) -> 126724.26 | H45: =F45-G45 -> 0 | I45: Safra Sergipe - 2025 | J45: Finalizado | K45: Nossa Senhora da Aparecida/SE | L45: =TEXT(B45,"MM/YYYY") -> 03/2025 | M45: =IF(B45="","",CONCATENATE("CXG-",TEXT(B45,"MMYY"))) -> CXG-0325 | N45: 45786.518
A46: 9a1bc14f | B46: 45743 | C46: 2703254641 | D46: Peterson Luan | E46: Newton Porto | F46: =SUMIFS(PedComCarrinho!E:E,PedComCarrinho!G:G,C:C) -> 159970 | G46: =SUMIFS(PagProdutor!F:F,PagProdutor!D:D,C:C)+(SUMIFS(PagComisao!F:F,PagComisao!K:K,C:C)) -> 159970 | H46: =F46-G46 -> 0 | I46: Safra Sergipe - 2025 | J46: Finalizado | K46: Não Informado/SE | L46: =TEXT(B46,"MM/YYYY") -> 03/2025 | M46: =IF(B46="","",CONCATENATE("CXG-",TEXT(B46,"MMYY"))) -> CXG-0325 | N46: 45786.518
A47: d00d6e45 | B47: 45742 | C47: 260325445 | D47: Reinaldo | E47: Newton Porto | F47: =SUMIFS(PedComCarrinho!E:E,PedComCarrinho!G:G,C:C) -> 721774.02 | G47: =SUMIFS(PagProdutor!F:F,PagProdutor!D:D,C:C)+(SUMIFS(PagComisao!F:F,PagComisao!K:K,C:C)) -> 721774.02 | H47: =F47-G47 -> 0 | I47: Safra Bahia - 2025 | J47: Finalizado | K47: Bom Jesus da Lapa/BA | L47: =TEXT(B47,"MM/YYYY") -> 03/2025 | M47: =IF(B47="","",CONCATENATE("CXG-",TEXT(B47,"MMYY"))) -> CXG-0325 | N47: 46084.499
A48: bef4abc4 | B48: 45788 | C48: 1205255417 | D48: Renato Galvão | E48: Ronaldo Silva | F48: =SUMIFS(PedComCarrinho!E:E,PedComCarrinho!G:G,C:C) -> 102396.44 | G48: =SUMIFS(PagProdutor!F:F,PagProdutor!D:D,C:C)+(SUMIFS(PagComisao!F:F,PagComisao!K:K,C:C)) -> 102396.44 | H48: =F48-G48 -> 0 | I48: Safra Maranhão - 2025 | J48: Finalizado | K48: Não Informado/MA | L48: =TEXT(B48,"MM/YYYY") -> 05/2025 | M48: =IF(B48="","",CONCATENATE("CXG-",TEXT(B48,"MMYY"))) -> CXG-0525
A49: e3d31e01 | B49: 45679 | C49: 2201251666 | D49: Samuel | E49: Ronaldo Silva | F49: =SUMIFS(PedComCarrinho!E:E,PedComCarrinho!G:G,C:C) -> 503515.7 | G49: =SUMIFS(PagProdutor!F:F,PagProdutor!D:D,C:C)+(SUMIFS(PagComisao!F:F,PagComisao!K:K,C:C)) -> 503515.7 | H49: =F49-G49 -> 0 | I49: Safra Sergipe - 2025 | J49: Finalizado | K49: Japoatã/SE | L49: =TEXT(B49,"MM/YYYY") -> 01/2025 | M49: =IF(B49="","",CONCATENATE("CXG-",TEXT(B49,"MMYY"))) -> CXG-0125 | N49: 45747.413
A50: 2dc7077e | B50: 45687 | C50: 3001252079 | D50: Thiago Feira Nova | E50: Ronaldo Silva | F50: =SUMIFS(PedComCarrinho!E:E,PedComCarrinho!G:G,C:C) -> 816873.12 | G50: =SUMIFS(PagProdutor!F:F,PagProdutor!D:D,C:C)+(SUMIFS(PagComisao!F:F,PagComisao!K:K,C:C)) -> 816873.12 | H50: =F50-G50 -> -1.1641532e-10 | I50: Safra Sergipe - 2025 | J50: Finalizado | K50: Feira Nova/SE | L50: =TEXT(B50,"MM/YYYY") -> 01/2025 | M50: =IF(B50="","",CONCATENATE("CXG-",TEXT(B50,"MMYY"))) -> CXG-0125 | N50: 45752.384
A51: 78529415 | B51: 45712 | C51: 2402252918 | D51: Wanderley | E51: Ronaldo Silva | F51: =SUMIFS(PedComCarrinho!E:E,PedComCarrinho!G:G,C:C) -> 0 | G51: =SUMIFS(PagProdutor!F:F,PagProdutor!D:D,C:C)+(SUMIFS(PagComisao!F:F,PagComisao!K:K,C:C)) -> 0 | H51: =F51-G51 -> 0 | I51: Safra Bahia - 2025 | J51: Finalizado | K51: Jeremoabo/BA | L51: =TEXT(B51,"MM/YYYY") -> 02/2025 | M51: =IF(B51="","",CONCATENATE("CXG-",TEXT(B51,"MMYY"))) -> CXG-0225
A52: bdda3781 | B52: 45743 | C52: 2703254573 | D52: Wendio Aparecida | E52: Ronaldo Silva | F52: =SUMIFS(PedComCarrinho!E:E,PedComCarrinho!G:G,C:C) -> 105145 | G52: =SUMIFS(PagProdutor!F:F,PagProdutor!D:D,C:C)+(SUMIFS(PagComisao!F:F,PagComisao!K:K,C:C)) -> 105145 | H52: =F52-G52 -> 0 | I52: Safra Sergipe - 2025 | J52: Finalizado | K52: Nossa Senhora da Aparecida/SE | L52: =TEXT(B52,"MM/YYYY") -> 03/2025 | M52: =IF(B52="","",CONCATENATE("CXG-",TEXT(B52,"MMYY"))) -> CXG-0325
A53: 0e1f7515 | B53: 45762 | C53: 1504255147 | D53: Wendoly Masley | E53: Newton Porto | F53: =SUMIFS(PedComCarrinho!E:E,PedComCarrinho!G:G,C:C) -> 1415957.2 | G53: =SUMIFS(PagProdutor!F:F,PagProdutor!D:D,C:C)+(SUMIFS(PagComisao!F:F,PagComisao!K:K,C:C)) -> 1415957.2 | H53: =F53-G53 -> 2.3283064e-10 | I53: Safra Bahia - 2025 | J53: Finalizado | K53: Não Informado/BA | L53: =TEXT(B53,"MM/YYYY") -> 04/2025 | M53: =IF(B53="","",CONCATENATE("CXG-",TEXT(B53,"MMYY"))) -> CXG-0425 | N53: 45776.36
A54: 89075a1c | B54: 45732 | C54: 1703254111 | D54: Ygor Cumbe | E54: Ronaldo Silva | F54: =SUMIFS(PedComCarrinho!E:E,PedComCarrinho!G:G,C:C) -> 650266.9 | G54: =SUMIFS(PagProdutor!F:F,PagProdutor!D:D,C:C)+(SUMIFS(PagComisao!F:F,PagComisao!K:K,C:C)) -> 650266.9 | H54: =F54-G54 -> 0 | I54: Safra Sergipe - 2025 | J54: Finalizado | K54: Cumbe/SE | L54: =TEXT(B54,"MM/YYYY") -> 03/2025 | M54: =IF(B54="","",CONCATENATE("CXG-",TEXT(B54,"MMYY"))) -> CXG-0325 | N54: 45741.401
A55: dcd92bcf | B55: 45685 | C55: 2801251960 | D55: Ze de Gerino | E55: Ronaldo Silva | F55: =SUMIFS(PedComCarrinho!E:E,PedComCarrinho!G:G,C:C) -> 363006.44 | G55: =SUMIFS(PagProdutor!F:F,PagProdutor!D:D,C:C)+(SUMIFS(PagComisao!F:F,PagComisao!K:K,C:C)) -> 363006.44 | H55: =F55-G55 -> 0 | I55: Safra Sergipe - 2025 | J55: Finalizado | K55: Não Informado/SE | L55: =TEXT(B55,"MM/YYYY") -> 01/2025 | M55: =IF(B55="","",CONCATENATE("CXG-",TEXT(B55,"MMYY"))) -> CXG-0125 | N55: 45687.676
A56: 811d7cec | B56: 45715 | C56: 2702253034 | D56: Ze Maia | E56: Newton Porto | F56: =SUMIFS(PedComCarrinho!E:E,PedComCarrinho!G:G,C:C) -> 182994.74 | G56: =SUMIFS(PagProdutor!F:F,PagProdutor!D:D,C:C)+(SUMIFS(PagComisao!F:F,PagComisao!K:K,C:C)) -> 182994.74 | H56: =F56-G56 -> 0 | I56: Safra Sergipe - 2025 | J56: Pendente | K56: Não Informado/SE | L56: =TEXT(B56,"MM/YYYY") -> 02/2025 | M56: =IF(B56="","",CONCATENATE("CXG-",TEXT(B56,"MMYY"))) -> CXG-0225 | N56: 46063.646
A57: bee0f0a2 | B57: 45804 | C57: 2705255745 | D57: Gabriel Balsas/Rio de Coco | E57: Newton Porto | F57: =SUMIFS(PedComCarrinho!E:E,PedComCarrinho!G:G,C:C) -> 75946 | G57: =SUMIFS(PagProdutor!F:F,PagProdutor!D:D,C:C)+(SUMIFS(PagComisao!F:F,PagComisao!K:K,C:C)) -> 75946 | H57: =F57-G57 -> 0 | I57: Safra Maranhão - 2025 | J57: Finalizado | K57: Balsas/MA | L57: =TEXT(B57,"MM/YYYY") -> 05/2025 | M57: =IF(B57="","",CONCATENATE("CXG-",TEXT(B57,"MMYY"))) -> CXG-0525
A58: a59ee30f | B58: 45806 | C58: 2905255893 | D58: Gabriel Balsas/Horizontina | E58: Newton Porto | F58: =SUMIFS(PedComCarrinho!E:E,PedComCarrinho!G:G,C:C) -> 451603.38 | G58: =SUMIFS(PagProdutor!F:F,PagProdutor!D:D,C:C)+(SUMIFS(PagComisao!F:F,PagComisao!K:K,C:C)) -> 451603.38 | H58: =F58-G58 -> 0 | I58: Safra Maranhão - 2025 | J58: Finalizado | K58: Balsas/MA | L58: =TEXT(B58,"MM/YYYY") -> 05/2025 | M58: =IF(B58="","",CONCATENATE("CXG-",TEXT(B58,"MMYY"))) -> CXG-0525 | N58: 45825.628
A59: d8267de8 | B59: 45808 | C59: 3105255943 | D59: Santa Fé - LEM | E59: Newton Porto | F59: =SUMIFS(PedComCarrinho!E:E,PedComCarrinho!G:G,C:C) -> 120519 | G59: =SUMIFS(PagProdutor!F:F,PagProdutor!D:D,C:C)+(SUMIFS(PagComisao!F:F,PagComisao!K:K,C:C)) -> 120519 | H59: =F59-G59 -> 0 | I59: Safra Maranhão - 2025 | J59: Finalizado | K59: Não Informado/PI | L59: =TEXT(B59,"MM/YYYY") -> 05/2025 | M59: =IF(B59="","",CONCATENATE("CXG-",TEXT(B59,"MMYY"))) -> CXG-0525
A60: 821a969e | B60: 45807 | C60: 0206256089 | D60: Fabiano Balsas | E60: Newton Porto | F60: =SUMIFS(PedComCarrinho!E:E,PedComCarrinho!G:G,C:C) -> 1759954.3 | G60: =SUMIFS(PagProdutor!F:F,PagProdutor!D:D,C:C)+(SUMIFS(PagComisao!F:F,PagComisao!K:K,C:C)) -> 1759954.3 | H60: =F60-G60 -> 0 | I60: Safra Maranhão - 2025 | J60: Finalizado | K60: Balsas/MA | L60: =TEXT(B60,"MM/YYYY") -> 05/2025 | M60: =IF(B60="","",CONCATENATE("CXG-",TEXT(B60,"MMYY"))) -> CXG-0525 | N60: 45838.361
A61: 6c0e6f38 | B61: 45811 | C61: 0306256155 | D61: Guilherme Balsas/Serra da Fortaleza | E61: Newton Porto | F61: =SUMIFS(PedComCarrinho!E:E,PedComCarrinho!G:G,C:C) -> 150328.92 | G61: =SUMIFS(PagProdutor!F:F,PagProdutor!D:D,C:C)+(SUMIFS(PagComisao!F:F,PagComisao!K:K,C:C)) -> 150328.92 | H61: =F61-G61 -> 0 | I61: Safra Maranhão - 2025 | J61: Finalizado | K61: Balsas/MA | L61: =TEXT(B61,"MM/YYYY") -> 06/2025 | M61: =IF(B61="","",CONCATENATE("CXG-",TEXT(B61,"MMYY"))) -> CXG-0625 | N61: 45840.713
A62: 0393bcec | B62: 45811 | C62: 0306256299 | D62: Lukas Bom Jesus | E62: Newton Porto | F62: =SUMIFS(PedComCarrinho!E:E,PedComCarrinho!G:G,C:C) -> 107740.83 | G62: =SUMIFS(PagProdutor!F:F,PagProdutor!D:D,C:C)+(SUMIFS(PagComisao!F:F,PagComisao!K:K,C:C)) -> 107740.83 | H62: =F62-G62 -> 0 | I62: Safra Piauí - 2025 | J62: Finalizado | K62: Não Informado/PI | L62: =TEXT(B62,"MM/YYYY") -> 06/2025 | M62: =IF(B62="","",CONCATENATE("CXG-",TEXT(B62,"MMYY"))) -> CXG-0625
A63: 030b9bcf | B63: 45824 | C63: 1706256363 | D63: Maeli Zaltron | E63: Wendoly Masley | F63: =SUMIFS(PedComCarrinho!E:E,PedComCarrinho!G:G,C:C) -> 412053.72 | G63: =SUMIFS(PagProdutor!F:F,PagProdutor!D:D,C:C)+(SUMIFS(PagComisao!F:F,PagComisao!K:K,C:C)) -> 412053.72 | H63: =F63-G63 -> 0 | I63: Safra Maranhão - 2025 | J63: Finalizado | K63: Não Informado/MA | L63: =TEXT(B63,"MM/YYYY") -> 06/2025 | M63: =IF(B63="","",CONCATENATE("CXG-",TEXT(B63,"MMYY"))) -> CXG-0625
A64: a9954ae1 | B64: 45827 | C64: 1906256467 | D64: Milton Ernesto | E64: Newton Porto | F64: =SUMIFS(PedComCarrinho!E:E,PedComCarrinho!G:G,C:C) -> 255984.33 | G64: =SUMIFS(PagProdutor!F:F,PagProdutor!D:D,C:C)+(SUMIFS(PagComisao!F:F,PagComisao!K:K,C:C)) -> 255984.33 | H64: =F64-G64 -> 0 | I64: Safra Maranhão - 2025 | J64: Finalizado | K64: Não Informado/MA | L64: =TEXT(B64,"MM/YYYY") -> 06/2025 | M64: =IF(B64="","",CONCATENATE("CXG-",TEXT(B64,"MMYY"))) -> CXG-0625
A65: 44895f19 | B65: 45838 | C65: 3006256539 | D65: Irineu/Suporte | E65: Newton Porto | F65: =SUMIFS(PedComCarrinho!E:E,PedComCarrinho!G:G,C:C) -> 5752116.6 | G65: =SUMIFS(PagProdutor!F:F,PagProdutor!D:D,C:C)+(SUMIFS(PagComisao!F:F,PagComisao!K:K,C:C)) -> 5752116.6 | H65: =F65-G65 -> 0 | I65: Safra Maranhão - 2025 | J65: Finalizado | K65: Balsas/MA | L65: =TEXT(B65,"MM/YYYY") -> 06/2025 | M65: =IF(B65="","",CONCATENATE("CXG-",TEXT(B65,"MMYY"))) -> CXG-0625 | N65: 46034.432
A66: 3a3a5cb7 | B66: 45840 | C66: 020725667 | D66: Jorge Schutz/Balsas | E66: Newton Porto | F66: =SUMIFS(PedComCarrinho!E:E,PedComCarrinho!G:G,C:C) -> 452212.61 | G66: =SUMIFS(PagProdutor!F:F,PagProdutor!D:D,C:C)+(SUMIFS(PagComisao!F:F,PagComisao!K:K,C:C)) -> 452212.61 | H66: =F66-G66 -> 0 | I66: Safra Maranhão - 2025 | J66: Finalizado | K66: Balsas/MA | L66: =TEXT(B66,"MM/YYYY") -> 07/2025 | M66: =IF(B66="","",CONCATENATE("CXG-",TEXT(B66,"MMYY"))) -> CXG-0725 | N66: 45849.37
A67: 8fdca8b2 | B67: 45840 | C67: 0207256797 | D67: Fabiano Balsas/Campo Real | E67: Newton Porto | F67: =SUMIFS(PedComCarrinho!E:E,PedComCarrinho!G:G,C:C) -> 483940.26 | G67: =SUMIFS(PagProdutor!F:F,PagProdutor!D:D,C:C)+(SUMIFS(PagComisao!F:F,PagComisao!K:K,C:C)) -> 483940.26 | H67: =F67-G67 -> 0 | I67: Safra Maranhão - 2025 | J67: Finalizado | K67: Balsas/MA | L67: =TEXT(B67,"MM/YYYY") -> 07/2025 | M67: =IF(B67="","",CONCATENATE("CXG-",TEXT(B67,"MMYY"))) -> CXG-0725 | N67: 45940.588
A68: 62bcc916 | B68: 45842 | C68: 0607256852 | D68: Guilherme Balsas | E68: Newton Porto | F68: =SUMIFS(PedComCarrinho!E:E,PedComCarrinho!G:G,C:C) -> 459674.22 | G68: =SUMIFS(PagProdutor!F:F,PagProdutor!D:D,C:C)+(SUMIFS(PagComisao!F:F,PagComisao!K:K,C:C)) -> 459674.22 | H68: =F68-G68 -> 0 | I68: Safra Maranhão - 2025 | J68: Finalizado | K68: Balsas/MA | L68: =TEXT(B68,"MM/YYYY") -> 07/2025 | M68: =IF(B68="","",CONCATENATE("CXG-",TEXT(B68,"MMYY"))) -> CXG-0725 | N68: 45861.424
A69: d9a860f9 | B69: 45863 | C69: 2507256966 | D69: Edenilson Balsas | E69: Newton Porto | F69: =SUMIFS(PedComCarrinho!E:E,PedComCarrinho!G:G,C:C) -> 516654.02 | G69: =SUMIFS(PagProdutor!F:F,PagProdutor!D:D,C:C)+(SUMIFS(PagComisao!F:F,PagComisao!K:K,C:C)) -> 516654.02 | H69: =F69-G69 -> 0 | I69: Safra Maranhão - 2025 | J69: Finalizado | K69: Balsas/MA | L69: =TEXT(B69,"MM/YYYY") -> 07/2025 | M69: =IF(B69="","",CONCATENATE("CXG-",TEXT(B69,"MMYY"))) -> CXG-0725 | N69: 45979.952
A70: 5a6a0697 | B70: 45867 | C70: 2907257082 | D70: Irineu | E70: Newton Porto | F70: =SUMIFS(PedComCarrinho!E:E,PedComCarrinho!G:G,C:C) -> 2694774.4 | G70: =SUMIFS(PagProdutor!F:F,PagProdutor!D:D,C:C)+(SUMIFS(PagComisao!F:F,PagComisao!K:K,C:C)) -> 2694774.4 | H70: =F70-G70 -> 0 | I70: Safra Maranhão - 2025 | J70: Finalizado | K70: Balsas/MA | L70: =TEXT(B70,"MM/YYYY") -> 07/2025 | M70: =IF(B70="","",CONCATENATE("CXG-",TEXT(B70,"MMYY"))) -> CXG-0725 | N70: 46034.432
A71: 6361b35e | B71: 45871 | C71: 0208257144 | D71: André | E71: Newton Porto | F71: =SUMIFS(PedComCarrinho!E:E,PedComCarrinho!G:G,C:C) -> 52231.85 | G71: =SUMIFS(PagProdutor!F:F,PagProdutor!D:D,C:C)+(SUMIFS(PagComisao!F:F,PagComisao!K:K,C:C)) -> 52231.85 | H71: =F71-G71 -> 0 | I71: Safra Sergipe - 2025 | J71: Finalizado | K71: Não Informado/SE | L71: =TEXT(B71,"MM/YYYY") -> 08/2025 | M71: =IF(B71="","",CONCATENATE("CXG-",TEXT(B71,"MMYY"))) -> CXG-0825
A72: f7702031 | B72: 45875 | C72: 0608257281 | D72: Ramon Bom Jesus | E72: Newton Porto | F72: =SUMIFS(PedComCarrinho!E:E,PedComCarrinho!G:G,C:C) -> 313092.88 | G72: =SUMIFS(PagProdutor!F:F,PagProdutor!D:D,C:C)+(SUMIFS(PagComisao!F:F,PagComisao!K:K,C:C)) -> 313092.88 | H72: =F72-G72 -> 0 | I72: Safra Maranhão - 2025 | J72: Finalizado | K72: Bom Jesus das Selvas/MA | L72: =TEXT(B72,"MM/YYYY") -> 08/2025 | M72: =IF(B72="","",CONCATENATE("CXG-",TEXT(B72,"MMYY"))) -> CXG-0825 | N72: 45881.342
A73: def00b5a | B73: 45882 | C73: 1308257319 | D73: Pedro Goiatins | E73: Ronaldo Silva | F73: =SUMIFS(PedComCarrinho!E:E,PedComCarrinho!G:G,C:C) -> 281031.85 | G73: =SUMIFS(PagProdutor!F:F,PagProdutor!D:D,C:C)+(SUMIFS(PagComisao!F:F,PagComisao!K:K,C:C)) -> 281031.85 | H73: =F73-G73 -> 0 | I73: Safra Tocantins - 2025 | J73: Finalizado | K73: Goiatins/TO | L73: =TEXT(B73,"MM/YYYY") -> 08/2025 | M73: =IF(B73="","",CONCATENATE("CXG-",TEXT(B73,"MMYY"))) -> CXG-0825 | N73: 45888.684
A74: 83cb9c2d | B74: 45883 | C74: 1408257495 | D74: Claudir Faz. Bacuri | E74: Ronaldo Silva | F74: =SUMIFS(PedComCarrinho!E:E,PedComCarrinho!G:G,C:C) -> 1667848 | G74: =SUMIFS(PagProdutor!F:F,PagProdutor!D:D,C:C)+(SUMIFS(PagComisao!F:F,PagComisao!K:K,C:C)) -> 1667848 | H74: =F74-G74 -> 0 | I74: Safra Tocantins - 2025 | J74: Finalizado | K74: Não informado/TO | L74: =TEXT(B74,"MM/YYYY") -> 08/2025 | M74: =IF(B74="","",CONCATENATE("CXG-",TEXT(B74,"MMYY"))) -> CXG-0825 | N74: 45904.684
A75: 2d6960c9 | B75: 45887 | C75: 1808257593 | D75: Pedro Campos Lindos | E75: Ronaldo Silva | F75: =SUMIFS(PedComCarrinho!E:E,PedComCarrinho!G:G,C:C) -> 2695919.4 | G75: =SUMIFS(PagProdutor!F:F,PagProdutor!D:D,C:C)+(SUMIFS(PagComisao!F:F,PagComisao!K:K,C:C)) -> 2695919.4 | H75: =F75-G75 -> 0 | I75: Safra Tocantins - 2025 | J75: Finalizado | K75: Não informado/TO | L75: =TEXT(B75,"MM/YYYY") -> 08/2025 | M75: =IF(B75="","",CONCATENATE("CXG-",TEXT(B75,"MMYY"))) -> CXG-0825 | N75: 45946.612 | O75: 45 Mil sacos a 60,00
A76: b43589d2 | B76: 45902 | C76: 0209257662 | D76: Carlos Campos Lindos | E76: Newton Porto | F76: =SUMIFS(PedComCarrinho!E:E,PedComCarrinho!G:G,C:C) -> 1524940.8 | G76: =SUMIFS(PagProdutor!F:F,PagProdutor!D:D,C:C)+(SUMIFS(PagComisao!F:F,PagComisao!K:K,C:C)) -> 1524940.8 | H76: =F76-G76 -> 0 | I76: Safra Piauí - 2025 | J76: Finalizado | K76: Não Informado/PI | L76: =TEXT(B76,"MM/YYYY") -> 09/2025 | M76: =IF(B76="","",CONCATENATE("CXG-",TEXT(B76,"MMYY"))) -> CXG-0925 | N76: 45936.395 | O76: 25 Mil Sacos á 60,00
A77: b7fd3672 | B77: 45916 | C77: 1609257729 | D77: Flavio Faz. Santana | E77: Newton Porto | F77: =SUMIFS(PedComCarrinho!E:E,PedComCarrinho!G:G,C:C) -> 512880 | G77: =SUMIFS(PagProdutor!F:F,PagProdutor!D:D,C:C)+(SUMIFS(PagComisao!F:F,PagComisao!K:K,C:C)) -> 512880 | H77: =F77-G77 -> 0 | I77: Safra Tocantins - 2025 | J77: Finalizado | K77: Não informado/TO | L77: =TEXT(B77,"MM/YYYY") -> 09/2025 | M77: =IF(B77="","",CONCATENATE("CXG-",TEXT(B77,"MMYY"))) -> CXG-0925 | N77: 45922.47
A78: 846d623f | B78: 45923 | C78: 2309257852 | D78: Marcelo Campos Lindos | E78: Newton Porto | F78: =SUMIFS(PedComCarrinho!E:E,PedComCarrinho!G:G,C:C) -> 811719.6 | G78: =SUMIFS(PagProdutor!F:F,PagProdutor!D:D,C:C)+(SUMIFS(PagComisao!F:F,PagComisao!K:K,C:C)) -> 811719.6 | H78: =F78-G78 -> 1.1641532e-10 | I78: Safra Tocantins - 2025 | J78: Finalizado | K78: Não informado/TO | L78: =TEXT(B78,"MM/YYYY") -> 09/2025 | M78: =IF(B78="","",CONCATENATE("CXG-",TEXT(B78,"MMYY"))) -> CXG-0925 | N78: 45936.394 | O78: 12 Mil Scs a 60,00
A79: 5296f347 | B79: 45932 | C79: 0210257956 | D79: Rodrigo Rocha | E79: Newton Porto | F79: =SUMIFS(PedComCarrinho!E:E,PedComCarrinho!G:G,C:C) -> 23651.16 | G79: =SUMIFS(PagProdutor!F:F,PagProdutor!D:D,C:C)+(SUMIFS(PagComisao!F:F,PagComisao!K:K,C:C)) -> 23651.16 | H79: =F79-G79 -> 0 | I79: Safra Sergipe - 2025 | J79: Finalizado | K79: Não Informado/SE | L79: =TEXT(B79,"MM/YYYY") -> 10/2025 | M79: =IF(B79="","",CONCATENATE("CXG-",TEXT(B79,"MMYY"))) -> CXG-1025 | N79: 45951.563 | O79: SORGO
A80: bec0b464 | B80: 45933 | C80: 0310258023 | D80: Irineu/2 | E80: Newton Porto | F80: =SUMIFS(PedComCarrinho!E:E,PedComCarrinho!G:G,C:C) -> 2105780.4 | G80: =SUMIFS(PagProdutor!F:F,PagProdutor!D:D,C:C)+(SUMIFS(PagComisao!F:F,PagComisao!K:K,C:C)) -> 2105780.4 | H80: =F80-G80 -> 4.6566129e-10 | I80: Safra Maranhão - 2025 | J80: Finalizado | K80: Balsas/MA | L80: =TEXT(B80,"MM/YYYY") -> 10/2025 | M80: =IF(B80="","",CONCATENATE("CXG-",TEXT(B80,"MMYY"))) -> CXG-1025 | N80: 46034.432
A81: bde8a98f | B81: 45933 | C81: 0310258196 | D81: Jamerson | E81: Newton Porto | F81: =SUMIFS(PedComCarrinho!E:E,PedComCarrinho!G:G,C:C) -> 122340 | G81: =SUMIFS(PagProdutor!F:F,PagProdutor!D:D,C:C)+(SUMIFS(PagComisao!F:F,PagComisao!K:K,C:C)) -> 122340 | H81: =F81-G81 -> 0 | I81: Safra Sergipe - 2025 | J81: Finalizado | K81: Não Informado/SE | L81: =TEXT(B81,"MM/YYYY") -> 10/2025 | M81: =IF(B81="","",CONCATENATE("CXG-",TEXT(B81,"MMYY"))) -> CXG-1025 | N81: 45971.379
A82: 843bd336 | B82: 45937 | C82: 0710258265 | D82: Gabriel Melo - Itabi | E82: Newton Porto | F82: =SUMIFS(PedComCarrinho!E:E,PedComCarrinho!G:G,C:C) -> 152928.21 | G82: =SUMIFS(PagProdutor!F:F,PagProdutor!D:D,C:C)+(SUMIFS(PagComisao!F:F,PagComisao!K:K,C:C)) -> 152928.21 | H82: =F82-G82 -> 0 | I82: Safra Sergipe - 2025 | J82: Finalizado | K82: Itabi/SE | L82: =TEXT(B82,"MM/YYYY") -> 10/2025 | M82: =IF(B82="","",CONCATENATE("CXG-",TEXT(B82,"MMYY"))) -> CXG-1025 | N82: 45971.658
A83: 6916d68d | B83: 45939 | C83: 0910258321 | D83: Kelly Jeremoabo | E83: Newton Porto | F83: =SUMIFS(PedComCarrinho!E:E,PedComCarrinho!G:G,C:C) -> 231098.01 | G83: =SUMIFS(PagProdutor!F:F,PagProdutor!D:D,C:C)+(SUMIFS(PagComisao!F:F,PagComisao!K:K,C:C)) -> 231098.01 | H83: =F83-G83 -> 0 | I83: Safra Bahia - 2025 | J83: Finalizado | K83: Jeremoabo/BA | L83: =TEXT(B83,"MM/YYYY") -> 10/2025 | M83: =IF(B83="","",CONCATENATE("CXG-",TEXT(B83,"MMYY"))) -> CXG-1025
A84: 585b990c | B84: 45941 | C84: 1210258496 | D84: Carlinhos | E84: Newton Porto | F84: =SUMIFS(PedComCarrinho!E:E,PedComCarrinho!G:G,C:C) -> 214681.12 | G84: =SUMIFS(PagProdutor!F:F,PagProdutor!D:D,C:C)+(SUMIFS(PagComisao!F:F,PagComisao!K:K,C:C)) -> 214681.12 | H84: =F84-G84 -> 0 | I84: Safra Sergipe - 2025 | J84: Finalizado | K84: Não Informado/SE | L84: =TEXT(B84,"MM/YYYY") -> 10/2025 | M84: =IF(B84="","",CONCATENATE("CXG-",TEXT(B84,"MMYY"))) -> CXG-1025 | N84: 45958.395
A85: 71bc7dc9 | B85: 45942 | C85: 1210258593 | D85: Maraivan | E85: Newton Porto | F85: =SUMIFS(PedComCarrinho!E:E,PedComCarrinho!G:G,C:C) -> 142609.22 | G85: =SUMIFS(PagProdutor!F:F,PagProdutor!D:D,C:C)+(SUMIFS(PagComisao!F:F,PagComisao!K:K,C:C)) -> 142609.22 | H85: =F85-G85 -> 0 | I85: Safra Sergipe - 2025 | J85: Finalizado | K85: Não Informado/SE | L85: =TEXT(B85,"MM/YYYY") -> 10/2025 | M85: =IF(B85="","",CONCATENATE("CXG-",TEXT(B85,"MMYY"))) -> CXG-1025
A86: 9ddeb99a | B86: 45944 | C86: 1410258627 | D86: Juranda | E86: Newton Porto | F86: =SUMIFS(PedComCarrinho!E:E,PedComCarrinho!G:G,C:C) -> 34056 | G86: =SUMIFS(PagProdutor!F:F,PagProdutor!D:D,C:C)+(SUMIFS(PagComisao!F:F,PagComisao!K:K,C:C)) -> 50000 | H86: =F86-G86 -> -15944 | I86: Safra Sergipe - 2025 | J86: Pendente | K86: Itaporanga/SE | L86: =TEXT(B86,"MM/YYYY") -> 10/2025 | M86: =IF(B86="","",CONCATENATE("CXG-",TEXT(B86,"MMYY"))) -> CXG-1025
A87: 473f2a9c | B87: 45944 | C87: 1410258770 | D87: Galeguinho do Milho | E87: Newton Porto | F87: =SUMIFS(PedComCarrinho!E:E,PedComCarrinho!G:G,C:C) -> 333152.83 | G87: =SUMIFS(PagProdutor!F:F,PagProdutor!D:D,C:C)+(SUMIFS(PagComisao!F:F,PagComisao!K:K,C:C)) -> 333152.83 | H87: =F87-G87 -> 0 | I87: Safra Sergipe - 2025 | J87: Finalizado | K87: Não Informado/SE | L87: =TEXT(B87,"MM/YYYY") -> 10/2025 | M87: =IF(B87="","",CONCATENATE("CXG-",TEXT(B87,"MMYY"))) -> CXG-1025 | N87: 45946.429
A88: 966a26d0 | B88: 45945 | C88: 1510258835 | D88: Pedro Campos Lindos | E88: Newton Porto | F88: =SUMIFS(PedComCarrinho!E:E,PedComCarrinho!G:G,C:C) -> 626283.42 | G88: =SUMIFS(PagProdutor!F:F,PagProdutor!D:D,C:C)+(SUMIFS(PagComisao!F:F,PagComisao!K:K,C:C)) -> 626283.42 | H88: =F88-G88 -> 0 | I88: Safra Tocantins - 2025 | J88: Finalizado | K88: Não informado/TO | L88: =TEXT(B88,"MM/YYYY") -> 10/2025 | M88: =IF(B88="","",CONCATENATE("CXG-",TEXT(B88,"MMYY"))) -> CXG-1025 | N88: 45947.425
A89: 1fee970f | B89: 45950 | C89: 2010258997 | D89: Marco Amaral | E89: Ronaldo Silva | F89: =SUMIFS(PedComCarrinho!E:E,PedComCarrinho!G:G,C:C) -> 161930.79 | G89: =SUMIFS(PagProdutor!F:F,PagProdutor!D:D,C:C)+(SUMIFS(PagComisao!F:F,PagComisao!K:K,C:C)) -> 161930.79 | H89: =F89-G89 -> 0 | I89: Safra Sergipe - 2025 | J89: Finalizado | K89: Não Informado/SE | L89: =TEXT(B89,"MM/YYYY") -> 10/2025 | M89: =IF(B89="","",CONCATENATE("CXG-",TEXT(B89,"MMYY"))) -> CXG-1025 | N89: 45951.449
A90: f71e45ea | B90: 45950 | C90: 2010259080 | D90: Denison Itabi | E90: Ronaldo Silva | F90: =SUMIFS(PedComCarrinho!E:E,PedComCarrinho!G:G,C:C) -> 173396.79 | G90: =SUMIFS(PagProdutor!F:F,PagProdutor!D:D,C:C)+(SUMIFS(PagComisao!F:F,PagComisao!K:K,C:C)) -> 173396.79 | H90: =F90-G90 -> 0 | I90: Safra Sergipe - 2025 | J90: Finalizado | K90: Itabi/SE | L90: =TEXT(B90,"MM/YYYY") -> 10/2025 | M90: =IF(B90="","",CONCATENATE("CXG-",TEXT(B90,"MMYY"))) -> CXG-1025 | N90: 45961.543
A91: 042e0c6f | B91: 45950 | C91: 201025914 | D91: Nininho | E91: Ronaldo Silva | F91: =SUMIFS(PedComCarrinho!E:E,PedComCarrinho!G:G,C:C) -> 79485.21 | G91: =SUMIFS(PagProdutor!F:F,PagProdutor!D:D,C:C)+(SUMIFS(PagComisao!F:F,PagComisao!K:K,C:C)) -> 79485.21 | H91: =F91-G91 -> 0 | I91: Safra Sergipe - 2025 | J91: Finalizado | K91: Não Informado/SE | L91: =TEXT(B91,"MM/YYYY") -> 10/2025 | M91: =IF(B91="","",CONCATENATE("CXG-",TEXT(B91,"MMYY"))) -> CXG-1025 | N91: 46009.416
A92: 69390928 | B92: 45949 | C92: 2010259279 | D92: Jânio Itabi | E92: Newton Porto | F92: =SUMIFS(PedComCarrinho!E:E,PedComCarrinho!G:G,C:C) -> 77996 | G92: =SUMIFS(PagProdutor!F:F,PagProdutor!D:D,C:C)+(SUMIFS(PagComisao!F:F,PagComisao!K:K,C:C)) -> 77996 | H92: =F92-G92 -> 0 | I92: Safra Sergipe - 2025 | J92: Finalizado | K92: Itabi/SE | L92: =TEXT(B92,"MM/YYYY") -> 10/2025 | M92: =IF(B92="","",CONCATENATE("CXG-",TEXT(B92,"MMYY"))) -> CXG-1025 | N92: 45950.444
A93: 985387be | B93: 45950 | C93: 2010259360 | D93: Galego | E93: Ronaldo Silva | F93: =SUMIFS(PedComCarrinho!E:E,PedComCarrinho!G:G,C:C) -> 80388 | G93: =SUMIFS(PagProdutor!F:F,PagProdutor!D:D,C:C)+(SUMIFS(PagComisao!F:F,PagComisao!K:K,C:C)) -> 80388 | H93: =F93-G93 -> 0 | I93: Safra Sergipe - 2025 | J93: Finalizado | K93: Não Informado/SE | L93: =TEXT(B93,"MM/YYYY") -> 10/2025 | M93: =IF(B93="","",CONCATENATE("CXG-",TEXT(B93,"MMYY"))) -> CXG-1025 | N93: 45950.445
A94: d897481e | B94: 45946 | C94: 211025945 | D94: Rodrigo Rocha | E94: Newton Porto | F94: =SUMIFS(PedComCarrinho!E:E,PedComCarrinho!G:G,C:C) -> 66660 | G94: =SUMIFS(PagProdutor!F:F,PagProdutor!D:D,C:C)+(SUMIFS(PagComisao!F:F,PagComisao!K:K,C:C)) -> 66660 | H94: =F94-G94 -> 0 | I94: Safra Sergipe - 2025 | J94: Finalizado | K94: Não Informado/SE | L94: =TEXT(B94,"MM/YYYY") -> 10/2025 | M94: =IF(B94="","",CONCATENATE("CXG-",TEXT(B94,"MMYY"))) -> CXG-1025 | N94: 45951.563
A95: 974ab27c | B95: 45948 | C95: 2110259558 | D95: Rodrigo Rocha | E95: Newton Porto | F95: =SUMIFS(PedComCarrinho!E:E,PedComCarrinho!G:G,C:C) -> 206680.6 | G95: =SUMIFS(PagProdutor!F:F,PagProdutor!D:D,C:C)+(SUMIFS(PagComisao!F:F,PagComisao!K:K,C:C)) -> 206680.6 | H95: =F95-G95 -> 0 | I95: Safra Sergipe - 2025 | J95: Finalizado | K95: Não Informado/SE | L95: =TEXT(B95,"MM/YYYY") -> 10/2025 | M95: =IF(B95="","",CONCATENATE("CXG-",TEXT(B95,"MMYY"))) -> CXG-1025 | N95: 45951.685 | O95: 3 Mil Scs a 61,00
A96: f3776725 | B96: 45953 | C96: 2310259662 | D96: Armazem Rocha | E96: Newton Porto | F96: =SUMIFS(PedComCarrinho!E:E,PedComCarrinho!G:G,C:C) -> 1033992.5 | G96: =SUMIFS(PagProdutor!F:F,PagProdutor!D:D,C:C)+(SUMIFS(PagComisao!F:F,PagComisao!K:K,C:C)) -> 1033992.5 | H96: =F96-G96 -> -2.3283064e-10 | I96: Safra Sergipe - 2025 | J96: Finalizado | K96: Não Informado/SE | L96: =TEXT(B96,"MM/YYYY") -> 10/2025 | M96: =IF(B96="","",CONCATENATE("CXG-",TEXT(B96,"MMYY"))) -> CXG-1025 | N96: 45978.418
A97: bbcdf089 | B97: 45953 | C97: 2310259712 | D97: Plinio | E97: Newton Porto | F97: =SUMIFS(PedComCarrinho!E:E,PedComCarrinho!G:G,C:C) -> 52989.54 | G97: =SUMIFS(PagProdutor!F:F,PagProdutor!D:D,C:C)+(SUMIFS(PagComisao!F:F,PagComisao!K:K,C:C)) -> 52989.54 | H97: =F97-G97 -> 0 | I97: Safra Sergipe - 2025 | J97: Finalizado | K97: Não Informado/SE | L97: =TEXT(B97,"MM/YYYY") -> 10/2025 | M97: =IF(B97="","",CONCATENATE("CXG-",TEXT(B97,"MMYY"))) -> CXG-1025
A98: 3bf8a5e1 | B98: 45957 | C98: 271025984 | D98: Joãozinho Itabi | E98: Ronaldo Silva | F98: =SUMIFS(PedComCarrinho!E:E,PedComCarrinho!G:G,C:C) -> 150821.43 | G98: =SUMIFS(PagProdutor!F:F,PagProdutor!D:D,C:C)+(SUMIFS(PagComisao!F:F,PagComisao!K:K,C:C)) -> 150821.43 | H98: =F98-G98 -> 0 | I98: Safra Sergipe - 2025 | J98: Finalizado | K98: Itabi/SE | L98: =TEXT(B98,"MM/YYYY") -> 10/2025 | M98: =IF(B98="","",CONCATENATE("CXG-",TEXT(B98,"MMYY"))) -> CXG-1025 | N98: 45958.396
A99: ca4135b6 | B99: 45957 | C99: 2710259952 | D99: Carlinhos | E99: Ronaldo Silva | F99: =SUMIFS(PedComCarrinho!E:E,PedComCarrinho!G:G,C:C) -> 57100.2 | G99: =SUMIFS(PagProdutor!F:F,PagProdutor!D:D,C:C)+(SUMIFS(PagComisao!F:F,PagComisao!K:K,C:C)) -> 57100.2 | H99: =F99-G99 -> 0 | I99: Safra Sergipe - 2025 | J99: Finalizado | K99: Não Informado/SE | L99: =TEXT(B99,"MM/YYYY") -> 10/2025 | M99: =IF(B99="","",CONCATENATE("CXG-",TEXT(B99,"MMYY"))) -> CXG-1025 | N99: 45958.395
A100: 3ba8a56b | B100: 45958 | C100: 28102510054 | D100: Maraivan | E100: Newton Porto | F100: =SUMIFS(PedComCarrinho!E:E,PedComCarrinho!G:G,C:C) -> 66577.46 | G100: =SUMIFS(PagProdutor!F:F,PagProdutor!D:D,C:C)+(SUMIFS(PagComisao!F:F,PagComisao!K:K,C:C)) -> 66577.46 | H100: =F100-G100 -> 0 | I100: Safra Sergipe - 2025 | J100: Finalizado | K100: Não Informado/SE | L100: =TEXT(B100,"MM/YYYY") -> 10/2025 | M100: =IF(B100="","",CONCATENATE("CXG-",TEXT(B100,"MMYY"))) -> CXG-1025
...

Sheet PedComCarrinho
A1: ID | B1: Produto | C1: Quantidade KG | D1: Quantidade SC | E1: Valor Total | F1: Valor Unit Medio | G1: PedidodeCompra
A2: 136758a2 | B2: Milho em Grãos | C2: =SUMIFS(CarrinhoFretes!D:D,CarrinhoFretes!U:U,G:G) -> 260980 | D2: =C2/60 -> 4349.6667 | E2: =SUMIFS(CarrinhoFretes!G:G,CarrinhoFretes!U:U,G:G) -> 305564.32 | F2: =IF(D2=0, 0, E2/D2) -> 70.250054 | G2: 150125254
A3: 5cfa751e | B3: Milho em Grãos | C3: =SUMIFS(CarrinhoFretes!D:D,CarrinhoFretes!U:U,G:G) -> 71340 | D3: =C3/60 -> 1189 | E3: =SUMIFS(CarrinhoFretes!G:G,CarrinhoFretes!U:U,G:G) -> 82041 | F3: =IF(D3=0, 0, E3/D3) -> 69 | G3: 160125346
A4: d2e35695 | B4: Milho em Grãos | C4: =SUMIFS(CarrinhoFretes!D:D,CarrinhoFretes!U:U,G:G) -> 772950 | D4: =C4/60 -> 12882.5 | E4: =SUMIFS(CarrinhoFretes!G:G,CarrinhoFretes!U:U,G:G) -> 917307.45 | F4: =IF(D4=0, 0, E4/D4) -> 71.205702 | G4: 160125470
A5: ba126ea2 | B5: Milho em Grãos | C5: =SUMIFS(CarrinhoFretes!D:D,CarrinhoFretes!U:U,G:G) -> 10620 | D5: =C5/60 -> 177 | E5: =SUMIFS(CarrinhoFretes!G:G,CarrinhoFretes!U:U,G:G) -> 12478.5 | F5: =IF(D5=0, 0, E5/D5) -> 70.5 | G5: 160125555
A6: 15fa2e1a | B6: Milho em Grãos | C6: =SUMIFS(CarrinhoFretes!D:D,CarrinhoFretes!U:U,G:G) -> 250920 | D6: =C6/60 -> 4182 | E6: =SUMIFS(CarrinhoFretes!G:G,CarrinhoFretes!U:U,G:G) -> 292740.7 | F6: =IF(D6=0, 0, E6/D6) -> 70.000167 | G6: 160125657
A7: 6ee635db | B7: Milho em Grãos | C7: =SUMIFS(CarrinhoFretes!D:D,CarrinhoFretes!U:U,G:G) -> 122140 | D7: =C7/60 -> 2035.6667 | E7: =SUMIFS(CarrinhoFretes!G:G,CarrinhoFretes!U:U,G:G) -> 133336.38 | F7: =IF(D7=0, 0, E7/D7) -> 65.500105 | G7: 160125786
A8: f48effec | B8: Milho em Grãos | C8: =SUMIFS(CarrinhoFretes!D:D,CarrinhoFretes!U:U,G:G) -> 284480 | D8: =C8/60 -> 4741.3333 | E8: =SUMIFS(CarrinhoFretes!G:G,CarrinhoFretes!U:U,G:G) -> 310557.12 | F8: =IF(D8=0, 0, E8/D8) -> 65.499955 | G8: 170125830
A9: 4b1be3cf | B9: Milho em Grãos | C9: =SUMIFS(CarrinhoFretes!D:D,CarrinhoFretes!U:U,G:G) -> 325300 | D9: =C9/60 -> 5421.6667 | E9: =SUMIFS(CarrinhoFretes!G:G,CarrinhoFretes!U:U,G:G) -> 376398.23 | F9: =IF(D9=0, 0, E9/D9) -> 69.42482 | G9: 170125967
A10: 5131bb60 | B10: Milho em Grãos | C10: =SUMIFS(CarrinhoFretes!D:D,CarrinhoFretes!U:U,G:G) -> 578080 | D10: =C10/60 -> 9634.6667 | E10: =SUMIFS(CarrinhoFretes!G:G,CarrinhoFretes!U:U,G:G) -> 629607.08 | F10: =IF(D10=0, 0, E10/D10) -> 65.348092 | G10: 1701251075
A11: 2e326eed | B11: Milho em Grãos | C11: =SUMIFS(CarrinhoFretes!D:D,CarrinhoFretes!U:U,G:G) -> 723320 | D11: =C11/60 -> 12055.333 | E11: =SUMIFS(CarrinhoFretes!G:G,CarrinhoFretes!U:U,G:G) -> 962320.53 | F11: =IF(D11=0, 0, E11/D11) -> 79.825294 | G11: 1701251131
A12: c537334c | B12: Milho em Grãos | C12: =SUMIFS(CarrinhoFretes!D:D,CarrinhoFretes!U:U,G:G) -> 48760 | D12: =C12/60 -> 812.66667 | E12: =SUMIFS(CarrinhoFretes!G:G,CarrinhoFretes!U:U,G:G) -> 56886.9 | F12: =IF(D12=0, 0, E12/D12) -> 70.000287 | G12: 1701251261
A13: e114a584 | B13: Milho em Grãos | C13: =SUMIFS(CarrinhoFretes!D:D,CarrinhoFretes!U:U,G:G) -> 213610 | D13: =C13/60 -> 3560.1667 | E13: =SUMIFS(CarrinhoFretes!G:G,CarrinhoFretes!U:U,G:G) -> 230806.63 | F13: =IF(D13=0, 0, E13/D13) -> 64.830288 | G13: 200125137
... A231: aeeb002d | B231: Milho em Grãos | C231: =SUMIFS(CarrinhoFretes!D:D,CarrinhoFretes!U:U,G:G) -> 1011560 | D231: =C231/60 -> 16859.333 | E231: =SUMIFS(CarrinhoFretes!G:G,CarrinhoFretes!U:U,G:G) -> 854069.82 | F231: =IF(D231=0, 0, E231/D231) -> 50.658576 | G231: 26052623088

Sheet PagProdutor
A1: ID | B1: Data | C1: Produtor | D1: PedidodeCompra | E1: Conta | F1: Valor | G1: Anexo | H1: Foto | I1: Anotações | J1: MesAno | K1: PedCxMensal
A2: 468cff49 | B2: 45671 | C2: Eudas | D2: 150125254 | E2: N.Nordeste - B.Brasil | F2: 152238.45 | J2: =TEXT(B2,"MM/YYYY") -> 01/2025 | K2: =IF(B2="","",CONCATENATE("CXG-",TEXT(B2,"MMYY"))) -> CXG-0125
A3: 3449b0de | B3: 45671 | C3: Eudas | D3: 150125254 | E3: N.Nordeste - B.Brasil | F3: 152238.45 | J3: =TEXT(B3,"MM/YYYY") -> 01/2025 | K3: =IF(B3="","",CONCATENATE("CXG-",TEXT(B3,"MMYY"))) -> CXG-0125
A4: 9da228b8 | B4: 45671 | C4: Kelly Itabaianinha | D4: 160125470 | E4: N.Nordeste - B.Brasil | F4: 62370 | J4: =TEXT(B4,"MM/YYYY") -> 01/2025 | K4: =IF(B4="","",CONCATENATE("CXG-",TEXT(B4,"MMYY"))) -> CXG-0125
A5: b13aad7d | B5: 45671 | C5: Kelly Itabaianinha | D5: 160125470 | E5: N.Nordeste - B.Brasil | F5: 59780 | J5: =TEXT(B5,"MM/YYYY") -> 01/2025 | K5: =IF(B5="","",CONCATENATE("CXG-",TEXT(B5,"MMYY"))) -> CXG-0125
A6: a1fb25b6 | B6: 45671 | C6: Gabriel Balsas/Irineu | D6: 170125830 | E6: N.Nordeste - B.Brasil | F6: 7881.9 | J6: =TEXT(B6,"MM/YYYY") -> 01/2025 | K6: =IF(B6="","",CONCATENATE("CXG-",TEXT(B6,"MMYY"))) -> CXG-0125
A7: 4f337c36 | B7: 45671 | C7: Gabriel Balsas/Irineu | D7: 170125830 | E7: N.Nordeste - B.Brasil | F7: 300000 | J7: =TEXT(B7,"MM/YYYY") -> 01/2025 | K7: =IF(B7="","",CONCATENATE("CXG-",TEXT(B7,"MMYY"))) -> CXG-0125
A8: 5c5991dc | B8: 45672 | C8: Clair Feira Nova | D8: 160125555 | E8: N.Nordeste - B.Brasil | F8: 12300 | J8: =TEXT(B8,"MM/YYYY") -> 01/2025 | K8: =IF(B8="","",CONCATENATE("CXG-",TEXT(B8,"MMYY"))) -> CXG-0125
A9: 3ba26342 | B9: 45672 | C9: Clair Feira Nova | D9: 160125555 | E9: Descontos | F9: 100 | I9: Balança | J9: =TEXT(B9,"MM/YYYY") -> 01/2025 | K9: =IF(B9="","",CONCATENATE("CXG-",TEXT(B9,"MMYY"))) -> CXG-0125
A10: c44a15f9 | B10: 45672 | C10: Kelly Itabaianinha | D10: 160125470 | E10: N.Nordeste - B.Brasil | F10: 83883.33 | J10: =TEXT(B10,"MM/YYYY") -> 01/2025 | K10: =IF(B10="","",CONCATENATE("CXG-",TEXT(B10,"MMYY"))) -> CXG-0125
A11: 447d0a02 | B11: 45672 | C11: Kelly Itabaianinha | D11: 160125470 | E11: N.Nordeste - B.Brasil | F11: 80990 | J11: =TEXT(B11,"MM/YYYY") -> 01/2025 | K11: =IF(B11="","",CONCATENATE("CXG-",TEXT(B11,"MMYY"))) -> CXG-0125
A12: da1c5653 | B12: 45673 | C12: Gabriel Balsas - Gilmar | D12: 160125786 | E12: S.Grão - Sicredi | F12: 132340 | I12: Pagou 21,45 a mais | J12: =TEXT(B12,"MM/YYYY") -> 01/2025 | K12: =IF(B12="","",CONCATENATE("CXG-",TEXT(B12,"MMYY"))) -> CXG-0125
A13: 60c722b3 | B13: 45673 | C13: Gabriel Balsas - Gilmar | D13: 160125786 | E13: Pgmt Indevido | F13: -21.45 | J13: =TEXT(B13,"MM/YYYY") -> 01/2025 | K13: =IF(B13="","",CONCATENATE("CXG-",TEXT(B13,"MMYY"))) -> CXG-0125
A14: b8a482b0 | B14: 45673 | C14: José Nunes | D14: 170125967 | E14: N.Nordeste - B.Brasil | F14: 160000 | I14: Adiantamento | J14: =TEXT(B14,"MM/YYYY") -> 01/2025 | K14: =IF(B14="","",CONCATENATE("CXG-",TEXT(B14,"MMYY"))) -> CXG-0125
A15: c8c449b5 | B15: 45673 | C15: Gabriel Balsas/Irineu | D15: 170125830 | E15: N.Nordeste - B.Brasil | F15: 304.72 | J15: =TEXT(B15,"MM/YYYY") -> 01/2025 | K15: =IF(B15="","",CONCATENATE("CXG-",TEXT(B15,"MMYY"))) -> CXG-0125
A16: 15abe9b2 | B16: 45674 | C16: Kelly Itabaianinha | D16: 160125470 | E16: S.Grão - Sicredi | F16: 74526.67 | J16: =TEXT(B16,"MM/YYYY") -> 01/2025 | K16: =IF(B16="","",CONCATENATE("CXG-",TEXT(B16,"MMYY"))) -> CXG-0125
A17: b4cf1ade | B17: 45675 | C17: Kelly Itabaianinha | D17: 160125470 | E17: S.Grão - Sicredi | F17: 150000 | J17: =TEXT(B17,"MM/YYYY") -> 01/2025 | K17: =IF(B17="","",CONCATENATE("CXG-",TEXT(B17,"MMYY"))) -> CXG-0125
A18: 9378dcb2 | B18: 45675 | C18: Kelly Itabaianinha | D18: 160125470 | E18: S.Grão - Sicredi | F18: 71713 | J18: =TEXT(B18,"MM/YYYY") -> 01/2025 | K18: =IF(B18="","",CONCATENATE("CXG-",TEXT(B18,"MMYY"))) -> CXG-0125
A19: d7b6148d | B19: 45675 | C19: Edenilson Balsas | D19: 200125137 | E19: S.Grão - Sicredi | F19: 73760 | J19: =TEXT(B19,"MM/YYYY") -> 01/2025 | K19: =IF(B19="","",CONCATENATE("CXG-",TEXT(B19,"MMYY"))) -> CXG-0125
A20: 2f4ad352 | B20: 45677 | C20: Marcos Roco Graccho | D20: 160125657 | E20: Descontos | F20: 400 | I20: Balança | J20: =TEXT(B20,"MM/YYYY") -> 01/2025 | K20: =IF(B20="","",CONCATENATE("CXG-",TEXT(B20,"MMYY"))) -> CXG-0125
A21: f63824f3 | B21: 45677 | C21: Marcos Roco Graccho | D21: 160125657 | E21: Descontos | F21: 200 | I21: Extratora | J21: =TEXT(B21,"MM/YYYY") -> 01/2025 | K21: =IF(B21="","",CONCATENATE("CXG-",TEXT(B21,"MMYY"))) -> CXG-0125
A22: 805452bf | B22: 45677 | C22: José Nunes | D22: 170125967 | E22: Descontos | F22: 500 | I22: Balança | J22: =TEXT(B22,"MM/YYYY") -> 01/2025 | K22: =IF(B22="","",CONCATENATE("CXG-",TEXT(B22,"MMYY"))) -> CXG-0125
A23: 90ace94d | B23: 45677 | C23: Edenilson Balsas | D23: 200125137 | E23: S.Grão - Sicredi | F23: 50000 | J23: =TEXT(B23,"MM/YYYY") -> 01/2025 | K23: =IF(B23="","",CONCATENATE("CXG-",TEXT(B23,"MMYY"))) -> CXG-0125
A24: 985daef3 | B24: 45677 | C24: Edenilson Balsas | D24: 200125137 | E24: S.Grão - Sicredi | F24: 28848 | J24: =TEXT(B24,"MM/YYYY") -> 01/2025 | K24: =IF(B24="","",CONCATENATE("CXG-",TEXT(B24,"MMYY"))) -> CXG-0125
A25: 7813d987 | B25: 45677 | C25: Abrel | D25: 1701251261 | E25: S.Grão - Sicredi | F25: 56886 | J25: =TEXT(B25,"MM/YYYY") -> 01/2025 | K25: =IF(B25="","",CONCATENATE("CXG-",TEXT(B25,"MMYY"))) -> CXG-0125
A26: 79200aa7 | B26: 45677 | C26: Abrel | D26: 1701251261 | E26: Descontos | F26: 0.9 | J26: =TEXT(B26,"MM/YYYY") -> 01/2025 | K26: =IF(B26="","",CONCATENATE("CXG-",TEXT(B26,"MMYY"))) -> CXG-0125
A27: 262cc249 | B27: 45677 | C27: Marcos Roco Graccho | D27: 160125657 | E27: S.Grão - Sicredi | F27: 150000 | J27: =TEXT(B27,"MM/YYYY") -> 01/2025 | K27: =IF(B27="","",CONCATENATE("CXG-",TEXT(B27,"MMYY"))) -> CXG-0125
A28: be270f32 | B28: 45677 | C28: Gabriel Balsas - Gilmar | D28: 1701251075 | E28: S.Grão - Sicredi | F28: 150000 | J28: =TEXT(B28,"MM/YYYY") -> 01/2025 | K28: =IF(B28="","",CONCATENATE("CXG-",TEXT(B28,"MMYY"))) -> CXG-0125
A29: 6f333624 | B29: 45677 | C29: Marcos Roco Graccho | D29: 160125657 | E29: S.Grão - Sicredi | F29: 90000 | J29: =TEXT(B29,"MM/YYYY") -> 01/2025 | K29: =IF(B29="","",CONCATENATE("CXG-",TEXT(B29,"MMYY"))) -> CXG-0125
A30: 2d67d5fb | B30: 45677 | C30: Milho Conde | D30: 2001251545 | E30: N.Nordeste - B.Brasil | F30: 140000 | J30: =TEXT(B30,"MM/YYYY") -> 01/2025 | K30: =IF(B30="","",CONCATENATE("CXG-",TEXT(B30,"MMYY"))) -> CXG-0125
A31: f96843ad | B31: 45678 | C31: Gabriel Balsas - Gilmar | D31: 1701251075 | E31: Descontos | F31: 463 | J31: =TEXT(B31,"MM/YYYY") -> 01/2025 | K31: =IF(B31="","",CONCATENATE("CXG-",TEXT(B31,"MMYY"))) -> CXG-0125
A32: 54cfbd21 | B32: 45679 | C32: Kelly Itabaianinha | D32: 160125470 | E32: Descontos | F32: 0.7 | J32: =TEXT(B32,"MM/YYYY") -> 01/2025 | K32: =IF(B32="","",CONCATENATE("CXG-",TEXT(B32,"MMYY"))) -> CXG-0125
A33: 8260c2ce | B33: 45679 | C33: Edenilson Balsas | D33: 200125137 | E33: N.Nordeste - B.Brasil | F33: 1192.25 | J33: =TEXT(B33,"MM/YYYY") -> 01/2025 | K33: =IF(B33="","",CONCATENATE("CXG-",TEXT(B33,"MMYY"))) -> CXG-0125
A34: 1fdfc2c6 | B34: 45679 | C34: José Nunes | D34: 170125967 | E34: S.Grão - Bradesco | F34: 215898 | J34: =TEXT(B34,"MM/YYYY") -> 01/2025 | K34: =IF(B34="","",CONCATENATE("CXG-",TEXT(B34,"MMYY"))) -> CXG-0125
A35: b3d8c0a7 | B35: 45679 | C35: José Nunes | D35: 170125967 | E35: Descontos | F35: 0.23 | J35: =TEXT(B35,"MM/YYYY") -> 01/2025 | K35: =IF(B35="","",CONCATENATE("CXG-",TEXT(B35,"MMYY"))) -> CXG-0125
A36: 3901d5f0 | B36: 45679 | C36: Samuel | D36: 2201251666 | E36: N.Nordeste - B.Brasil | F36: 700 | I36: Extratora | J36: =TEXT(B36,"MM/YYYY") -> 01/2025 | K36: =IF(B36="","",CONCATENATE("CXG-",TEXT(B36,"MMYY"))) -> CXG-0125
A37: 6290b1fb | B37: 45679 | C37: Francisco Benjamin | D37: 160125346 | E37: Santiagro | F37: 45071.66 | J37: =TEXT(B37,"MM/YYYY") -> 01/2025 | K37: =IF(B37="","",CONCATENATE("CXG-",TEXT(B37,"MMYY"))) -> CXG-0125
A38: 9474cee6 | B38: 45679 | C38: Gabriel Balsas/Irineu | D38: 2001251462 | E38: N.Nordeste - B.Brasil | F38: 300000 | J38: =TEXT(B38,"MM/YYYY") -> 01/2025 | K38: =IF(B38="","",CONCATENATE("CXG-",TEXT(B38,"MMYY"))) -> CXG-0125
A39: 34161587 | B39: 45680 | C39: Milho Conde | D39: 2001251545 | E39: N.Nordeste - B.Brasil | F39: 9000 | J39: =TEXT(B39,"MM/YYYY") -> 01/2025 | K39: =IF(B39="","",CONCATENATE("CXG-",TEXT(B39,"MMYY"))) -> CXG-0125
A40: a24494bb | B40: 45680 | C40: Kelly Itabaianinha | D40: 160125470 | E40: N.Nordeste - B.Brasil | F40: 150000 | J40: =TEXT(B40,"MM/YYYY") -> 01/2025 | K40: =IF(B40="","",CONCATENATE("CXG-",TEXT(B40,"MMYY"))) -> CXG-0125
A41: 829b2eb4 | B41: 45680 | C41: Lucas LEM | D41: 2301251745 | E41: S.Grão - Sicredi | F41: 46900 | J41: =TEXT(B41,"MM/YYYY") -> 01/2025 | K41: =IF(B41="","",CONCATENATE("CXG-",TEXT(B41,"MMYY"))) -> CXG-0125
A42: 55d8ba28 | B42: 45681 | C42: Marcos Roco Graccho | D42: 160125657 | E42: S.Grão - Sicredi | F42: 52140 | J42: =TEXT(B42,"MM/YYYY") -> 01/2025 | K42: =IF(B42="","",CONCATENATE("CXG-",TEXT(B42,"MMYY"))) -> CXG-0125
A43: b8cd6351 | B43: 45681 | C43: Marcos Roco Graccho | D43: 160125657 | E43: Descontos | F43: 0.7 | J43: =TEXT(B43,"MM/YYYY") -> 01/2025 | K43: =IF(B43="","",CONCATENATE("CXG-",TEXT(B43,"MMYY"))) -> CXG-0125
A44: 3d3c0a63 | B44: 45681 | C44: Francisco Benjamin | D44: 160125346 | E44: Santiagro | F44: 24114 | J44: =TEXT(B44,"MM/YYYY") -> 01/2025 | K44: =IF(B44="","",CONCATENATE("CXG-",TEXT(B44,"MMYY"))) -> CXG-0125
A45: 1a72517c | B45: 45681 | C45: Kelly Itabaianinha | D45: 160125470 | E45: Santiagro | F45: 87977 | J45: =TEXT(B45,"MM/YYYY") -> 01/2025 | K45: =IF(B45="","",CONCATENATE("CXG-",TEXT(B45,"MMYY"))) -> CXG-0125
A47: 5f9f13d0 | B47: 45681 | C47: Gabriel Balsas/Irineu | D47: 2001251462 | E47: Santiagro | F47: 22190 | J47: =TEXT(B47,"MM/YYYY") -> 01/2025 | K47: =IF(B47="","",CONCATENATE("CXG-",TEXT(B47,"MMYY"))) -> CXG-0125
A48: 1519c0f3 | B48: 45682 | C48: Samuel | D48: 2201251666 | E48: Branco - B.Brasil | F48: 450 | I48: Extratora | J48: =TEXT(B48,"MM/YYYY") -> 01/2025 | K48: =IF(B48="","",CONCATENATE("CXG-",TEXT(B48,"MMYY"))) -> CXG-0125
A49: 3a562a76 | B49: 45682 | C49: George Tocantins | D49: 2501251862 | E49: N.Nordeste - B.Brasil | F49: 40918 | J49: =TEXT(B49,"MM/YYYY") -> 01/2025 | K49: =IF(B49="","",CONCATENATE("CXG-",TEXT(B49,"MMYY"))) -> CXG-0125
A50: ce93aa46 | B50: 45684 | C50: Samuel | D50: 2201251666 | E50: S.Grão - Sicredi | F50: 400 | J50: =TEXT(B50,"MM/YYYY") -> 01/2025 | K50: =IF(B50="","",CONCATENATE("CXG-",TEXT(B50,"MMYY"))) -> CXG-0125
A51: daa399be | B51: 45684 | C51: Samuel | D51: 2201251666 | E51: S.Grão - Sicredi | F51: 300 | J51: =TEXT(B51,"MM/YYYY") -> 01/2025 | K51: =IF(B51="","",CONCATENATE("CXG-",TEXT(B51,"MMYY"))) -> CXG-0125
A52: 4bb8e16b | B52: 45684 | C52: Edenilson Balsas | D52: 200125137 | E52: S.Grão - Sicredi | F52: 77006.16 | J52: =TEXT(B52,"MM/YYYY") -> 01/2025 | K52: =IF(B52="","",CONCATENATE("CXG-",TEXT(B52,"MMYY"))) -> CXG-0125
A53: b9ee3dc7 | B53: 45684 | C53: Edenilson Balsas | D53: 200125137 | E53: Descontos | F53: 0.22 | I53: Zerado até Hallan | J53: =TEXT(B53,"MM/YYYY") -> 01/2025 | K53: =IF(B53="","",CONCATENATE("CXG-",TEXT(B53,"MMYY"))) -> CXG-0125
A54: 05165f78 | B54: 45685 | C54: Milho Conde | D54: 2001251545 | E54: N.Nordeste - B.Brasil | F54: 98000 | J54: =TEXT(B54,"MM/YYYY") -> 01/2025 | K54: =IF(B54="","",CONCATENATE("CXG-",TEXT(B54,"MMYY"))) -> CXG-0125
A55: 707b677b | B55: 45686 | C55: Samuel | D55: 2201251666 | E55: N.Nordeste - B.Brasil | F55: 7720 | J55: =TEXT(B55,"MM/YYYY") -> 01/2025 | K55: =IF(B55="","",CONCATENATE("CXG-",TEXT(B55,"MMYY"))) -> CXG-0125
A56: e1bd1ffe | B56: 45686 | C56: Kelly Itabaianinha | D56: 160125470 | E56: N.Nordeste - B.Brasil | F56: 850 | I56: Extratora | J56: =TEXT(B56,"MM/YYYY") -> 01/2025 | K56: =IF(B56="","",CONCATENATE("CXG-",TEXT(B56,"MMYY"))) -> CXG-0125
A57: ea0647d4 | B57: 45686 | C57: Gabriel Balsas/Irineu | D57: 2001251462 | E57: N.Nordeste - B.Brasil | F57: 200000 | J57: =TEXT(B57,"MM/YYYY") -> 01/2025 | K57: =IF(B57="","",CONCATENATE("CXG-",TEXT(B57,"MMYY"))) -> CXG-0125
A58: 042d2a99 | B58: 45686 | C58: Gabriel Balsas - Gilmar | D58: 1701251075 | E58: N.Nordeste - B.Brasil | F58: 150000 | J58: =TEXT(B58,"MM/YYYY") -> 01/2025 | K58: =IF(B58="","",CONCATENATE("CXG-",TEXT(B58,"MMYY"))) -> CXG-0125
A59: 5086f19b | B59: 45687 | C59: Milho Conde | D59: 2001251545 | E59: N.Nordeste - B.Brasil | F59: 255000 | J59: =TEXT(B59,"MM/YYYY") -> 01/2025 | K59: =IF(B59="","",CONCATENATE("CXG-",TEXT(B59,"MMYY"))) -> CXG-0125
A60: 03cfb81f | B60: 45687 | C60: Gabriel Balsas - Gilmar | D60: 1701251075 | E60: N.Nordeste - B.Brasil | F60: 127000 | J60: =TEXT(B60,"MM/YYYY") -> 01/2025 | K60: =IF(B60="","",CONCATENATE("CXG-",TEXT(B60,"MMYY"))) -> CXG-0125
A61: 050b4a06 | B61: 45688 | C61: Gabriel Balsas/Irineu | D61: 2001251462 | E61: N.Nordeste - B.Brasil | F61: 150000 | J61: =TEXT(B61,"MM/YYYY") -> 01/2025 | K61: =IF(B61="","",CONCATENATE("CXG-",TEXT(B61,"MMYY"))) -> CXG-0125
A62: 9fd646c0 | B62: 45672 | C62: Francisco Benjamin | D62: 160125346 | E62: Adiantamento | F62: 12855.34 | I62: Comprovante - de 346.900,00 - Ita Grãos | J62: =TEXT(B62,"MM/YYYY") -> 01/2025 | K62: =IF(B62="","",CONCATENATE("CXG-",TEXT(B62,"MMYY"))) -> CXG-0125
A63: f490ee65 | B63: 45667 | C63: Milho Conde | D63: 2001251545 | E63: Adiantamento | F63: 46411.42 | I63: Desconto - 50.000,00 - Neto BB | J63: =TEXT(B63,"MM/YYYY") -> 01/2025 | K63: =IF(B63="","",CONCATENATE("CXG-",TEXT(B63,"MMYY"))) -> CXG-0125
A64: 6a2ad91a | B64: 45691 | C64: Carlinhos | D64: 0302252193 | E64: N.Nordeste - B.Brasil | F64: 60000 | I64: Adiantamento | J64: =TEXT(B64,"MM/YYYY") -> 02/2025 | K64: =IF(B64="","",CONCATENATE("CXG-",TEXT(B64,"MMYY"))) -> CXG-0225
A65: 2573288b | B65: 45691 | C65: Carlinhos | D65: 0302252193 | E65: N.Nordeste - B.Brasil | F65: 40000 | I65: Adiantamento | J65: =TEXT(B65,"MM/YYYY") -> 02/2025 | K65: =IF(B65="","",CONCATENATE("CXG-",TEXT(B65,"MMYY"))) -> CXG-0225
A66: 308645c0 | B66: 45691 | C66: Samuel | D66: 2201251666 | E66: S.Grão - Sicredi | F66: 78795.17 | J66: =TEXT(B66,"MM/YYYY") -> 02/2025 | K66: =IF(B66="","",CONCATENATE("CXG-",TEXT(B66,"MMYY"))) -> CXG-0225
A67: fe398eaa | B67: 45691 | C67: Samuel | D67: 2201251666 | E67: S.Grão - Sicredi | F67: 147054.03 | J67: =TEXT(B67,"MM/YYYY") -> 02/2025 | K67: =IF(B67="","",CONCATENATE("CXG-",TEXT(B67,"MMYY"))) -> CXG-0225
A68: b0620469 | B68: 45691 | C68: Clair Feira Nova | D68: 160125555 | E68: Descontos | F68: 78.5 | J68: =TEXT(B68,"MM/YYYY") -> 02/2025 | K68: =IF(B68="","",CONCATENATE("CXG-",TEXT(B68,"MMYY"))) -> CXG-0225
A69: a6815c42 | B69: 45691 | C69: Eudas | D69: 150125254 | E69: Descontos | F69: 1087.42 | J69: =TEXT(B69,"MM/YYYY") -> 02/2025 | K69: =IF(B69="","",CONCATENATE("CXG-",TEXT(B69,"MMYY"))) -> CXG-0225
A70: 1ad1f3ce | B70: 45692 | C70: Gabriel Balsas - Gilmar | D70: 1701251075 | E70: Descontos | F70: 6.58 | J70: =TEXT(B70,"MM/YYYY") -> 02/2025 | K70: =IF(B70="","",CONCATENATE("CXG-",TEXT(B70,"MMYY"))) -> CXG-0225
A71: 219d7ebc | B71: 45692 | C71: Carlinhos | D71: 0302252193 | E71: N.Nordeste - B.Brasil | F71: 100000 | J71: =TEXT(B71,"MM/YYYY") -> 02/2025 | K71: =IF(B71="","",CONCATENATE("CXG-",TEXT(B71,"MMYY"))) -> CXG-0225
A72: 5521db20 | B72: 45693 | C72: Gabriel Balsas/Irineu | D72: 2001251462 | E72: N.Nordeste - B.Brasil | F72: 142800 | J72: =TEXT(B72,"MM/YYYY") -> 02/2025 | K72: =IF(B72="","",CONCATENATE("CXG-",TEXT(B72,"MMYY"))) -> CXG-0225
A73: 3f85a560 | B73: 45693 | C73: Gabriel Balsas/Irineu | D73: 2001251462 | E73: Descontos | F73: 1.47 | J73: =TEXT(B73,"MM/YYYY") -> 02/2025 | K73: =IF(B73="","",CONCATENATE("CXG-",TEXT(B73,"MMYY"))) -> CXG-0225
A74: 887a110d | B74: 45693 | C74: Gabriel Balsas - Pedro | D74: 0502252287 | E74: N.Nordeste - B.Brasil | F74: 80000 | J74: =TEXT(B74,"MM/YYYY") -> 02/2025 | K74: =IF(B74="","",CONCATENATE("CXG-",TEXT(B74,"MMYY"))) -> CXG-0225
A75: d6a17d63 | B75: 45693 | C75: Samuel | D75: 2201251666 | E75: S.Grão - Sicredi | F75: 55900 | J75: =TEXT(B75,"MM/YYYY") -> 02/2025 | K75: =IF(B75="","",CONCATENATE("CXG-",TEXT(B75,"MMYY"))) -> CXG-0225
A76: 6b93139a | B76: 45694 | C76: Carlinhos | D76: 0302252193 | E76: Santiagro | F76: 100000 | J76: =TEXT(B76,"MM/YYYY") -> 02/2025 | K76: =IF(B76="","",CONCATENATE("CXG-",TEXT(B76,"MMYY"))) -> CXG-0225
A77: b85cc2da | B77: 45694 | C77: Gabriel Balsas - Gilmar | D77: 1701251075 | E77: Santiagro | F77: 190000 | J77: =TEXT(B77,"MM/YYYY") -> 02/2025 | K77: =IF(B77="","",CONCATENATE("CXG-",TEXT(B77,"MMYY"))) -> CXG-0225
... A82: 2931230f | B82: 45696 | C82: Thiago Feira Nova | D82: 3001252079 | E82: N.Nordeste - B.Brasil | F82: 180000 | J82: =TEXT(B82,"MM/YYYY") -> 02/2025 | K82: =IF(B82="","",CONCATENATE("CXG-",TEXT(B82,"MMYY"))) -> CXG-0225
A83: aae6da59 | B83: 45698 | C83: Samuel | D83: 2201251666 | E83: Descontos | F83: 360 | I83: Balança | J83: =TEXT(B83,"MM/YYYY") -> 02/2025 | K83: =IF(B83="","",CONCATENATE("CXG-",TEXT(B83,"MMYY"))) -> CXG-0225
A84: c77c440b | B84: 45698 | C84: Thiago Feira Nova | D84: 3001252079 | E84: Santiagro | F84: 93471.78 | J84: =TEXT(B84,"MM/YYYY") -> 02/2025 | K84: =IF(B84="","",CONCATENATE("CXG-",TEXT(B84,"MMYY"))) -> CXG-0225
A85: 554cd4b5 | B85: 45699 | C85: George Tocantins | D85: 2501251862 | E85: Descontos | F85: -0.2 | J85: =TEXT(B85,"MM/YYYY") -> 02/2025 | K85: =IF(B85="","",CONCATENATE("CXG-",TEXT(B85,"MMYY"))) -> CXG-0225
A86: 8383fdaf | B86: 45699 | C86: Milho Conde | D86: 2001251545 | E86: N.Nordeste - B.Brasil | F86: 120000 | I86: Comprovante de 145.000,00 | J86: =TEXT(B86,"MM/YYYY") -> 02/2025 | K86: =IF(B86="","",CONCATENATE("CXG-",TEXT(B86,"MMYY"))) -> CXG-0225
A87: a0727a5e | B87: 45699 | C87: Carlinhos | D87: 0302252193 | E87: N.Nordeste - B.Brasil | F87: 25000 | I87: Comprovante de 145.000,00 | J87: =TEXT(B87,"MM/YYYY") -> 02/2025 | K87: =IF(B87="","",CONCATENATE("CXG-",TEXT(B87,"MMYY"))) -> CXG-0225
A88: 1429a368 | B88: 45700 | C88: Gabriel Balsas - Pedro | D88: 0502252287 | E88: N.Nordeste - B.Brasil | F88: 70336.66 | J88: =TEXT(B88,"MM/YYYY") -> 02/2025 | K88: =IF(B88="","",CONCATENATE("CXG-",TEXT(B88,"MMYY"))) -> CXG-0225
A89: 758c1678 | B89: 45700 | C89: Milho Conde | D89: 2001251545 | E89: N.Nordeste - B.Brasil | F89: 7500 | J89: =TEXT(B89,"MM/YYYY") -> 02/2025 | K89: =IF(B89="","",CONCATENATE("CXG-",TEXT(B89,"MMYY"))) -> CXG-0225
A90: 4a0df31d | B90: 45700 | C90: Ze de Gerino | D90: 2801251960 | E90: N.Nordeste - B.Brasil | F90: 3006.44 | J90: =TEXT(B90,"MM/YYYY") -> 02/2025 | K90: =IF(B90="","",CONCATENATE("CXG-",TEXT(B90,"MMYY"))) -> CXG-0225
A91: bc6897eb | B91: 45700 | C91: Gabriel Balsas - Gilmar | D91: 1701251075 | E91: N.Nordeste - B.Brasil | F91: 9247 | J91: =TEXT(B91,"MM/YYYY") -> 02/2025 | K91: =IF(B91="","",CONCATENATE("CXG-",TEXT(B91,"MMYY"))) -> CXG-0225
A92: 0e4d0960 | B92: 45700 | C92: Gabriel Balsas - Gilmar | D92: 1701251075 | E92: Descontos | F92: 0.1 | J92: =TEXT(B92,"MM/YYYY") -> 02/2025 | K92: =IF(B92="","",CONCATENATE("CXG-",TEXT(B92,"MMYY"))) -> CXG-0225
A93: 1876df51 | B93: 45701 | C93: Guilherme Balsas | D93: 1302252597 | E93: N.Nordeste - B.Brasil | F93: 94768 | J93: =TEXT(B93,"MM/YYYY") -> 02/2025 | K93: =IF(B93="","",CONCATENATE("CXG-",TEXT(B93,"MMYY"))) -> CXG-0225
A94: d48d25f9 | B94: 45701 | C94: Guilherme Balsas | D94: 1302252597 | E94: Santiagro | F94: 91439.18 | J94: =TEXT(B94,"MM/YYYY") -> 02/2025 | K94: =IF(B94="","",CONCATENATE("CXG-",TEXT(B94,"MMYY"))) -> CXG-0225
A95: 5160a594 | B95: 45701 | C95: Guilherme Balsas | D95: 1302252597 | E95: N.Nordeste - B.Brasil | F95: 1491.7 | J95: =TEXT(B95,"MM/YYYY") -> 02/2025 | K95: =IF(B95="","",CONCATENATE("CXG-",TEXT(B95,"MMYY"))) -> CXG-0225
A96: e3701194 | B96: 45701 | C96: Thiago Feira Nova | D96: 3001252079 | E96: N.Nordeste - B.Brasil | F96: 100000 | J96: =TEXT(B96,"MM/YYYY") -> 02/2025 | K96: =IF(B96="","",CONCATENATE("CXG-",TEXT(B96,"MMYY"))) -> CXG-0225
A97: ce20f638 | B97: 45702 | C97: Gabriel Melo - Itabi | D97: 140225260 | E97: N.Nordeste - B.Brasil | F97: 28000 | J97: =TEXT(B97,"MM/YYYY") -> 02/2025 | K97: =IF(B97="","",CONCATENATE("CXG-",TEXT(B97,"MMYY"))) -> CXG-0225
A98: 8b6a47b2 | B98: 45702 | C98: Carlinhos | D98: 0302252193 | E98: Terceiros | F98: 60000 | I98: Pagou a Santa Cruz | J98: =TEXT(B98,"MM/YYYY") -> 02/2025 | K98: =IF(B98="","",CONCATENATE("CXG-",TEXT(B98,"MMYY"))) -> CXG-0225
A99: e4764d46 | B99: 45702 | C99: Carlinhos | D99: 0302252193 | E99: Santiagro | F99: 80210 | J99: =TEXT(B99,"MM/YYYY") -> 02/2025 | K99: =IF(B99="","",CONCATENATE("CXG-",TEXT(B99,"MMYY"))) -> CXG-0225
A100: 191bf7c7 | B100: 45702 | C100: Carlinhos | D100: 0302252193 | E100: N.Nordeste - B.Brasil | F100: 111190 | J100: =TEXT(B100,"MM/YYYY") -> 02/2025 | K100: =IF(B100="","",CONCATENATE("CXG-",TEXT(B100,"MMYY"))) -> CXG-0225
A101: 5d4e180c | B101: 45702 | C101: Carlinhos | D101: 0302252193 | E101: Descontos | F101: 0.01 | J101: =TEXT(B101,"MM/YYYY") -> 02/2025 | K101: =IF(B101="","",CONCATENATE("CXG-",TEXT(B101,"MMYY"))) -> CXG-0225
A102: cbde9715 | B102: 45702 | C102: Thiago Feira Nova | D102: 3001252079 | E102: N.Nordeste - B.Brasil | F102: 25000 | J102: =TEXT(B102,"MM/YYYY") -> 02/2025 | K102: =IF(B102="","",CONCATENATE("CXG-",TEXT(B102,"MMYY"))) -> CXG-0225
A103: 737bd8d2 | B103: 45703 | C103: Elizabete | D103: 1102252412 | E103: Santiagro | F103: 193000 | J103: =TEXT(B103,"MM/YYYY") -> 02/2025 | K103: =IF(B103="","",CONCATENATE("CXG-",TEXT(B103,"MMYY"))) -> CXG-0225
A104: ed5c1a42 | B104: 45705 | C104: Gabriel Melo - Itabi | D104: 140225260 | E104: Santiagro | F104: 100000 | J104: =TEXT(B104,"MM/YYYY") -> 02/2025 | K104: =IF(B104="","",CONCATENATE("CXG-",TEXT(B104,"MMYY"))) -> CXG-0225
A105: ae941853 | B105: 45705 | C105: Gabriel Melo - Itabi | D105: 140225260 | E105: Santiagro | F105: 82914 | J105: =TEXT(B105,"MM/YYYY") -> 02/2025 | K105: =IF(B105="","",CONCATENATE("CXG-",TEXT(B105,"MMYY"))) -> CXG-0225
...

Sheet PedComissão
A1: ID | B1: Data | C1: Parceiro | D1: PedidodeCompra | E1: Valor | F1: Valor Pago | G1: Valor Pendente | H1: Anotações | I1: PedComissao | J1: MesAno | K1: PedCxMensal
A2: 031ffa5f | B2: 45673 | C2: Gabriel Balsas | D2: 160125786 | E2: 1017.83 | F2: =SUMIFS(PagComisao!F:F,PagComisao!C:C,I:I) -> 1017.83 | G2: =E2-F2 -> 0 | I2: 160125218 | J2: =TEXT(B2,"MM/YYYY") -> 01/2025 | K2: =IF(B2="","",CONCATENATE("CXG-",TEXT(B2,"MMYY"))) -> CXG-0125
A3: 1b38353a | B3: 45671 | C3: Gabriel Balsas | D3: 170125830 | E3: 2370.5 | F3: =SUMIFS(PagComisao!F:F,PagComisao!C:C,I:I) -> 2370.5 | G3: =E3-F3 -> 0 | H3: Descontos Comprovante de 5 Mil da Implantação | I3: 170125334 | J3: =TEXT(B3,"MM/YYYY") -> 01/2025 | K3: =IF(B3="","",CONCATENATE("CXG-",TEXT(B3,"MMYY"))) -> CXG-0125
A4: 16948693 | B4: 45678 | C4: Gabriel Balsas | D4: 2001251462 | E4: 2427.39 | F4: =SUMIFS(PagComisao!F:F,PagComisao!C:C,I:I) -> 2427.39 | G4: =E4-F4 -> 0 | H4: Comprovante 3.122,09 | I4: 220125446 | J4: =TEXT(B4,"MM/YYYY") -> 01/2025 | K4: =IF(B4="","",CONCATENATE("CXG-",TEXT(B4,"MMYY"))) -> CXG-0125
A5: 5a09db25 | B5: 45678 | C5: Gabriel Balsas | D5: 1701251075 | E5: 694.7 | F5: =SUMIFS(PagComisao!F:F,PagComisao!C:C,I:I) -> 694.7 | G5: =E5-F5 -> 0 | H5: Comprovante 3.122,09 | I5: 220125578 | J5: =TEXT(B5,"MM/YYYY") -> 01/2025 | K5: =IF(B5="","",CONCATENATE("CXG-",TEXT(B5,"MMYY"))) -> CXG-0125
A6: eebc0e78 | B6: 45684 | C6: Gabriel Balsas | D6: 2001251462 | E6: 1334.09 | F6: =SUMIFS(PagComisao!F:F,PagComisao!C:C,I:I) -> 1334.09 | G6: =E6-F6 -> 0 | I6: 280125623 | J6: =TEXT(B6,"MM/YYYY") -> 01/2025 | K6: =IF(B6="","",CONCATENATE("CXG-",TEXT(B6,"MMYY"))) -> CXG-0125
A7: dc56a0ca | B7: 45684 | C7: Gabriel Balsas | D7: 1701251075 | E7: 259.2 | F7: =SUMIFS(PagComisao!F:F,PagComisao!C:C,I:I) -> 259.2 | G7: =E7-F7 -> 0 | I7: 280125714 | J7: =TEXT(B7,"MM/YYYY") -> 01/2025 | K7: =IF(B7="","",CONCATENATE("CXG-",TEXT(B7,"MMYY"))) -> CXG-0125
A8: d7738f85 | B8: 45691 | C8: Gabriel Balsas | D8: 1701251075 | E8: 1016.9 | F8: =SUMIFS(PagComisao!F:F,PagComisao!C:C,I:I) -> 1016.9 | G8: =E8-F8 -> 0 | I8: 030225850 | J8: =TEXT(B8,"MM/YYYY") -> 02/2025 | K8: =IF(B8="","",CONCATENATE("CXG-",TEXT(B8,"MMYY"))) -> CXG-0225
A9: d40643b3 | B9: 45692 | C9: Gabriel Balsas | D9: 1701251075 | E9: 919.6 | F9: =SUMIFS(PagComisao!F:F,PagComisao!C:C,I:I) -> 919.6 | G9: =E9-F9 -> 0 | H9: Carros: Rogerio, Carlos Aguiar e Douglas | I9: 040225998 | J9: =TEXT(B9,"MM/YYYY") -> 02/2025 | K9: =IF(B9="","",CONCATENATE("CXG-",TEXT(B9,"MMYY"))) -> CXG-0225
A10: f0f27a42 | B10: 45699 | C10: Gabriel Balsas | D10: 0502252287 | E10: 1173.85 | F10: =SUMIFS(PagComisao!F:F,PagComisao!C:C,I:I) -> 1173.85 | G10: =E10-F10 -> 0 | H10: Jonh e Regivaldo | I10: 1202251081 | J10: =TEXT(B10,"MM/YYYY") -> 02/2025 | K10: =IF(B10="","",CONCATENATE("CXG-",TEXT(B10,"MMYY"))) -> CXG-0225
A11: 5a6e4c1c | B11: 45701 | C11: Gabriel Balsas | D11: 1302252597 | E11: 1478.05 | F11: 1478.05 | G11: =E11-F11 -> 0 | H11: 3 Carros, Gustavo, Heder e Pereirinha. | I11: 1302251195 | J11: =TEXT(B11,"MM/YYYY") -> 02/2025 | K11: =IF(B11="","",CONCATENATE("CXG-",TEXT(B11,"MMYY"))) -> CXG-0225
A12: be8b61ae | B12: 45709 | C12: Guilherme | D12: 1302252597 | E12: 1840.33 | F12: =SUMIFS(PagComisao!F:F,PagComisao!C:C,I:I) -> 1840.33 | G12: =E12-F12 -> 0 | I12: 2402251240 | J12: =TEXT(B12,"MM/YYYY") -> 02/2025 | K12: =IF(B12="","",CONCATENATE("CXG-",TEXT(B12,"MMYY"))) -> CXG-0225
A13: 55a7f0b5 | B13: 45734 | C13: Gabriel Balsas | D13: 1003253656 | E13: 1887.69 | F13: =SUMIFS(PagComisao!F:F,PagComisao!C:C,I:I) -> 1887.69 | G13: =E13-F13 -> 0 | H13: Comissão Até o Carro de Valtemir - CX | I13: 1803251329 | J13: =TEXT(B13,"MM/YYYY") -> 03/2025 | K13: =IF(B13="","",CONCATENATE("CXG-",TEXT(B13,"MMYY"))) -> CXG-0325
A14: e7ebc9f7 | B14: 45734 | C14: Gabriel Balsas | D14: 1003253515 | E14: 4624.08 | F14: =SUMIFS(PagComisao!F:F,PagComisao!C:C,I:I) -> 4624.08 | G14: =E14-F14 -> 0 | H14: Comissão Até o Carro Andson Paiva | I14: 1803251492 | J14: =TEXT(B14,"MM/YYYY") -> 03/2025 | K14: =IF(B14="","",CONCATENATE("CXG-",TEXT(B14,"MMYY"))) -> CXG-0325
A15: 2092b041 | B15: 45782 | C15: Guilherme | D15: 0505255299 | E15: 2000 | F15: =SUMIFS(PagComisao!F:F,PagComisao!C:C,I:I) -> 2000 | G15: =E15-F15 -> 0 | I15: 0705251587 | J15: =TEXT(B15,"MM/YYYY") -> 05/2025 | K15: =IF(B15="","",CONCATENATE("CXG-",TEXT(B15,"MMYY"))) -> CXG-0525
A16: 79d6da61 | B16: 45785 | C16: Guilherme | D16: 0505255299 | E16: 1000 | F16: =SUMIFS(PagComisao!F:F,PagComisao!C:C,I:I) -> 1000 | G16: =E16-F16 -> 0 | I16: 0905251662 | J16: =TEXT(B16,"MM/YYYY") -> 05/2025 | K16: =IF(B16="","",CONCATENATE("CXG-",TEXT(B16,"MMYY"))) -> CXG-0525
A17: 445d10d6 | B17: 45790 | C17: Gabriel Balsas | D17: 1205255544 | E17: 586 | F17: =SUMIFS(PagComisao!F:F,PagComisao!C:C,I:I) -> 586 | G17: =E17-F17 -> 0 | I17: 1405251713 | J17: =TEXT(B17,"MM/YYYY") -> 05/2025 | K17: =IF(B17="","",CONCATENATE("CXG-",TEXT(B17,"MMYY"))) -> CXG-0525
E20: 0 | F20: =SUMIFS(PagComisao!F:F,PagComisao!C:C,I:I) -> 0 | G20: =E20-F20 -> 0 | J20: =TEXT(B20,"MM/YYYY") -> 12/1899 | K20: =IF(B20="","",CONCATENATE("CXG-",TEXT(B20,"MMYY")))
E21: 0 | F21: =SUMIFS(PagComisao!F:F,PagComisao!C:C,I:I) -> 0 | G21: =E21-F21 -> 0 | J21: =TEXT(B21,"MM/YYYY") -> 12/1899 | K21: =IF(B21="","",CONCATENATE("CXG-",TEXT(B21,"MMYY")))
E22: 0 | F22: =SUMIFS(PagComisao!F:F,PagComisao!C:C,I:I) -> 0 | G22: =E22-F22 -> 0 | J22: =TEXT(B22,"MM/YYYY") -> 12/1899 | K22: =IF(B22="","",CONCATENATE("CXG-",TEXT(B22,"MMYY")))
E23: 0 | F23: =SUMIFS(PagComisao!F:F,PagComisao!C:C,I:I) -> 0 | G23: =E23-F23 -> 0 | J23: =TEXT(B23,"MM/YYYY") -> 12/1899 | K23: =IF(B23="","",CONCATENATE("CXG-",TEXT(B23,"MMYY")))
E24: 0 | F24: =SUMIFS(PagComisao!F:F,PagComisao!C:C,I:I) -> 0 | G24: =E24-F24 -> 0 | J24: =TEXT(B24,"MM/YYYY") -> 12/1899 | K24: =IF(B24="","",CONCATENATE("CXG-",TEXT(B24,"MMYY")))
E25: 0 | F25: =SUMIFS(PagComisao!F:F,PagComisao!C:C,I:I) -> 0 | G25: =E25-F25 -> 0 | J25: =TEXT(B25,"MM/YYYY") -> 12/1899 | K25: =IF(B25="","",CONCATENATE("CXG-",TEXT(B25,"MMYY")))
E26: 0 | F26: =SUMIFS(PagComisao!F:F,PagComisao!C:C,I:I) -> 0 | G26: =E26-F26 -> 0 | J26: =TEXT(B26,"MM/YYYY") -> 12/1899 | K26: =IF(B26="","",CONCATENATE("CXG-",TEXT(B26,"MMYY")))
E27: 0 | F27: =SUMIFS(PagComisao!F:F,PagComisao!C:C,I:I) -> 0 | G27: =E27-F27 -> 0 | J27: =TEXT(B27,"MM/YYYY") -> 12/1899 | K27: =IF(B27="","",CONCATENATE("CXG-",TEXT(B27,"MMYY")))
E28: 0 | F28: =SUMIFS(PagComisao!F:F,PagComisao!C:C,I:I) -> 0 | G28: =E28-F28 -> 0 | J28: =TEXT(B28,"MM/YYYY") -> 12/1899 | K28: =IF(B28="","",CONCATENATE("CXG-",TEXT(B28,"MMYY")))
E29: 0 | F29: =SUMIFS(PagComisao!F:F,PagComisao!C:C,I:I) -> 0 | G29: =E29-F29 -> 0 | J29: =TEXT(B29,"MM/YYYY") -> 12/1899 | K29: =IF(B29="","",CONCATENATE("CXG-",TEXT(B29,"MMYY")))
E30: 0 | F30: =SUMIFS(PagComisao!F:F,PagComisao!C:C,I:I) -> 0 | G30: =E30-F30 -> 0 | J30: =TEXT(B30,"MM/YYYY") -> 12/1899 | K30: =IF(B30="","",CONCATENATE("CXG-",TEXT(B30,"MMYY")))
E31: 0 | F31: =SUMIFS(PagComisao!F:F,PagComisao!C:C,I:I) -> 0 | G31: =E31-F31 -> 0 | J31: =TEXT(B31,"MM/YYYY") -> 12/1899 | K31: =IF(B31="","",CONCATENATE("CXG-",TEXT(B31,"MMYY")))

Sheet PagComisao
A1: id | B1: data | C1: PedComissao | D1: Parceiro | E1: Conta | F1: Valor | G1: Anexo | H1: Foto | I1: MesAno | J1: PedCxMensal | K1: PedidodeCompra
A2: ee8b648e | B2: 45673 | C2: 160125218 | D2: Gabriel Balsas | E2: Neto - B.Brasil | F2: 1017.83 | I2: =TEXT(B2,"MM/YYYY") -> 01/2025 | J2: =IF(B2="","",CONCATENATE("CXG-",TEXT(B2,"MMYY"))) -> CXG-0125 | K2: 160125786
A3: f43c7bf8 | B3: 45673 | C3: 170125334 | D3: Gabriel Balsas | E3: Neto - B.Brasil | F3: 305 | I3: =TEXT(B3,"MM/YYYY") -> 01/2025 | J3: =IF(B3="","",CONCATENATE("CXG-",TEXT(B3,"MMYY"))) -> CXG-0125 | K3: 170125830
A4: d6e667b2 | B4: 45671 | C4: 170125334 | D4: Gabriel Balsas | E4: Descontos | F4: 2065.5 | I4: =TEXT(B4,"MM/YYYY") -> 01/2025 | J4: =IF(B4="","",CONCATENATE("CXG-",TEXT(B4,"MMYY"))) -> CXG-0125 | K4: 170125830
A5: d649a8ed | B5: 45678 | C5: 220125578 | D5: Gabriel Balsas | E5: S.Grão - Sicredi | F5: 694.7 | I5: =TEXT(B5,"MM/YYYY") -> 01/2025 | J5: =IF(B5="","",CONCATENATE("CXG-",TEXT(B5,"MMYY"))) -> CXG-0125 | K5: 1701251075
A6: a90cdcf7 | B6: 45678 | C6: 220125446 | D6: Gabriel Balsas | E6: S.Grão - Sicredi | F6: 2427.39 | I6: =TEXT(B6,"MM/YYYY") -> 01/2025 | J6: =IF(B6="","",CONCATENATE("CXG-",TEXT(B6,"MMYY"))) -> CXG-0125 | K6: 2001251462
A7: 27c9a609 | B7: 45685 | C7: 280125623 | D7: Gabriel Balsas | E7: S.Grão - Sicredi | F7: 1334.09 | I7: =TEXT(B7,"MM/YYYY") -> 01/2025 | J7: =IF(B7="","",CONCATENATE("CXG-",TEXT(B7,"MMYY"))) -> CXG-0125 | K7: 2001251462
A8: e625a00f | B8: 45684 | C8: 280125714 | D8: Gabriel Balsas | E8: S.Grão - Sicredi | F8: 259.2 | I8: =TEXT(B8,"MM/YYYY") -> 01/2025 | J8: =IF(B8="","",CONCATENATE("CXG-",TEXT(B8,"MMYY"))) -> CXG-0125 | K8: 1701251075
A9: dedc966a | B9: 45695 | C9: 040225998 | D9: Gabriel Balsas | E9: N.Nordeste - B.Brasil | F9: 919.6 | I9: =TEXT(B9,"MM/YYYY") -> 02/2025 | J9: =IF(B9="","",CONCATENATE("CXG-",TEXT(B9,"MMYY"))) -> CXG-0225 | K9: 1701251075
A10: 3686c105 | B10: 45695 | C10: 030225850 | D10: Gabriel Balsas | E10: N.Nordeste - B.Brasil | F10: 1016.9 | I10: =TEXT(B10,"MM/YYYY") -> 02/2025 | J10: =IF(B10="","",CONCATENATE("CXG-",TEXT(B10,"MMYY"))) -> CXG-0225 | K10: 1701251075
A11: 34040aba | B11: 45702 | C11: 1202251081 | D11: Gabriel Balsas | E11: N.Nordeste - B.Brasil | F11: 1173.85 | I11: =TEXT(B11,"MM/YYYY") -> 02/2025 | J11: =IF(B11="","",CONCATENATE("CXG-",TEXT(B11,"MMYY"))) -> CXG-0225 | K11: 0502252287
A12: 7ee3b325 | B12: 45709 | C12: 2402251240 | D12: Guilherme | E12: S.Grão - Sicredi | F12: 1840.33 | I12: =TEXT(B12,"MM/YYYY") -> 02/2025 | J12: =IF(B12="","",CONCATENATE("CXG-",TEXT(B12,"MMYY"))) -> CXG-0225 | K12: 1302252597
A13: df4c9cb0 | B13: 45735 | C13: 1803251329 | D13: Gabriel Balsas | E13: S.Grão - Sicredi | F13: 1887.69 | I13: =TEXT(B13,"MM/YYYY") -> 03/2025 | J13: =IF(B13="","",CONCATENATE("CXG-",TEXT(B13,"MMYY"))) -> CXG-0325 | K13: 1003253656
... A17: f7bb4631 | B17: 45790 | C17: 1405251713 | D17: Gabriel Balsas | E17: N.Nordeste - B.Brasil | F17: 586 | I17: =TEXT(B17,"MM/YYYY") -> 05/2025 | J17: =IF(B17="","",CONCATENATE("CXG-",TEXT(B17,"MMYY"))) -> CXG-0525 | K17: 1205255544
C18: 1302252597
I20: =TEXT(B20,"MM/YYYY") -> 12/1899 | J20: =IF(B20="","",CONCATENATE("CXG-",TEXT(B20,"MMYY")))
I21: =TEXT(B21,"MM/YYYY") -> 12/1899 | J21: =IF(B21="","",CONCATENATE("CXG-",TEXT(B21,"MMYY")))
I22: =TEXT(B22,"MM/YYYY") -> 12/1899 | J22: =IF(B22="","",CONCATENATE("CXG-",TEXT(B22,"MMYY")))
I23: =TEXT(B23,"MM/YYYY") -> 12/1899 | J23: =IF(B23="","",CONCATENATE("CXG-",TEXT(B23,"MMYY")))
I24: =TEXT(B24,"MM/YYYY") -> 12/1899 | J24: =IF(B24="","",CONCATENATE("CXG-",TEXT(B24,"MMYY")))
I25: =TEXT(B25,"MM/YYYY") -> 12/1899 | J25: =IF(B25="","",CONCATENATE("CXG-",TEXT(B25,"MMYY")))
I26: =TEXT(B26,"MM/YYYY") -> 12/1899 | J26: =IF(B26="","",CONCATENATE("CXG-",TEXT(B26,"MMYY")))
I27: =TEXT(B27,"MM/YYYY") -> 12/1899 | J27: =IF(B27="","",CONCATENATE("CXG-",TEXT(B27,"MMYY")))
I28: =TEXT(B28,"MM/YYYY") -> 12/1899 | J28: =IF(B28="","",CONCATENATE("CXG-",TEXT(B28,"MMYY")))
I29: =TEXT(B29,"MM/YYYY") -> 12/1899 | J29: =IF(B29="","",CONCATENATE("CXG-",TEXT(B29,"MMYY")))
I30: =TEXT(B30,"MM/YYYY") -> 12/1899 | J30: =IF(B30="","",CONCATENATE("CXG-",TEXT(B30,"MMYY")))
I31: =TEXT(B31,"MM/YYYY") -> 12/1899 | J31: =IF(B31="","",CONCATENATE("CXG-",TEXT(B31,"MMYY")))
I32: =TEXT(B32,"MM/YYYY") -> 12/1899 | J32: =IF(B32="","",CONCATENATE("CXG-",TEXT(B32,"MMYY")))

Sheet PedFretes
A1: id | B1: Data | C1: PedidodeCompra | D1: PedidoFrete | E1: ValorTotal | F1: ValorPago | G1: ValorPendente | H1: Anotações | I1: Gatilho | J1: MesAno | K1: PedCxMensal | L1: Despesas Extras | M1: Transportadora | N1: Observações
A2: 4b2260c0 | B2: 45672 | D2: TW15012521 | E2: =SUMIFS(CarrinhoFretes!L:L,CarrinhoFretes!C:C,D:D) -> 326549.7 | F2: =SUMIFS(PagFretes!E:E,PagFretes!C:C,D:D)+(SUMIFS(PagFreteIndividal!E:E, PagFreteIndividal!H:H, D:D, PagFreteIndividal!F:F, "<>Adiantamento") ) -> 326549.7 | G2: =E2-F2 -> 0 | H2: Finalizado | I2: 46017.454 | J2: =TEXT(B2,"MM/YYYY") -> 01/2025 | K2: =IF(B2="","",CONCATENATE("CXG-",TEXT(B2,"MMYY"))) -> CXG-0125 | L2: =SUMIFS(DesExtFrete!F:F,DesExtFrete!C:C,D:D) -> 160 | M2: TW - Suporte Agrícola | N2: Janeiro
A3: 075f1185 | B3: 45673 | D3: SR16012556 | E3: =SUMIFS(CarrinhoFretes!L:L,CarrinhoFretes!C:C,D:D) -> 151885.9 | F3: =SUMIFS(PagFretes!E:E,PagFretes!C:C,D:D)+(SUMIFS(PagFreteIndividal!E:E, PagFreteIndividal!H:H, D:D, PagFreteIndividal!F:F, "<>Adiantamento") ) -> 151885.9 | G3: =E3-F3 -> 0 | H3: Finalizado | I3: 45687.607 | J3: =TEXT(B3,"MM/YYYY") -> 01/2025 | K3: =IF(B3="","",CONCATENATE("CXG-",TEXT(B3,"MMYY"))) -> CXG-0125 | L3: =SUMIFS(DesExtFrete!F:F,DesExtFrete!C:C,D:D) -> 0 | M3: SR - Sergio Rocha
F4: =SUMIFS(PagFretes!E:E,PagFretes!C:C,D:D)+(SUMIFS(PagFreteIndividal!E:E, PagFreteIndividal!H:H, D:D, PagFreteIndividal!F:F, "<>Adiantamento") ) -> 0
A5: 6c0de1c5 | B5: 45674 | D5: AT170125124 | E5: =SUMIFS(CarrinhoFretes!L:L,CarrinhoFretes!C:C,D:D) -> 3944276.8 | F5: =SUMIFS(PagFretes!E:E,PagFretes!C:C,D:D)+(SUMIFS(PagFreteIndividal!E:E, PagFreteIndividal!H:H, D:D, PagFreteIndividal!F:F, "<>Adiantamento") ) -> 3944276.8 | G5: =E5-F5 -> 9.3132257e-10 | H5: Finalizado | I5: 45677.856 | J5: =TEXT(B5,"MM/YYYY") -> 01/2025 | K5: =IF(B5="","",CONCATENATE("CXG-",TEXT(B5,"MMYY"))) -> CXG-0125 | L5: =SUMIFS(DesExtFrete!F:F,DesExtFrete!C:C,D:D) -> 47282.75 | M5: AT - Autônomo
A6: 97659c54 | B6: 45689 | D6: SR30012567 | E6: =SUMIFS(CarrinhoFretes!L:L,CarrinhoFretes!C:C,D:D) -> 153396.8 | F6: =SUMIFS(PagFretes!E:E,PagFretes!C:C,D:D)+(SUMIFS(PagFreteIndividal!E:E, PagFreteIndividal!H:H, D:D, PagFreteIndividal!F:F, "<>Adiantamento") ) -> 153396.8 | G6: =E6-F6 -> 0 | H6: Finalizado | J6: =TEXT(B6,"MM/YYYY") -> 02/2025 | K6: =IF(B6="","",CONCATENATE("CXG-",TEXT(B6,"MMYY"))) -> CXG-0225 | L6: =SUMIFS(DesExtFrete!F:F,DesExtFrete!C:C,D:D) -> 3500 | M6: SR - Sergio Rocha
A7: 09b67c51 | B7: 45689 | D7: CX30012572 | E7: =SUMIFS(CarrinhoFretes!L:L,CarrinhoFretes!C:C,D:D) -> 217568.4 | F7: =SUMIFS(PagFretes!E:E,PagFretes!C:C,D:D)+(SUMIFS(PagFreteIndividal!E:E, PagFreteIndividal!H:H, D:D, PagFreteIndividal!F:F, "<>Adiantamento") ) -> 217568.4 | G7: =E7-F7 -> 0 | H7: Finalizado | J7: =TEXT(B7,"MM/YYYY") -> 02/2025 | K7: =IF(B7="","",CONCATENATE("CXG-",TEXT(B7,"MMYY"))) -> CXG-0225 | L7: =SUMIFS(DesExtFrete!F:F,DesExtFrete!C:C,D:D) -> 1900 | M7: CX - Caio Xavier
A8: 75b0d823 | B8: 45689 | D8: MA30012584 | E8: =SUMIFS(CarrinhoFretes!L:L,CarrinhoFretes!C:C,D:D) -> 175246.4 | F8: =SUMIFS(PagFretes!E:E,PagFretes!C:C,D:D)+(SUMIFS(PagFreteIndividal!E:E, PagFreteIndividal!H:H, D:D, PagFreteIndividal!F:F, "<>Adiantamento") ) -> 175246.4 | G8: =E8-F8 -> 0 | H8: Finalizado | J8: =TEXT(B8,"MM/YYYY") -> 02/2025 | K8: =IF(B8="","",CONCATENATE("CXG-",TEXT(B8,"MMYY"))) -> CXG-0225 | L8: =SUMIFS(DesExtFrete!F:F,DesExtFrete!C:C,D:D) -> 0 | M8: MA - Matheus Aguiar
A9: 54d2d15b | B9: 45687 | D9: MT300125910 | E9: =SUMIFS(CarrinhoFretes!L:L,CarrinhoFretes!C:C,D:D) -> 4854 | F9: =SUMIFS(PagFretes!E:E,PagFretes!C:C,D:D)+(SUMIFS(PagFreteIndividal!E:E, PagFreteIndividal!H:H, D:D, PagFreteIndividal!F:F, "<>Adiantamento") ) -> 4854 | G9: =E9-F9 -> 0 | H9: Finalizado | I9: 46014.411 | J9: =TEXT(B9,"MM/YYYY") -> 01/2025 | K9: =IF(B9="","",CONCATENATE("CXG-",TEXT(B9,"MMYY"))) -> CXG-0125 | L9: =SUMIFS(DesExtFrete!F:F,DesExtFrete!C:C,D:D) -> 0 | M9: MT - Mirele Transportes
A12: 784df63f | B12: 45692 | D12: SE040225122 | E12: =SUMIFS(CarrinhoFretes!L:L,CarrinhoFretes!C:C,D:D) -> 0 | F12: =SUMIFS(PagFretes!E:E,PagFretes!C:C,D:D)+(SUMIFS(PagFreteIndividal!E:E, PagFreteIndividal!H:H, D:D, PagFreteIndividal!F:F, "<>Adiantamento") ) -> 0 | G12: =E12-F12 -> 0 | H12: Pendente | J12: =TEXT(B12,"MM/YYYY") -> 02/2025 | K12: =IF(B12="","",CONCATENATE("CXG-",TEXT(B12,"MMYY"))) -> CXG-0225 | L12: =SUMIFS(DesExtFrete!F:F,DesExtFrete!C:C,D:D) -> 0 | M12: SEM FRETE
A13: e2c834d1 | B13: 45693 | D13: TW050225133 | E13: =SUMIFS(CarrinhoFretes!L:L,CarrinhoFretes!C:C,D:D) -> 227818.9 | F13: =SUMIFS(PagFretes!E:E,PagFretes!C:C,D:D)+(SUMIFS(PagFreteIndividal!E:E, PagFreteIndividal!H:H, D:D, PagFreteIndividal!F:F, "<>Adiantamento") ) -> 227818.9 | G13: =E13-F13 -> 0 | H13: Finalizado | I13: 45761.385 | J13: =TEXT(B13,"MM/YYYY") -> 02/2025 | K13: =IF(B13="","",CONCATENATE("CXG-",TEXT(B13,"MMYY"))) -> CXG-0225 | L13: =SUMIFS(DesExtFrete!F:F,DesExtFrete!C:C,D:D) -> 0 | M13: TW - Suporte Agrícola | N13: Fevereiro
A14: ad82c256 | B14: 45708 | D14: MC200225141 | E14: =SUMIFS(CarrinhoFretes!L:L,CarrinhoFretes!C:C,D:D) -> 8814 | F14: =SUMIFS(PagFretes!E:E,PagFretes!C:C,D:D)+(SUMIFS(PagFreteIndividal!E:E, PagFreteIndividal!H:H, D:D, PagFreteIndividal!F:F, "<>Adiantamento") ) -> 8814 | G14: =E14-F14 -> 0 | H14: Finalizado | J14: =TEXT(B14,"MM/YYYY") -> 02/2025 | K14: =IF(B14="","",CONCATENATE("CXG-",TEXT(B14,"MMYY"))) -> CXG-0225 | L14: =SUMIFS(DesExtFrete!F:F,DesExtFrete!C:C,D:D) -> 0 | M14: MC - Marcelo do Clube
A15: 509d6f40 | B15: 45721 | D15: TW050325151 | E15: =SUMIFS(CarrinhoFretes!L:L,CarrinhoFretes!C:C,D:D) -> 652188.3 | F15: =SUMIFS(PagFretes!E:E,PagFretes!C:C,D:D)+(SUMIFS(PagFreteIndividal!E:E, PagFreteIndividal!H:H, D:D, PagFreteIndividal!F:F, "<>Adiantamento") ) -> 652188.3 | G15: =E15-F15 -> 0 | H15: Finalizado | I15: 45751.64 | J15: =TEXT(B15,"MM/YYYY") -> 03/2025 | K15: =IF(B15="","",CONCATENATE("CXG-",TEXT(B15,"MMYY"))) -> CXG-0325 | L15: =SUMIFS(DesExtFrete!F:F,DesExtFrete!C:C,D:D) -> 200 | M15: TW - Suporte Agrícola | N15: Março
A16: 1250a9f5 | B16: 45733 | D16: FA1703251610 | E16: =SUMIFS(CarrinhoFretes!L:L,CarrinhoFretes!C:C,D:D) -> 70439.6 | F16: =SUMIFS(PagFretes!E:E,PagFretes!C:C,D:D)+(SUMIFS(PagFreteIndividal!E:E, PagFreteIndividal!H:H, D:D, PagFreteIndividal!F:F, "<>Adiantamento") ) -> 70439.6 | G16: =E16-F16 -> 0 | H16: Finalizado | J16: =TEXT(B16,"MM/YYYY") -> 03/2025 | K16: =IF(B16="","",CONCATENATE("CXG-",TEXT(B16,"MMYY"))) -> CXG-0325 | L16: =SUMIFS(DesExtFrete!F:F,DesExtFrete!C:C,D:D) -> 0 | M16: FA - Felipe Aguiar
A17: 2f64fc4f | B17: 45738 | D17: MT230325171 | E17: =SUMIFS(CarrinhoFretes!L:L,CarrinhoFretes!C:C,D:D) -> 13417.6 | F17: =SUMIFS(PagFretes!E:E,PagFretes!C:C,D:D)+(SUMIFS(PagFreteIndividal!E:E, PagFreteIndividal!H:H, D:D, PagFreteIndividal!F:F, "<>Adiantamento") ) -> 13417.6 | G17: =E17-F17 -> 0 | H17: Finalizado | I17: 46014.412 | J17: =TEXT(B17,"MM/YYYY") -> 03/2025 | K17: =IF(B17="","",CONCATENATE("CXG-",TEXT(B17,"MMYY"))) -> CXG-0325 | L17: =SUMIFS(DesExtFrete!F:F,DesExtFrete!C:C,D:D) -> 0 | M17: MT - Mirele Transportes
A18: 000e2ee2 | B18: 45748 | D18: TW010425184 | E18: =SUMIFS(CarrinhoFretes!L:L,CarrinhoFretes!C:C,D:D) -> 302902.5 | F18: =SUMIFS(PagFretes!E:E,PagFretes!C:C,D:D)+(SUMIFS(PagFreteIndividal!E:E, PagFreteIndividal!H:H, D:D, PagFreteIndividal!F:F, "<>Adiantamento") ) -> 302902.5 | G18: =E18-F18 -> 0 | H18: Finalizado | I18: 45779.387 | J18: =TEXT(B18,"MM/YYYY") -> 04/2025 | K18: =IF(B18="","",CONCATENATE("CXG-",TEXT(B18,"MMYY"))) -> CXG-0425 | L18: =SUMIFS(DesExtFrete!F:F,DesExtFrete!C:C,D:D) -> 0 | M18: TW - Suporte Agrícola | N18: Abril
A19: 340b5558 | B19: 45778 | D19: TW070525195 | E19: =SUMIFS(CarrinhoFretes!L:L,CarrinhoFretes!C:C,D:D) -> 543246.32 | F19: =SUMIFS(PagFretes!E:E,PagFretes!C:C,D:D)+(SUMIFS(PagFreteIndividal!E:E, PagFreteIndividal!H:H, D:D, PagFreteIndividal!F:F, "<>Adiantamento") ) -> 543246.32 | G19: =E19-F19 -> 0 | H19: Finalizado | I19: 45937.81 | J19: =TEXT(B19,"MM/YYYY") -> 05/2025 | K19: =IF(B19="","",CONCATENATE("CXG-",TEXT(B19,"MMYY"))) -> CXG-0525 | L19: =SUMIFS(DesExtFrete!F:F,DesExtFrete!C:C,D:D) -> 0 | M19: TW - Suporte Agrícola | N19: Maio
A20: d4a8ba14 | B20: 45810 | D20: TW020625206 | E20: =SUMIFS(CarrinhoFretes!L:L,CarrinhoFretes!C:C,D:D) -> 1059541.8 | F20: =SUMIFS(PagFretes!E:E,PagFretes!C:C,D:D)+(SUMIFS(PagFreteIndividal!E:E, PagFreteIndividal!H:H, D:D, PagFreteIndividal!F:F, "<>Adiantamento") ) -> 1059541.8 | G20: =E20-F20 -> 0 | H20: Finalizado | I20: 45937.81 | J20: =TEXT(B20,"MM/YYYY") -> 06/2025 | K20: =IF(B20="","",CONCATENATE("CXG-",TEXT(B20,"MMYY"))) -> CXG-0625 | L20: =SUMIFS(DesExtFrete!F:F,DesExtFrete!C:C,D:D) -> 0 | M20: TW - Suporte Agrícola | N20: JUNHO
A21: 6f1c4271 | B21: 45839 | D21: TW010725214 | E21: =SUMIFS(CarrinhoFretes!L:L,CarrinhoFretes!C:C,D:D) -> 1455535.8 | F21: =SUMIFS(PagFretes!E:E,PagFretes!C:C,D:D)+(SUMIFS(PagFreteIndividal!E:E, PagFreteIndividal!H:H, D:D, PagFreteIndividal!F:F, "<>Adiantamento") ) -> 1455535.8 | G21: =E21-F21 -> 0 | H21: Finalizado | I21: 45937.811 | J21: =TEXT(B21,"MM/YYYY") -> 07/2025 | K21: =IF(B21="","",CONCATENATE("CXG-",TEXT(B21,"MMYY"))) -> CXG-0725 | L21: =SUMIFS(DesExtFrete!F:F,DesExtFrete!C:C,D:D) -> 0 | M21: TW - Suporte Agrícola | N21: JULHO
A22: 63567898 | B22: 45869 | D22: TW310725224 | E22: =SUMIFS(CarrinhoFretes!L:L,CarrinhoFretes!C:C,D:D) -> 1216603.6 | F22: =SUMIFS(PagFretes!E:E,PagFretes!C:C,D:D)+(SUMIFS(PagFreteIndividal!E:E, PagFreteIndividal!H:H, D:D, PagFreteIndividal!F:F, "<>Adiantamento") ) -> 1216603.6 | G22: =E22-F22 -> 4.6566129e-10 | H22: Finalizado | I22: 45939.388 | J22: =TEXT(B22,"MM/YYYY") -> 07/2025 | K22: =IF(B22="","",CONCATENATE("CXG-",TEXT(B22,"MMYY"))) -> CXG-0725 | L22: =SUMIFS(DesExtFrete!F:F,DesExtFrete!C:C,D:D) -> 0 | M22: TW - Suporte Agrícola | N22: AGOSTO
A23: 90f7a46c | B23: 45901 | D23: TW010925231 | E23: =SUMIFS(CarrinhoFretes!L:L,CarrinhoFretes!C:C,D:D) -> 1213935 | F23: =SUMIFS(PagFretes!E:E,PagFretes!C:C,D:D)+(SUMIFS(PagFreteIndividal!E:E, PagFreteIndividal!H:H, D:D, PagFreteIndividal!F:F, "<>Adiantamento") ) -> 1213935 | G23: =E23-F23 -> 2.3283064e-10 | H23: Finalizado | I23: 45937.812 | J23: =TEXT(B23,"MM/YYYY") -> 09/2025 | K23: =IF(B23="","",CONCATENATE("CXG-",TEXT(B23,"MMYY"))) -> CXG-0925 | L23: =SUMIFS(DesExtFrete!F:F,DesExtFrete!C:C,D:D) -> 0 | M23: TW - Suporte Agrícola | N23: SETEMBRO
A24: 171e5cec | B24: 45931 | D24: TW011025244 | E24: =SUMIFS(CarrinhoFretes!L:L,CarrinhoFretes!C:C,D:D) -> 902808.85 | F24: =SUMIFS(PagFretes!E:E,PagFretes!C:C,D:D)+(SUMIFS(PagFreteIndividal!E:E, PagFreteIndividal!H:H, D:D, PagFreteIndividal!F:F, "<>Adiantamento") ) -> 902808.85 | G24: =E24-F24 -> 2.3283064e-10 | H24: Finalizado | I24: 45969.459 | J24: =TEXT(B24,"MM/YYYY") -> 10/2025 | K24: =IF(B24="","",CONCATENATE("CXG-",TEXT(B24,"MMYY"))) -> CXG-1025 | L24: =SUMIFS(DesExtFrete!F:F,DesExtFrete!C:C,D:D) -> 0 | M24: TW - Suporte Agrícola | N24: OUTUBRO
A25: 08bfe32f | B25: 45960 | D25: TW301025251 | E25: =SUMIFS(CarrinhoFretes!L:L,CarrinhoFretes!C:C,D:D) -> 396830.72 | F25: =SUMIFS(PagFretes!E:E,PagFretes!C:C,D:D)+(SUMIFS(PagFreteIndividal!E:E, PagFreteIndividal!H:H, D:D, PagFreteIndividal!F:F, "<>Adiantamento") ) -> 396830.72 | G25: =E25-F25 -> -1.1641532e-10 | H25: Finalizado | I25: 45992.641 | J25: =TEXT(B25,"MM/YYYY") -> 10/2025 | K25: =IF(B25="","",CONCATENATE("CXG-",TEXT(B25,"MMYY"))) -> CXG-1025 | L25: =SUMIFS(DesExtFrete!F:F,DesExtFrete!C:C,D:D) -> 0 | M25: TW - Suporte Agrícola | N25: NOVEMBRO
A26: 56cf6666 | B26: 45992 | D26: TW011225260 | E26: =SUMIFS(CarrinhoFretes!L:L,CarrinhoFretes!C:C,D:D) -> 598086.6 | F26: =SUMIFS(PagFretes!E:E,PagFretes!C:C,D:D)+(SUMIFS(PagFreteIndividal!E:E, PagFreteIndividal!H:H, D:D, PagFreteIndividal!F:F, "<>Adiantamento") ) -> 598086.6 | G26: =E26-F26 -> -1.1641532e-10 | H26: Finalizado | I26: 46022.395 | J26: =TEXT(B26,"MM/YYYY") -> 12/2025 | K26: =IF(B26="","",CONCATENATE("CXG-",TEXT(B26,"MMYY"))) -> CXG-1225 | L26: =SUMIFS(DesExtFrete!F:F,DesExtFrete!C:C,D:D) -> 0 | M26: TW - Suporte Agrícola | N26: DEZEMBRO
A27: 4837b287 | B27: 46027 | D27: TW050126272 | E27: =SUMIFS(CarrinhoFretes!L:L,CarrinhoFretes!C:C,D:D) -> 761038.8 | F27: =SUMIFS(PagFretes!E:E,PagFretes!C:C,D:D)+(SUMIFS(PagFreteIndividal!E:E, PagFreteIndividal!H:H, D:D, PagFreteIndividal!F:F, "<>Adiantamento") ) -> 761038.8 | G27: =E27-F27 -> -1.1641532e-10 | H27: Finalizado | I27: 46056.377 | J27: =TEXT(B27,"MM/YYYY") -> 01/2026 | K27: =IF(B27="","",CONCATENATE("CXG-",TEXT(B27,"MMYY"))) -> CXG-0126 | L27: =SUMIFS(DesExtFrete!F:F,DesExtFrete!C:C,D:D) -> 0 | M27: TW - Suporte Agrícola | N27: JANEIRO
A28: 2a9c59e0 | B28: 46031 | D28: AT090126288 | E28: =SUMIFS(CarrinhoFretes!L:L,CarrinhoFretes!C:C,D:D) -> 2268506 | F28: =SUMIFS(PagFretes!E:E,PagFretes!C:C,D:D)+(SUMIFS(PagFreteIndividal!E:E, PagFreteIndividal!H:H, D:D, PagFreteIndividal!F:F, "<>Adiantamento") ) -> 2259852.2 | G28: =E28-F28 -> 8653.8 | H28: Pendente | J28: =TEXT(B28,"MM/YYYY") -> 01/2026 | K28: =IF(B28="","",CONCATENATE("CXG-",TEXT(B28,"MMYY"))) -> CXG-0126 | L28: =SUMIFS(DesExtFrete!F:F,DesExtFrete!C:C,D:D) -> 10340.86 | M28: AT - Autônomo
A29: 8e3b26f4 | B29: 46054 | D29: TW020226297 | E29: =SUMIFS(CarrinhoFretes!L:L,CarrinhoFretes!C:C,D:D) -> 697564.8 | F29: =SUMIFS(PagFretes!E:E,PagFretes!C:C,D:D)+(SUMIFS(PagFreteIndividal!E:E, PagFreteIndividal!H:H, D:D, PagFreteIndividal!F:F, "<>Adiantamento") ) -> 697564.8 | G29: =E29-F29 -> -1.1641532e-10 | H29: Finalizado | I29: 46084.624 | J29: =TEXT(B29,"MM/YYYY") -> 02/2026 | K29: =IF(B29="","",CONCATENATE("CXG-",TEXT(B29,"MMYY"))) -> CXG-0226 | L29: =SUMIFS(DesExtFrete!F:F,DesExtFrete!C:C,D:D) -> 0 | M29: TW - Suporte Agrícola | N29: FEVEREIRO
A31: c1b1d242 | B31: 46081 | D31: TW020326314 | E31: =SUMIFS(CarrinhoFretes!L:L,CarrinhoFretes!C:C,D:D) -> 499885.9 | F31: =SUMIFS(PagFretes!E:E,PagFretes!C:C,D:D)+(SUMIFS(PagFreteIndividal!E:E, PagFreteIndividal!H:H, D:D, PagFreteIndividal!F:F, "<>Adiantamento") ) -> 499885.9 | G31: =E31-F31 -> 0 | H31: Finalizado | I31: 46118.343 | J31: =TEXT(B31,"MM/YYYY") -> 02/2026 | K31: =IF(B31="","",CONCATENATE("CXG-",TEXT(B31,"MMYY"))) -> CXG-0226 | L31: =SUMIFS(DesExtFrete!F:F,DesExtFrete!C:C,D:D) -> 0 | M31: TW - Suporte Agrícola | N31: MARÇO
A32: 54cbf105 | B32: 46084 | D32: NP030326326 | E32: =SUMIFS(CarrinhoFretes!L:L,CarrinhoFretes!C:C,D:D) -> 88843.7 | F32: =SUMIFS(PagFretes!E:E,PagFretes!C:C,D:D)+(SUMIFS(PagFreteIndividal!E:E, PagFreteIndividal!H:H, D:D, PagFreteIndividal!F:F, "<>Adiantamento") ) -> 88843.7 | G32: =E32-F32 -> 0 | H32: Finalizado | I32: 46113.426 | J32: =TEXT(B32,"MM/YYYY") -> 03/2026 | K32: =IF(B32="","",CONCATENATE("CXG-",TEXT(B32,"MMYY"))) -> CXG-0326 | L32: =SUMIFS(DesExtFrete!F:F,DesExtFrete!C:C,D:D) -> 0 | M32: NP - Newton Porto | N32: MARÇO
A34: 1511c106 | B34: 46113 | D34: NP010426343 | E34: =SUMIFS(CarrinhoFretes!L:L,CarrinhoFretes!C:C,D:D) -> 116876.6 | F34: =SUMIFS(PagFretes!E:E,PagFretes!C:C,D:D)+(SUMIFS(PagFreteIndividal!E:E, PagFreteIndividal!H:H, D:D, PagFreteIndividal!F:F, "<>Adiantamento") ) -> 116876.6 | G34: =E34-F34 -> 0 | H34: Finalizado | I34: 46146.433 | J34: =TEXT(B34,"MM/YYYY") -> 04/2026 | K34: =IF(B34="","",CONCATENATE("CXG-",TEXT(B34,"MMYY"))) -> CXG-0426 | L34: =SUMIFS(DesExtFrete!F:F,DesExtFrete!C:C,D:D) -> 0 | M34: NP - Newton Porto | N34: ABRIL
A35: ae0e8c87 | B35: 46113 | D35: TW010426352 | E35: =SUMIFS(CarrinhoFretes!L:L,CarrinhoFretes!C:C,D:D) -> 453501.7 | F35: =SUMIFS(PagFretes!E:E,PagFretes!C:C,D:D)+(SUMIFS(PagFreteIndividal!E:E, PagFreteIndividal!H:H, D:D, PagFreteIndividal!F:F, "<>Adiantamento") ) -> 453501.7 | G35: =E35-F35 -> -1.7462298e-10 | H35: Finalizado | I35: 46146.414 | J35: =TEXT(B35,"MM/YYYY") -> 04/2026 | K35: =IF(B35="","",CONCATENATE("CXG-",TEXT(B35,"MMYY"))) -> CXG-0426 | L35: =SUMIFS(DesExtFrete!F:F,DesExtFrete!C:C,D:D) -> 0 | M35: TW - Suporte Agrícola | N35: ABRIL
A36: a91dc498 | B36: 46139 | D36: MA270426366 | E36: =SUMIFS(CarrinhoFretes!L:L,CarrinhoFretes!C:C,D:D) -> 128293.3 | F36: =SUMIFS(PagFretes!E:E,PagFretes!C:C,D:D)+(SUMIFS(PagFreteIndividal!E:E, PagFreteIndividal!H:H, D:D, PagFreteIndividal!F:F, "<>Adiantamento") ) -> 128293.3 | G36: =E36-F36 -> 0 | H36: Pendente | J36: =TEXT(B36,"MM/YYYY") -> 04/2026 | K36: =IF(B36="","",CONCATENATE("CXG-",TEXT(B36,"MMYY"))) -> CXG-0426 | L36: =SUMIFS(DesExtFrete!F:F,DesExtFrete!C:C,D:D) -> 0 | M36: MA - Matheus Aguiar
A37: 1a9f5f13 | B37: 46143 | D37: TW040526371 | E37: =SUMIFS(CarrinhoFretes!L:L,CarrinhoFretes!C:C,D:D) -> 45372.8 | F37: =SUMIFS(PagFretes!E:E,PagFretes!C:C,D:D)+(SUMIFS(PagFreteIndividal!E:E, PagFreteIndividal!H:H, D:D, PagFreteIndividal!F:F, "<>Adiantamento") ) -> 911444.32 | G37: =E37-F37 -> -866071.52 | H37: Finalizado | I37: 46164.728 | J37: =TEXT(B37,"MM/YYYY") -> 05/2026 | K37: =IF(B37="","",CONCATENATE("CXG-",TEXT(B37,"MMYY"))) -> CXG-0526 | L37: =SUMIFS(DesExtFrete!F:F,DesExtFrete!C:C,D:D) -> 0 | M37: TW - Suporte Agrícola | N37: MAIO
A38: a95808d6 | B38: 46143 | D38: NP040526383 | E38: =SUMIFS(CarrinhoFretes!L:L,CarrinhoFretes!C:C,D:D) -> 157291.6 | F38: =SUMIFS(PagFretes!E:E,PagFretes!C:C,D:D)+(SUMIFS(PagFreteIndividal!E:E, PagFreteIndividal!H:H, D:D, PagFreteIndividal!F:F, "<>Adiantamento") ) -> 157291.6 | G38: =E38-F38 -> 0 | H38: Finalizado | I38: 46174.419 | J38: =TEXT(B38,"MM/YYYY") -> 05/2026 | K38: =IF(B38="","",CONCATENATE("CXG-",TEXT(B38,"MMYY"))) -> CXG-0526 | L38: =SUMIFS(DesExtFrete!F:F,DesExtFrete!C:C,D:D) -> 0 | M38: NP - Newton Porto | N38: MAIO
A39: e69f9139 | B39: 46146 | D39: TW040526397 | E39: =SUMIFS(CarrinhoFretes!L:L,CarrinhoFretes!C:C,D:D) -> 471807.4 | F39: =SUMIFS(PagFretes!E:E,PagFretes!C:C,D:D)+(SUMIFS(PagFreteIndividal!E:E, PagFreteIndividal!H:H, D:D, PagFreteIndividal!F:F, "<>Adiantamento") ) -> 471807.4 | G39: =E39-F39 -> 0 | H39: Finalizado | I39: 46174.419 | J39: =TEXT(B39,"MM/YYYY") -> 05/2026 | K39: =IF(B39="","",CONCATENATE("CXG-",TEXT(B39,"MMYY"))) -> CXG-0526 | L39: =SUMIFS(DesExtFrete!F:F,DesExtFrete!C:C,D:D) -> 0 | M39: TW - Suporte Agrícola | N39: MAIO TRANSLOG
A40: c3d25e50 | B40: 46162 | D40: D 2005264010 | E40: =SUMIFS(CarrinhoFretes!L:L,CarrinhoFretes!C:C,D:D) -> 325215.4 | F40: =SUMIFS(PagFretes!E:E,PagFretes!C:C,D:D)+(SUMIFS(PagFreteIndividal!E:E, PagFreteIndividal!H:H, D:D, PagFreteIndividal!F:F, "<>Adiantamento") ) -> 301215.4 | G40: =E40-F40 -> 24000 | H40: Pendente | J40: =TEXT(B40,"MM/YYYY") -> 05/2026 | K40: =IF(B40="","",CONCATENATE("CXG-",TEXT(B40,"MMYY"))) -> CXG-0526 | L40: =SUMIFS(DesExtFrete!F:F,DesExtFrete!C:C,D:D) -> 800 | M40: D - Daniel
A41: 7fb45e73 | B41: 46173 | D41: TW010626417 | E41: =SUMIFS(CarrinhoFretes!L:L,CarrinhoFretes!C:C,D:D) -> 42451.4 | F41: =SUMIFS(PagFretes!E:E,PagFretes!C:C,D:D)+(SUMIFS(PagFreteIndividal!E:E, PagFreteIndividal!H:H, D:D, PagFreteIndividal!F:F, "<>Adiantamento") ) -> 209152.13 | G41: =E41-F41 -> -166700.73 | H41: Pendente | I41: 46174.419 | J41: =TEXT(B41,"MM/YYYY") -> 05/2026 | K41: =IF(B41="","",CONCATENATE("CXG-",TEXT(B41,"MMYY"))) -> CXG-0526 | L41: =SUMIFS(DesExtFrete!F:F,DesExtFrete!C:C,D:D) -> 0 | M41: TW - Suporte Agrícola | N41: JUNHO TRANSLOG
A42: d3ea77de | B42: 46173 | D42: NP010626423 | E42: =SUMIFS(CarrinhoFretes!L:L,CarrinhoFretes!C:C,D:D) -> 17697.6 | F42: =SUMIFS(PagFretes!E:E,PagFretes!C:C,D:D)+(SUMIFS(PagFreteIndividal!E:E, PagFreteIndividal!H:H, D:D, PagFreteIndividal!F:F, "<>Adiantamento") ) -> -33080.72 | G42: =E42-F42 -> 50778.32 | H42: Pendente | I42: 46174.419 | J42: =TEXT(B42,"MM/YYYY") -> 05/2026 | K42: =IF(B42="","",CONCATENATE("CXG-",TEXT(B42,"MMYY"))) -> CXG-0526 | L42: =SUMIFS(DesExtFrete!F:F,DesExtFrete!C:C,D:D) -> 0 | M42: NP - Newton Porto | N42: JUNHO

Sheet PagFretes
A1: id | B1: Data | C1: PedidoFrete | D1: Conta | E1: Valor | F1: Anexo | G1: Foto | H1: Anotações | I1: Gatilho | J1: MesAno | K1: PedCxMensal
A2: f003e721 | B2: 45691 | C2: TW15012521 | D2: N.Nordeste - B.Brasil | E2: 100000 | H2: TW - Suporte Agrícola | J2: =TEXT(B2,"MM/YYYY") -> 02/2025 | K2: =IF(B2="","",CONCATENATE("CXG-",TEXT(B2,"MMYY"))) -> CXG-0225
A3: ce5933ec | B3: 45691 | C3: TW15012521 | D3: Terceiros | E3: 29040 | H3: TW - Suporte Agrícola | J3: =TEXT(B3,"MM/YYYY") -> 02/2025 | K3: =IF(B3="","",CONCATENATE("CXG-",TEXT(B3,"MMYY"))) -> CXG-0225
A4: ff6ccf87 | B4: 45691 | C4: TW15012521 | D4: Terceiros | E4: 65000 | H4: TW - Suporte Agrícola | J4: =TEXT(B4,"MM/YYYY") -> 02/2025 | K4: =IF(B4="","",CONCATENATE("CXG-",TEXT(B4,"MMYY"))) -> CXG-0225
A5: 3d92b355 | B5: 45691 | C5: TW15012521 | D5: S.Grão - Sicredi | E5: 2568.04 | H5: TW - Suporte Agrícola | J5: =TEXT(B5,"MM/YYYY") -> 02/2025 | K5: =IF(B5="","",CONCATENATE("CXG-",TEXT(B5,"MMYY"))) -> CXG-0225
A6: 3b2cae1e | B6: 45692 | C6: TW15012521 | D6: Terceiros | E6: 50000 | H6: TW - Suporte Agrícola | J6: =TEXT(B6,"MM/YYYY") -> 02/2025 | K6: =IF(B6="","",CONCATENATE("CXG-",TEXT(B6,"MMYY"))) -> CXG-0225
A7: 9f9a0d54 | B7: 45693 | C7: TW15012521 | D7: Terceiros | E7: 46964.72 | H7: TW - Suporte Agrícola | J7: =TEXT(B7,"MM/YYYY") -> 02/2025 | K7: =IF(B7="","",CONCATENATE("CXG-",TEXT(B7,"MMYY"))) -> CXG-0225
A8: da603134 | B8: 45693 | C8: TW15012521 | D8: Descontos | E8: 5683 | H8: TW - Suporte Agrícola | J8: =TEXT(B8,"MM/YYYY") -> 02/2025 | K8: =IF(B8="","",CONCATENATE("CXG-",TEXT(B8,"MMYY"))) -> CXG-0225
A9: 43b1509f | B9: 45693 | C9: TW15012521 | D9: N.Nordeste - B.Brasil | E9: 25000 | H9: TW - Suporte Agrícola | J9: =TEXT(B9,"MM/YYYY") -> 02/2025 | K9: =IF(B9="","",CONCATENATE("CXG-",TEXT(B9,"MMYY"))) -> CXG-0225
A10: 5239baf7 | B10: 45693 | C10: TW15012521 | D10: Descontos | E10: 293.94 | H10: TW - Suporte Agrícola | J10: =TEXT(B10,"MM/YYYY") -> 02/2025 | K10: =IF(B10="","",CONCATENATE("CXG-",TEXT(B10,"MMYY"))) -> CXG-0225
A11: 4637eb8d | B11: 45693 | C11: TW050225133 | D11: S.Grão - Sicredi | E11: 4755.77 | H11: TW - Suporte Agrícola | J11: =TEXT(B11,"MM/YYYY") -> 02/2025 | K11: =IF(B11="","",CONCATENATE("CXG-",TEXT(B11,"MMYY"))) -> CXG-0225
A12: bb998191 | B12: 45693 | C12: TW050225133 | D12: S.Grão - Sicredi | E12: 13445.29 | H12: TW - Suporte Agrícola | J12: =TEXT(B12,"MM/YYYY") -> 02/2025 | K12: =IF(B12="","",CONCATENATE("CXG-",TEXT(B12,"MMYY"))) -> CXG-0225
A13: 8a9921d3 | B13: 45712 | C13: TW050225133 | D13: N.Nordeste - B.Brasil | E13: 190000 | H13: TW - Suporte Agrícola | J13: =TEXT(B13,"MM/YYYY") -> 02/2025 | K13: =IF(B13="","",CONCATENATE("CXG-",TEXT(B13,"MMYY"))) -> CXG-0225
... A41: 3ba0d5e7 | B41: 45772 | C41: TW010425184 | D41: Terceiros | E41: 72000 | H41: TW - Suporte Agrícola | J41: =TEXT(B41,"MM/YYYY") -> 04/2025 | K41: =IF(B41="","",CONCATENATE("CXG-",TEXT(B41,"MMYY"))) -> CXG-0425
J42: =TEXT(B42,"MM/YYYY") -> 12/1899 | K42: =IF(B42="","",CONCATENATE("CXG-",TEXT(B42,"MMYY")))
A43: 6c9f5a4e | B43: 45779 | C43: TW010425184 | D43: Descontos | E43: 253.44 | H43: TW - Suporte Agrícola | J43: =TEXT(B43,"MM/YYYY") -> 05/2025 | K43: =IF(B43="","",CONCATENATE("CXG-",TEXT(B43,"MMYY"))) -> CXG-0525
A44: 3063c02f | B44: 45779 | C44: TW010425184 | D44: S.Grão - Sicredi | E44: 500 | H44: TW - Suporte Agrícola | J44: =TEXT(B44,"MM/YYYY") -> 05/2025 | K44: =IF(B44="","",CONCATENATE("CXG-",TEXT(B44,"MMYY"))) -> CXG-0525
A45: ed5e0df8 | B45: 45782 | C45: TW070525195 | D45: Terceiros | E45: 50000 | H45: TW - Suporte Agrícola | J45: =TEXT(B45,"MM/YYYY") -> 05/2025 | K45: =IF(B45="","",CONCATENATE("CXG-",TEXT(B45,"MMYY"))) -> CXG-0525
A46: 795f415d | B46: 45786 | C46: TW070525195 | D46: S.Grão - Sicredi | E46: 70000 | H46: TW - Suporte Agrícola | J46: =TEXT(B46,"MM/YYYY") -> 05/2025 | K46: =IF(B46="","",CONCATENATE("CXG-",TEXT(B46,"MMYY"))) -> CXG-0525
A47: 5d29ddc4 | B47: 45790 | C47: TW070525195 | D47: S.Grão - Sicredi | E47: 4858.49 | G47: Seguro Iveco | H47: TW - Suporte Agrícola | J47: =TEXT(B47,"MM/YYYY") -> 05/2025 | K47: =IF(B47="","",CONCATENATE("CXG-",TEXT(B47,"MMYY"))) -> CXG-0525
A48: 3673dda5 | B48: 45790 | C48: TW070525195 | D48: S.Grão - Sicredi | E48: 13744.12 | G48: Parcela Iveco | H48: TW - Suporte Agrícola | J48: =TEXT(B48,"MM/YYYY") -> 05/2025 | K48: =IF(B48="","",CONCATENATE("CXG-",TEXT(B48,"MMYY"))) -> CXG-0525
A49: 45db4f20 | B49: 45790 | C49: TW070525195 | D49: N.Nordeste - B.Brasil | E49: 9740 | G49: Multa Alvaci | H49: TW - Suporte Agrícola | J49: =TEXT(B49,"MM/YYYY") -> 05/2025 | K49: =IF(B49="","",CONCATENATE("CXG-",TEXT(B49,"MMYY"))) -> CXG-0525
A50: 55f4b649 | B50: 45791 | C50: TW070525195 | D50: N.Nordeste - B.Brasil | E50: 6400 | G50: Transbordo Alvaci e André | H50: TW - Suporte Agrícola | J50: =TEXT(B50,"MM/YYYY") -> 05/2025 | K50: =IF(B50="","",CONCATENATE("CXG-",TEXT(B50,"MMYY"))) -> CXG-0525
A51: 3b5821a8 | B51: 45791 | C51: TW070525195 | D51: N.Nordeste - B.Brasil | E51: 3600 | G51: Transbordo Alvaci e André | H51: TW - Suporte Agrícola | J51: =TEXT(B51,"MM/YYYY") -> 05/2025 | K51: =IF(B51="","",CONCATENATE("CXG-",TEXT(B51,"MMYY"))) -> CXG-0525
A52: 7c98722c | B52: 45792 | C52: SR30012567 | D52: N.Nordeste - B.Brasil | E52: 7605.8 | G52: Dia 29/01 - Comprovante de 20.000,00 do Adiantamento | H52: SR - Sergio Rocha | J52: =TEXT(B52,"MM/YYYY") -> 05/2025 | K52: =IF(B52="","",CONCATENATE("CXG-",TEXT(B52,"MMYY"))) -> CXG-0525
A53: 586c747c | B53: 45793 | C53: TW070525195 | D53: Descontos | E53: 394.03 | G53: André Faltou 9,33 Scs dia 12/05 | H53: TW - Suporte Agrícola | J53: =TEXT(B53,"MM/YYYY") -> 05/2025 | K53: =IF(B53="","",CONCATENATE("CXG-",TEXT(B53,"MMYY"))) -> CXG-0525
A54: 77a50922 | B54: 45793 | C54: TW070525195 | D54: N.Nordeste - B.Brasil | E54: 1201.85 | G54: Revisão Alvaci | H54: TW - Suporte Agrícola | J54: =TEXT(B54,"MM/YYYY") -> 05/2025 | K54: =IF(B54="","",CONCATENATE("CXG-",TEXT(B54,"MMYY"))) -> CXG-0525
A55: 64cefb3b | B55: 45797 | C55: TW070525195 | D55: Terceiros | E55: 71040 | G55: Mari | H55: TW - Suporte Agrícola | J55: =TEXT(B55,"MM/YYYY") -> 05/2025 | K55: =IF(B55="","",CONCATENATE("CXG-",TEXT(B55,"MMYY"))) -> CXG-0525
A56: 63daf8d7 | B56: 45797 | C56: TW070525195 | D56: Terceiros | E56: 40000 | G56: Clodoaldo | H56: TW - Suporte Agrícola | J56: =TEXT(B56,"MM/YYYY") -> 05/2025 | K56: =IF(B56="","",CONCATENATE("CXG-",TEXT(B56,"MMYY"))) -> CXG-0525
A57: 41cba62a | B57: 45798 | C57: TW070525195 | D57: Terceiros | E57: 40000 | G57: Clodoando | H57: TW - Suporte Agrícola | J57: =TEXT(B57,"MM/YYYY") -> 05/2025 | K57: =IF(B57="","",CONCATENATE("CXG-",TEXT(B57,"MMYY"))) -> CXG-0525
A58: 05a2ad5e | B58: 45798 | C58: TW070525195 | D58: Descontos | E58: 1003.59 | G58: Mario Faltou 16,34 Scs dia 16/05 | H58: TW - Suporte Agrícola | J58: =TEXT(B58,"MM/YYYY") -> 05/2025 | K58: =IF(B58="","",CONCATENATE("CXG-",TEXT(B58,"MMYY"))) -> CXG-0525
A59: 04b1bd5d | B59: 45798 | C59: TW070525195 | D59: N.Nordeste - B.Brasil | E59: 20000 | H59: TW - Suporte Agrícola | J59: =TEXT(B59,"MM/YYYY") -> 05/2025 | K59: =IF(B59="","",CONCATENATE("CXG-",TEXT(B59,"MMYY"))) -> CXG-0525
A60: 8626f53c | B60: 45802 | C60: TW070525195 | D60: S.Grão - Sicredi | E60: 100 | G60: Gorjeta Alvaci "Policia" | H60: TW - Suporte Agrícola | J60: =TEXT(B60,"MM/YYYY") -> 05/2025 | K60: =IF(B60="","",CONCATENATE("CXG-",TEXT(B60,"MMYY"))) -> CXG-0525
A61: 38df8fa8 | B61: 45804 | C61: TW070525195 | D61: Descontos | E61: 88 | G61: Marques Faltou 6,00 Scs dia 23/05 | H61: TW - Suporte Agrícola | J61: =TEXT(B61,"MM/YYYY") -> 05/2025 | K61: =IF(B61="","",CONCATENATE("CXG-",TEXT(B61,"MMYY"))) -> CXG-0525
A62: 202440f1 | B62: 45804 | C62: TW070525195 | D62: Terceiros | E62: 35000 | G62: Clodoaldo | H62: TW - Suporte Agrícola | J62: =TEXT(B62,"MM/YYYY") -> 05/2025 | K62: =IF(B62="","",CONCATENATE("CXG-",TEXT(B62,"MMYY"))) -> CXG-0525
A63: 48107f66 | B63: 45805 | C63: TW070525195 | D63: Terceiros | E63: 4900 | G63: Clodoaldo | H63: TW - Suporte Agrícola | J63: =TEXT(B63,"MM/YYYY") -> 05/2025 | K63: =IF(B63="","",CONCATENATE("CXG-",TEXT(B63,"MMYY"))) -> CXG-0525
A64: a9417c92 | B64: 45805 | C64: TW070525195 | D64: Terceiros | E64: 56005 | G64: Clodoaldo | H64: TW - Suporte Agrícola | J64: =TEXT(B64,"MM/YYYY") -> 05/2025 | K64: =IF(B64="","",CONCATENATE("CXG-",TEXT(B64,"MMYY"))) -> CXG-0525
A65: 17e5246b | B65: 45806 | C65: TW070525195 | D65: N.Nordeste - B.Brasil | E65: 118000 | H65: TW - Suporte Agrícola | J65: =TEXT(B65,"MM/YYYY") -> 05/2025 | K65: =IF(B65="","",CONCATENATE("CXG-",TEXT(B65,"MMYY"))) -> CXG-0525
A66: 4e47d097 | B66: 45806 | C66: TW070525195 | D66: Terceiros | E66: 19200 | G66: Clodoaldo | H66: TW - Suporte Agrícola | J66: =TEXT(B66,"MM/YYYY") -> 05/2025 | K66: =IF(B66="","",CONCATENATE("CXG-",TEXT(B66,"MMYY"))) -> CXG-0525
A67: aa3bb528 | B67: 45810 | C67: TW020625206 | D67: Descontos | E67: 630 | G67: Mario Faltou -12,00 Scs dia 29/05 | H67: TW - Suporte Agrícola | J67: =TEXT(B67,"MM/YYYY") -> 06/2025 | K67: =IF(B67="","",CONCATENATE("CXG-",TEXT(B67,"MMYY"))) -> CXG-0625
A68: 9769a385 | B68: 45810 | C68: TW070525195 | D68: Adiantamento | E68: -22028.76 | G68: Saldo Mês de Junho | H68: TW - Suporte Agrícola | J68: =TEXT(B68,"MM/YYYY") -> 06/2025 | K68: =IF(B68="","",CONCATENATE("CXG-",TEXT(B68,"MMYY"))) -> CXG-0625
A69: 5b5f7c00 | B69: 45810 | C69: TW020625206 | D69: Adiantamento | E69: 22028.76 | G69: Saldo Mês Anterior | H69: TW - Suporte Agrícola | J69: =TEXT(B69,"MM/YYYY") -> 06/2025 | K69: =IF(B69="","",CONCATENATE("CXG-",TEXT(B69,"MMYY"))) -> CXG-0625
A70: 9fec25c7 | B70: 45811 | C70: TW020625206 | D70: S.Grão - Sicredi | E70: 4755.77 | G70: Seguro Iveco | H70: TW - Suporte Agrícola | J70: =TEXT(B70,"MM/YYYY") -> 06/2025 | K70: =IF(B70="","",CONCATENATE("CXG-",TEXT(B70,"MMYY"))) -> CXG-0625
A71: 484dc58b | B71: 45811 | C71: TW020625206 | D71: S.Grão - Sicredi | E71: 13445.29 | G71: Parcela Iveco | H71: TW - Suporte Agrícola | J71: =TEXT(B71,"MM/YYYY") -> 06/2025 | K71: =IF(B71="","",CONCATENATE("CXG-",TEXT(B71,"MMYY"))) -> CXG-0625
A72: 64fd12de | B72: 45811 | C72: TW020625206 | D72: Terceiros | E72: 30000 | G72: Clodoaldo | H72: TW - Suporte Agrícola | J72: =TEXT(B72,"MM/YYYY") -> 06/2025 | K72: =IF(B72="","",CONCATENATE("CXG-",TEXT(B72,"MMYY"))) -> CXG-0625
A73: e9b77722 | B73: 45811 | C73: TW020625206 | D73: Terceiros | E73: 39731 | G73: Clodoaldo | H73: TW - Suporte Agrícola | J73: =TEXT(B73,"MM/YYYY") -> 06/2025 | K73: =IF(B73="","",CONCATENATE("CXG-",TEXT(B73,"MMYY"))) -> CXG-0625
A74: a1064d5b | B74: 45813 | C74: TW020625206 | D74: S.Grão - Sicredi | E74: 4037.88 | G74: Gilvan METEOR | H74: TW - Suporte Agrícola | J74: =TEXT(B74,"MM/YYYY") -> 06/2025 | K74: =IF(B74="","",CONCATENATE("CXG-",TEXT(B74,"MMYY"))) -> CXG-0625
A75: ba87061f | B75: 45815 | C75: TW020625206 | D75: Descontos | E75: 749.7 | G75: Gustavo Faltou -13,33 Scs dia 03/06 | H75: TW - Suporte Agrícola | J75: =TEXT(B75,"MM/YYYY") -> 06/2025 | K75: =IF(B75="","",CONCATENATE("CXG-",TEXT(B75,"MMYY"))) -> CXG-0625
A76: 0726053e | B76: 45815 | C76: TW020625206 | D76: Descontos | E76: 194.4 | G76: Heder Faltou -7,16 Scs dia 03/06 | H76: TW - Suporte Agrícola | J76: =TEXT(B76,"MM/YYYY") -> 06/2025 | K76: =IF(B76="","",CONCATENATE("CXG-",TEXT(B76,"MMYY"))) -> CXG-0625
A77: cc0cb029 | B77: 45820 | C77: TW020625206 | D77: Descontos | E77: 430 | G77: Marques Faltou -10,0 Scs dia 07/06 | H77: TW - Suporte Agrícola | J77: =TEXT(B77,"MM/YYYY") -> 06/2025 | K77: =IF(B77="","",CONCATENATE("CXG-",TEXT(B77,"MMYY"))) -> CXG-0625
A78: 94d8f152 | B78: 45821 | C78: TW020625206 | D78: N.Nordeste - B.Brasil | E78: 100000 | H78: TW - Suporte Agrícola | J78: =TEXT(B78,"MM/YYYY") -> 06/2025 | K78: =IF(B78="","",CONCATENATE("CXG-",TEXT(B78,"MMYY"))) -> CXG-0625
A79: 8824b188 | B79: 45825 | C79: TW020625206 | D79: N.Nordeste - B.Brasil | E79: 300 | G79: Conserto IVECO | H79: TW - Suporte Agrícola | J79: =TEXT(B79,"MM/YYYY") -> 06/2025 | K79: =IF(B79="","",CONCATENATE("CXG-",TEXT(B79,"MMYY"))) -> CXG-0625
A80: 557f15f1 | B80: 45826 | C80: TW020625206 | D80: N.Nordeste - B.Brasil | E80: 50000 | H80: TW - Suporte Agrícola | J80: =TEXT(B80,"MM/YYYY") -> 06/2025 | K80: =IF(B80="","",CONCATENATE("CXG-",TEXT(B80,"MMYY"))) -> CXG-0625
A81: 94331ff2 | B81: 45826 | C81: TW020625206 | D81: N.Nordeste - B.Brasil | E81: 1135.52 | G81: Iveco Peças - Maio | H81: TW - Suporte Agrícola | J81: =TEXT(B81,"MM/YYYY") -> 06/2025 | K81: =IF(B81="","",CONCATENATE("CXG-",TEXT(B81,"MMYY"))) -> CXG-0625
A82: 8107b41a | B82: 45826 | C82: TW020625206 | D82: N.Nordeste - B.Brasil | E82: 1150 | G82: Iveco Peças - Junho | H82: TW - Suporte Agrícola | J82: =TEXT(B82,"MM/YYYY") -> 06/2025 | K82: =IF(B82="","",CONCATENATE("CXG-",TEXT(B82,"MMYY"))) -> CXG-0625
A83: b98f2c76 | B83: 45826 | C83: TW020625206 | D83: Terceiros | E83: 14000 | G83: Clodoaldo | H83: TW - Suporte Agrícola | J83: =TEXT(B83,"MM/YYYY") -> 06/2025 | K83: =IF(B83="","",CONCATENATE("CXG-",TEXT(B83,"MMYY"))) -> CXG-0625
A84: 8cb7c8d8 | B84: 45826 | C84: TW020625206 | D84: Terceiros | E84: 30000 | G84: Clodoaldo | H84: TW - Suporte Agrícola | J84: =TEXT(B84,"MM/YYYY") -> 06/2025 | K84: =IF(B84="","",CONCATENATE("CXG-",TEXT(B84,"MMYY"))) -> CXG-0625
A85: 65a604dc | B85: 45826 | C85: TW020625206 | D85: N.Nordeste - B.Brasil | E85: 50000 | H85: TW - Suporte Agrícola | J85: =TEXT(B85,"MM/YYYY") -> 06/2025 | K85: =IF(B85="","",CONCATENATE("CXG-",TEXT(B85,"MMYY"))) -> CXG-0625
A86: a7f04f62 | B86: 45828 | C86: TW020625206 | D86: Terceiros | E86: 62762 | G86: Netto Serra | H86: TW - Suporte Agrícola | J86: =TEXT(B86,"MM/YYYY") -> 06/2025 | K86: =IF(B86="","",CONCATENATE("CXG-",TEXT(B86,"MMYY"))) -> CXG-0625
A87: 0d4b1b70 | B87: 45828 | C87: TW020625206 | D87: Terceiros | E87: 13900 | G87: Clodoaldo | H87: TW - Suporte Agrícola | J87: =TEXT(B87,"MM/YYYY") -> 06/2025 | K87: =IF(B87="","",CONCATENATE("CXG-",TEXT(B87,"MMYY"))) -> CXG-0625
A88: 47a0c648 | B88: 45828 | C88: TW020625206 | D88: Terceiros | E88: 13945.66 | G88: Clodoaldo | H88: TW - Suporte Agrícola | J88: =TEXT(B88,"MM/YYYY") -> 06/2025 | K88: =IF(B88="","",CONCATENATE("CXG-",TEXT(B88,"MMYY"))) -> CXG-0625
A89: fa76b3da | B89: 45828 | C89: TW020625206 | D89: Terceiros | E89: 48000 | G89: Clodoaldo | H89: TW - Suporte Agrícola | J89: =TEXT(B89,"MM/YYYY") -> 06/2025 | K89: =IF(B89="","",CONCATENATE("CXG-",TEXT(B89,"MMYY"))) -> CXG-0625
A90: bb487bab | B90: 45831 | C90: TW020625206 | D90: Terceiros | E90: 25000 | G90: Clodoaldo | H90: TW - Suporte Agrícola | J90: =TEXT(B90,"MM/YYYY") -> 06/2025 | K90: =IF(B90="","",CONCATENATE("CXG-",TEXT(B90,"MMYY"))) -> CXG-0625
A91: 467ea523 | B91: 45832 | C91: TW020625206 | D91: Descontos | E91: 266.4 | G91: Douglas Faltou -8,33 Scs dia 19/06 | H91: TW - Suporte Agrícola | J91: =TEXT(B91,"MM/YYYY") -> 06/2025 | K91: =IF(B91="","",CONCATENATE("CXG-",TEXT(B91,"MMYY"))) -> CXG-0625
A92: f30505e6 | B92: 45832 | C92: TW020625206 | D92: Terceiros | E92: 30000 | G92: Diego | H92: TW - Suporte Agrícola | J92: =TEXT(B92,"MM/YYYY") -> 06/2025 | K92: =IF(B92="","",CONCATENATE("CXG-",TEXT(B92,"MMYY"))) -> CXG-0625
A93: 5af072eb | B93: 45833 | C93: TW020625206 | D93: Terceiros | E93: 14554 | G93: Diego | H93: TW - Suporte Agrícola | J93: =TEXT(B93,"MM/YYYY") -> 06/2025 | K93: =IF(B93="","",CONCATENATE("CXG-",TEXT(B93,"MMYY"))) -> CXG-0625
A94: bbad6345 | B94: 45833 | C94: SR30012567 | D94: N.Nordeste - B.Brasil | E94: 28316.2 | H94: SR - Sergio Rocha | J94: =TEXT(B94,"MM/YYYY") -> 06/2025 | K94: =IF(B94="","",CONCATENATE("CXG-",TEXT(B94,"MMYY"))) -> CXG-0625
A95: 16cbe36c | B95: 45833 | C95: TW020625206 | D95: Terceiros | E95: 20000 | G95: Clodoaldo | H95: TW - Suporte Agrícola | J95: =TEXT(B95,"MM/YYYY") -> 06/2025 | K95: =IF(B95="","",CONCATENATE("CXG-",TEXT(B95,"MMYY"))) -> CXG-0625
A96: c5883388 | B96: 45833 | C96: TW020625206 | D96: Terceiros | E96: 74520 | G96: Clodoaldo | H96: TW - Suporte Agrícola | J96: =TEXT(B96,"MM/YYYY") -> 06/2025 | K96: =IF(B96="","",CONCATENATE("CXG-",TEXT(B96,"MMYY"))) -> CXG-0625
A97: d7400c92 | B97: 45833 | C97: TW020625206 | D97: Terceiros | E97: 80000 | G97: André JP | H97: TW - Suporte Agrícola | J97: =TEXT(B97,"MM/YYYY") -> 06/2025 | K97: =IF(B97="","",CONCATENATE("CXG-",TEXT(B97,"MMYY"))) -> CXG-0625
A98: fcd79d08 | B98: 45833 | C98: TW020625206 | D98: Terceiros | E98: 76423 | G98: André Sapé | H98: TW - Suporte Agrícola | J98: =TEXT(B98,"MM/YYYY") -> 06/2025 | K98: =IF(B98="","",CONCATENATE("CXG-",TEXT(B98,"MMYY"))) -> CXG-0625
A99: 90aae087 | B99: 45838 | C99: TW020625206 | D99: Santiagro | E99: 38580 | G99: Santiagro | H99: TW - Suporte Agrícola | J99: =TEXT(B99,"MM/YYYY") -> 06/2025 | K99: =IF(B99="","",CONCATENATE("CXG-",TEXT(B99,"MMYY"))) -> CXG-0625
A100: f6cbf751 | B100: 45838 | C100: TW020625206 | D100: Santiagro | E100: 100000 | G100: Santiagro | H100: TW - Suporte Agrícola | J100: =TEXT(B100,"MM/YYYY") -> 06/2025 | K100: =IF(B100="","",CONCATENATE("CXG-",TEXT(B100,"MMYY"))) -> CXG-0625
A101: fc46e396 | B101: 45838 | C101: TW020625206 | D101: Santiagro | E101: 99000 | G101: Santiagro | H101: TW - Suporte Agrícola | J101: =TEXT(B101,"MM/YYYY") -> 06/2025 | K101: =IF(B101="","",CONCATENATE("CXG-",TEXT(B101,"MMYY"))) -> CXG-0625
A102: f9bb3624 | B102: 45838 | C102: TW020625206 | D102: Descontos | E102: 2.42 | H102: TW - Suporte Agrícola | J102: =TEXT(B102,"MM/YYYY") -> 06/2025 | K102: =IF(B102="","",CONCATENATE("CXG-",TEXT(B102,"MMYY"))) -> CXG-0625
A103: 4849fae7 | B103: 45840 | C103: TW010725214 | D103: N.Nordeste - B.Brasil | E103: 18149.76 | G103: Bolto Meteor | H103: TW - Suporte Agrícola | J103: =TEXT(B103,"MM/YYYY") -> 07/2025 | K103: =IF(B103="","",CONCATENATE("CXG-",TEXT(B103,"MMYY"))) -> CXG-0725
A104: 5f6982b5 | B104: 45840 | C104: TW010725214 | D104: N.Nordeste - B.Brasil | E104: 4755.77 | G104: IVECO SEGURO | H104: TW - Suporte Agrícola | J104: =TEXT(B104,"MM/YYYY") -> 07/2025 | K104: =IF(B104="","",CONCATENATE("CXG-",TEXT(B104,"MMYY"))) -> CXG-0725
A105: 71b4a46e | B105: 45840 | C105: TW010725214 | D105: N.Nordeste - B.Brasil | E105: 13445.29 | G105: IVECO PARCELA | H105: TW - Suporte Agrícola | J105: =TEXT(B105,"MM/YYYY") -> 07/2025 | K105: =IF(B105="","",CONCATENATE("CXG-",TEXT(B105,"MMYY"))) -> CXG-0725
A106: 217d3c5a | B106: 45840 | C106: TW010725214 | D106: N.Nordeste - B.Brasil | E106: 1131 | G106: IVECO PEÇAS | H106: TW - Suporte Agrícola | J106: =TEXT(B106,"MM/YYYY") -> 07/2025 | K106: =IF(B106="","",CONCATENATE("CXG-",TEXT(B106,"MMYY"))) -> CXG-0725
A107: 869d11b1 | B107: 45840 | C107: TW010725214 | D107: N.Nordeste - B.Brasil | E107: 2400 | G107: RODAS METEOR | H107: TW - Suporte Agrícola | J107: =TEXT(B107,"MM/YYYY") -> 07/2025 | K107: =IF(B107="","",CONCATENATE("CXG-",TEXT(B107,"MMYY"))) -> CXG-0725
A108: f0d31982 | B108: 45840 | C108: TW010725214 | D108: Santiagro | E108: 64000 | G108: Santiagro | H108: TW - Suporte Agrícola | J108: =TEXT(B108,"MM/YYYY") -> 07/2025 | K108: =IF(B108="","",CONCATENATE("CXG-",TEXT(B108,"MMYY"))) -> CXG-0725
A109: f8c1f00f | B109: 45841 | C109: TW010725214 | D109: N.Nordeste - B.Brasil | E109: 743.12 | G109: Seguro Meteor | H109: TW - Suporte Agrícola | J109: =TEXT(B109,"MM/YYYY") -> 07/2025 | K109: =IF(B109="","",CONCATENATE("CXG-",TEXT(B109,"MMYY"))) -> CXG-0725
A110: 404fc983 | B110: 45841 | C110: TW010725214 | D110: N.Nordeste - B.Brasil | E110: 4037.88 | G110: Seguro Meteor | H110: TW - Suporte Agrícola | J110: =TEXT(B110,"MM/YYYY") -> 07/2025 | K110: =IF(B110="","",CONCATENATE("CXG-",TEXT(B110,"MMYY"))) -> CXG-0725
A111: 991a9d82 | B111: 45841 | C111: TW010725214 | D111: Terceiros | E111: 30500 | G111: Clodoaldo | H111: TW - Suporte Agrícola | J111: =TEXT(B111,"MM/YYYY") -> 07/2025 | K111: =IF(B111="","",CONCATENATE("CXG-",TEXT(B111,"MMYY"))) -> CXG-0725
A112: 71afc302 | B112: 45841 | C112: TW010725214 | D112: Terceiros | E112: 100774 | G112: Clodoaldo / Cheque | H112: TW - Suporte Agrícola | J112: =TEXT(B112,"MM/YYYY") -> 07/2025 | K112: =IF(B112="","",CONCATENATE("CXG-",TEXT(B112,"MMYY"))) -> CXG-0725
A113: ec1971c5 | B113: 45845 | C113: TW010725214 | D113: Descontos | E113: 243 | G113: Douglas Faltou -8,00 Scs dia 03/07 | H113: TW - Suporte Agrícola | J113: =TEXT(B113,"MM/YYYY") -> 07/2025 | K113: =IF(B113="","",CONCATENATE("CXG-",TEXT(B113,"MMYY"))) -> CXG-0725
A114: 84e361ab | B114: 45845 | C114: TW010725214 | D114: Terceiros | E114: 49611.66 | G114: Clodoaldo | H114: TW - Suporte Agrícola | J114: =TEXT(B114,"MM/YYYY") -> 07/2025 | K114: =IF(B114="","",CONCATENATE("CXG-",TEXT(B114,"MMYY"))) -> CXG-0725
... A163: 1d81fe58 | B163: 45869 | C163: TW310725224 | D163: Terceiros | E163: 50000 | G163: Santa Cruz - Comprovante de 74.960,00 | H163: TW - Suporte Agrícola | J163: =TEXT(B163,"MM/YYYY") -> 07/2025 | K163: =IF(B163="","",CONCATENATE("CXG-",TEXT(B163,"MMYY"))) -> CXG-0725
A164: 1c221aa6 | B164: 45869 | C164: TW010725214 | D164: Descontos | E164: 2.78 | H164: TW - Suporte Agrícola | J164: =TEXT(B164,"MM/YYYY") -> 07/2025 | K164: =IF(B164="","",CONCATENATE("CXG-",TEXT(B164,"MMYY"))) -> CXG-0725
A165: db9b66e2 | B165: 45869 | C165: TW310725224 | D165: Terceiros | E165: 3737.07 | G165: Santa Cruz | H165: TW - Suporte Agrícola | J165: =TEXT(B165,"MM/YYYY") -> 07/2025 | K165: =IF(B165="","",CONCATENATE("CXG-",TEXT(B165,"MMYY"))) -> CXG-0725
A166: 9a6437e0 | B166: 45869 | C166: TW310725224 | D166: Terceiros | E166: 25000 | G166: Clodoaldo | H166: TW - Suporte Agrícola | J166: =TEXT(B166,"MM/YYYY") -> 07/2025 | K166: =IF(B166="","",CONCATENATE("CXG-",TEXT(B166,"MMYY"))) -> CXG-0725
A167: 1ff994e2 | B167: 45869 | C167: TW310725224 | D167: Terceiros | E167: 51460 | G167: Clodoaldo Cheque | H167: TW - Suporte Agrícola | J167: =TEXT(B167,"MM/YYYY") -> 07/2025 | K167: =IF(B167="","",CONCATENATE("CXG-",TEXT(B167,"MMYY"))) -> CXG-0725
A168: 16f3925c | B168: 45870 | C168: TW310725224 | D168: Terceiros | E168: 39450 | G168: Clodoaldo | H168: TW - Suporte Agrícola | J168: =TEXT(B168,"MM/YYYY") -> 08/2025 | K168: =IF(B168="","",CONCATENATE("CXG-",TEXT(B168,"MMYY"))) -> CXG-0825
A169: 82b34eac | B169: 45870 | C169: TW310725224 | D169: Terceiros | E169: 20000 | G169: Clodoaldo | H169: TW - Suporte Agrícola | J169: =TEXT(B169,"MM/YYYY") -> 08/2025 | K169: =IF(B169="","",CONCATENATE("CXG-",TEXT(B169,"MMYY"))) -> CXG-0825
A170: e07b5b8c | B170: 45873 | C170: TW310725224 | D170: S.Grão - Sicredi | E170: 723.59 | G170: Seguro Meteor | H170: TW - Suporte Agrícola | J170: =TEXT(B170,"MM/YYYY") -> 08/2025 | K170: =IF(B170="","",CONCATENATE("CXG-",TEXT(B170,"MMYY"))) -> CXG-0825
A171: 9fcfbaeb | B171: 45873 | C171: TW310725224 | D171: S.Grão - Sicredi | E171: 4755.77 | G171: Seguro IVECO | H171: TW - Suporte Agrícola | J171: =TEXT(B171,"MM/YYYY") -> 08/2025 | K171: =IF(B171="","",CONCATENATE("CXG-",TEXT(B171,"MMYY"))) -> CXG-0825
A172: c783ee7a | B172: 45873 | C172: TW310725224 | D172: S.Grão - Sicredi | E172: 1741 | G172: Peças Iveco | H172: TW - Suporte Agrícola | J172: =TEXT(B172,"MM/YYYY") -> 08/2025 | K172: =IF(B172="","",CONCATENATE("CXG-",TEXT(B172,"MMYY"))) -> CXG-0825
A173: 5097742c | B173: 45873 | C173: TW310725224 | D173: S.Grão - Sicredi | E173: 1131 | G173: Peças Iveco | H173: TW - Suporte Agrícola | J173: =TEXT(B173,"MM/YYYY") -> 08/2025 | K173: =IF(B173="","",CONCATENATE("CXG-",TEXT(B173,"MMYY"))) -> CXG-0825
A174: b527e6df | B174: 45873 | C174: TW310725224 | D174: S.Grão - Sicredi | E174: 2400 | G174: Rodas Meteor | H174: TW - Suporte Agrícola | J174: =TEXT(B174,"MM/YYYY") -> 08/2025 | K174: =IF(B174="","",CONCATENATE("CXG-",TEXT(B174,"MMYY"))) -> CXG-0825
A175: 9800a2b3 | B175: 45873 | C175: TW310725224 | D175: S.Grão - Sicredi | E175: 13445.29 | G175: Iveco Parcela | H175: TW - Suporte Agrícola | J175: =TEXT(B175,"MM/YYYY") -> 08/2025 | K175: =IF(B175="","",CONCATENATE("CXG-",TEXT(B175,"MMYY"))) -> CXG-0825
...

Sheet PagFreteIndividal
A1: idpag | B1: id | C1: data | D1: motorista | E1: valor | F1: conta | G1: anotações | H1: idpedidodefrete | I1: MesAno | J1: PedCxMensal
A2: 311bed82 | B2: 0125757 | C2: 45700 | D2: Anderson André | E2: -60.5 | F2: Descontos | H2: AT170125124 | I2: =TEXT(C2,"MM/YYYY") -> 02/2025 | J2: =IF(C2="","",CONCATENATE("CXG-",TEXT(C2,"MMYY"))) -> CXG-0225
A3: cde8dab3 | B3: 0125673 | C3: 45700 | D3: Williams | E3: -59.4 | F3: Descontos | H3: AT170125124 | I3: =TEXT(C3,"MM/YYYY") -> 02/2025 | J3: =IF(C3="","",CONCATENATE("CXG-",TEXT(C3,"MMYY"))) -> CXG-0225
A4: e006e38e | B4: 9b9809f1 | C4: 45673 | D4: Adson | E4: -45 | F4: Pgmt Indevido | H4: AT170125124 | I4: =TEXT(C4,"MM/YYYY") -> 01/2025 | J4: =IF(C4="","",CONCATENATE("CXG-",TEXT(C4,"MMYY"))) -> CXG-0125
A5: 97d42bc9 | B5: 0125637 | C5: 45700 | D5: João Italo | E5: -3.9 | F5: Descontos | H5: AT170125124 | I5: =TEXT(C5,"MM/YYYY") -> 02/2025 | J5: =IF(C5="","",CONCATENATE("CXG-",TEXT(C5,"MMYY"))) -> CXG-0225
A6: f248b18d | B6: 04252691 | C6: 45762 | D6: André Luiz | E6: -2 | F6: Descontos | H6: AT170125124 | I6: =TEXT(C6,"MM/YYYY") -> 04/2025 | J6: =IF(C6="","",CONCATENATE("CXG-",TEXT(C6,"MMYY"))) -> CXG-0425
A7: d639b5ac | B7: 06253413 | C7: 45819 | D7: Eduardo Marcelo | E7: 0.05 | F7: Descontos | H7: AT170125124 | I7: =TEXT(C7,"MM/YYYY") -> 06/2025 | J7: =IF(C7="","",CONCATENATE("CXG-",TEXT(C7,"MMYY"))) -> CXG-0625
A8: f3087441 | B8: 12258654 | C8: 45999 | D8: Jose Cícero- MT | E8: 0.05 | F8: Descontos | H8: AT170125124 | I8: =TEXT(C8,"MM/YYYY") -> 12/2025 | J8: =IF(C8="","",CONCATENATE("CXG-",TEXT(C8,"MMYY"))) -> CXG-1225
A9: 3380f718 | B9: 0125920 | C9: 45688 | D9: Vitor | E9: 0.1 | F9: Descontos | H9: AT170125124 | I9: =TEXT(C9,"MM/YYYY") -> 01/2025 | J9: =IF(C9="","",CONCATENATE("CXG-",TEXT(C9,"MMYY"))) -> CXG-0125
A10: 4a407c8a | B10: e05cf712 | C10: 45672 | D10: José Adelson - SR | E10: 15655 | F10: N.Nordeste - B.Brasil | H10: SR16012556 | I10: =TEXT(C10,"MM/YYYY") -> 01/2025 | J10: =IF(C10="","",CONCATENATE("CXG-",TEXT(C10,"MMYY"))) -> CXG-0125
A11: cbae2c88 | B11: e05cf712 | C11: 45672 | D11: José Adelson - SR | E11: 0.2 | F11: Descontos | H11: SR16012556 | I11: =TEXT(C11,"MM/YYYY") -> 01/2025 | J11: =IF(C11="","",CONCATENATE("CXG-",TEXT(C11,"MMYY"))) -> CXG-0125
A12: 3368b0d5 | B12: 12258931 | C12: 46003 | D12: Edvaldo Cirino | E12: 0.1 | F12: Descontos | H12: AT170125124 | I12: =TEXT(C12,"MM/YYYY") -> 12/2025 | J12: =IF(C12="","",CONCATENATE("CXG-",TEXT(C12,"MMYY"))) -> CXG-1225
A13: b54c9831 | B13: 0125420 | C13: 45713 | D13: Adson | E13: 0.2 | F13: Descontos | H13: AT170125124 | I13: =TEXT(C13,"MM/YYYY") -> 02/2025 | J13: =IF(C13="","",CONCATENATE("CXG-",TEXT(C13,"MMYY"))) -> CXG-0225
... A46: 7c9099dd | B46: 12258989 | C46: 46001 | D46: Paulo Edvaldo | E46: 120 | F46: S.Grão - Sicredi | H46: AT170125124 | I46: =TEXT(C46,"MM/YYYY") -> 12/2025 | J46: =IF(C46="","",CONCATENATE("CXG-",TEXT(C46,"MMYY"))) -> CXG-1225
A47: 68d1235c | B47: 0125597 | C47: 45682 | D47: Amaury | E47: 124.1 | F47: N.Nordeste - B.Brasil | G47: Comprovante de 6.000,00 | H47: AT170125124 | I47: =TEXT(C47,"MM/YYYY") -> 01/2025 | J47: =IF(C47="","",CONCATENATE("CXG-",TEXT(C47,"MMYY"))) -> CXG-0125
A48: fb3a9762 | B48: 09255767 | C48: 45910 | D48: Agro Real | E48: 136.94 | F48: Descontos | H48: AT170125124 | I48: =TEXT(C48,"MM/YYYY") -> 09/2025 | J48: =IF(C48="","",CONCATENATE("CXG-",TEXT(C48,"MMYY"))) -> CXG-0925
A49: 1d080538 | B49: 0125588 | C49: 45682 | D49: Werlen | E49: 141.6 | F49: N.Nordeste - B.Brasil | G49: Comprovante de 6.000,00 | H49: AT170125124 | I49: =TEXT(C49,"MM/YYYY") -> 01/2025 | J49: =IF(C49="","",CONCATENATE("CXG-",TEXT(C49,"MMYY"))) -> CXG-0125
A50: 2dda88c6 | B50: 0125726 | C50: 45682 | D50: Ricardo Washington | E50: 146.7 | F50: N.Nordeste - B.Brasil | G50: Comprovante de 6.000,00 | H50: AT170125124 | I50: =TEXT(C50,"MM/YYYY") -> 01/2025 | J50: =IF(C50="","",CONCATENATE("CXG-",TEXT(C50,"MMYY"))) -> CXG-0125
A51: c7774e44 | B51: 0125707 | C51: 45682 | D51: Amaury | E51: 198.2 | F51: N.Nordeste - B.Brasil | G51: Comprovante de 6.000,00 | H51: AT170125124 | I51: =TEXT(C51,"MM/YYYY") -> 01/2025 | J51: =IF(C51="","",CONCATENATE("CXG-",TEXT(C51,"MMYY"))) -> CXG-0125
A52: b8b703a1 | B52: 0125697 | C52: 45682 | D52: Werlen | E52: 221.6 | F52: N.Nordeste - B.Brasil | G52: Comprovante de 6.000,00 | H52: AT170125124 | I52: =TEXT(C52,"MM/YYYY") -> 01/2025 | J52: =IF(C52="","",CONCATENATE("CXG-",TEXT(C52,"MMYY"))) -> CXG-0125
A53: 69d12755 | B53: 10257033 | C53: 45952 | D53: Tomás Muller 1 | E53: 246 | F53: S.Grão - Sicredi | H53: AT170125124 | I53: =TEXT(C53,"MM/YYYY") -> 10/2025 | J53: =IF(C53="","",CONCATENATE("CXG-",TEXT(C53,"MMYY"))) -> CXG-1025
A54: b79aecfc | B54: 10257240 | C54: 45964 | D54: Jose Cícero- MT | E54: 287.2 | F54: Descontos | H54: AT170125124 | I54: =TEXT(C54,"MM/YYYY") -> 11/2025 | J54: =IF(C54="","",CONCATENATE("CXG-",TEXT(C54,"MMYY"))) -> CXG-1125
A55: e86442fe | B55: 06253307 | C55: 45814 | D55: Ls 4 Eixo Santa Fé | E55: 305.2 | F55: Descontos | H55: AT170125124 | I55: =TEXT(C55,"MM/YYYY") -> 06/2025 | J55: =IF(C55="","",CONCATENATE("CXG-",TEXT(C55,"MMYY"))) -> CXG-0625
A56: 4d79bcfe | B56: 11258020 | C56: 45987 | D56: Juraci | E56: 307 | F56: Descontos | H56: AT170125124 | I56: =TEXT(C56,"MM/YYYY") -> 11/2025 | J56: =IF(C56="","",CONCATENATE("CXG-",TEXT(C56,"MMYY"))) -> CXG-1125
A57: 8113910d | B57: 10256590 | C57: 45945 | D57: Edson - André | E57: 325.4 | F57: Descontos | H57: AT170125124 | I57: =TEXT(C57,"MM/YYYY") -> 10/2025 | J57: =IF(C57="","",CONCATENATE("CXG-",TEXT(C57,"MMYY"))) -> CXG-1025
A58: 8ab72ea5 | B58: 12258995 | C58: 46001 | D58: Edvaldo Barreto | E58: 338.75 | F58: S.Grão - Sicredi | H58: AT170125124 | I58: =TEXT(C58,"MM/YYYY") -> 12/2025 | J58: =IF(C58="","",CONCATENATE("CXG-",TEXT(C58,"MMYY"))) -> CXG-1225
A59: 7edfbfd8 | B59: 08255115 | C59: 45888 | D59: André Inacio | E59: 369 | F59: S.Grão - Sicredi | H59: AT170125124 | I59: =TEXT(C59,"MM/YYYY") -> 08/2025 | J59: =IF(C59="","",CONCATENATE("CXG-",TEXT(C59,"MMYY"))) -> CXG-0825
A60: 0f931f2b | B60: 12258692 | C60: 46001 | D60: Paulo | E60: 395.2 | F60: S.Grão - Sicredi | H60: AT170125124 | I60: =TEXT(C60,"MM/YYYY") -> 12/2025 | J60: =IF(C60="","",CONCATENATE("CXG-",TEXT(C60,"MMYY"))) -> CXG-1225
A61: 73d8e341 | B61: 10256613 | C61: 45945 | D61: Michel - Andre | E61: 418.8 | F61: Descontos | H61: AT170125124 | I61: =TEXT(C61,"MM/YYYY") -> 10/2025 | J61: =IF(C61="","",CONCATENATE("CXG-",TEXT(C61,"MMYY"))) -> CXG-1025
A62: c0912e82 | B62: 07254304 | C62: 45848 | D62: Alyson | E62: 498 | F62: Branco - B.Brasil | H62: AT170125124 | I62: =TEXT(C62,"MM/YYYY") -> 07/2025 | J62: =IF(C62="","",CONCATENATE("CXG-",TEXT(C62,"MMYY"))) -> CXG-0725
A63: b1e30de4 | B63: 06253454 | C63: 45817 | D63: Carros GUILHERME | E63: 500 | F63: N.Nordeste - B.Brasil | H63: AT170125124 | I63: =TEXT(C63,"MM/YYYY") -> 06/2025 | J63: =IF(C63="","",CONCATENATE("CXG-",TEXT(C63,"MMYY"))) -> CXG-0625
A64: bb5be85b | B64: 11257752 | C64: 45976 | D64: Oldair - André | E64: 500 | F64: S.Grão - Sicredi | H64: AT170125124 | I64: =TEXT(C64,"MM/YYYY") -> 11/2025 | J64: =IF(C64="","",CONCATENATE("CXG-",TEXT(C64,"MMYY"))) -> CXG-1125
... A71: 926b54a0 | B71: 11258001 | C71: 45988 | D71: Valmir - MT | E71: 600 | F71: S.Grão - Sicredi | H71: AT170125124 | I71: =TEXT(C71,"MM/YYYY") -> 11/2025 | J71: =IF(C71="","",CONCATENATE("CXG-",TEXT(C71,"MMYY"))) -> CXG-1125
A72: 09664c57 | B72: b4fc34bc | C72: 45684 | D72: Rogerio - SR | E72: 13800 | F72: N.Nordeste - B.Brasil | G72: Comprovante de 93.003,00 | H72: SR16012556 | I72: =TEXT(C72,"MM/YYYY") -> 01/2025 | J72: =IF(C72="","",CONCATENATE("CXG-",TEXT(C72,"MMYY"))) -> CXG-0125
A73: 5c0c55b7 | B73: 796941eb | C73: 45684 | D73: Geudo - SR | E73: 14292.2 | F73: N.Nordeste - B.Brasil | G73: Comprovante de 93.003,00 | H73: SR16012556 | I73: =TEXT(C73,"MM/YYYY") -> 01/2025 | J73: =IF(C73="","",CONCATENATE("CXG-",TEXT(C73,"MMYY"))) -> CXG-0125
A74: 11c6049b | B74: 0125382 | C74: 45684 | D74: Mozart - SR | E74: 15904.5 | F74: N.Nordeste - B.Brasil | G74: Comprovante de 93.003,00 | H74: SR16012556 | I74: =TEXT(C74,"MM/YYYY") -> 01/2025 | J74: =IF(C74="","",CONCATENATE("CXG-",TEXT(C74,"MMYY"))) -> CXG-0125
A75: 4aded7a3 | B75: 0125413 | C75: 45684 | D75: Luan Herculano - SR | E75: 16146 | F75: N.Nordeste - B.Brasil | G75: Comprovante de 93.003,00 | H75: SR16012556 | I75: =TEXT(C75,"MM/YYYY") -> 01/2025 | J75: =IF(C75="","",CONCATENATE("CXG-",TEXT(C75,"MMYY"))) -> CXG-0125
A76: dea55917 | B76: 0125400 | C76: 45684 | D76: Alan Marcio - SR | E76: 17001.6 | F76: N.Nordeste - B.Brasil | G76: Comprovante de 93.003,00 | H76: SR16012556 | I76: =TEXT(C76,"MM/YYYY") -> 01/2025 | J76: =IF(C76="","",CONCATENATE("CXG-",TEXT(C76,"MMYY"))) -> CXG-0125
A77: 831e7fab | B77: 0125442 | C77: 45684 | D77: Cesar - SR | E77: 15858.7 | F77: N.Nordeste - B.Brasil | G77: Comprovante de 93.003,00 | H77: SR16012556 | I77: =TEXT(C77,"MM/YYYY") -> 01/2025 | J77: =IF(C77="","",CONCATENATE("CXG-",TEXT(C77,"MMYY"))) -> CXG-0125
A78: 72aa595b | B78: 0125442 | C78: 45684 | D78: Cesar - SR | E78: 2.1 | F78: Descontos | H78: SR16012556 | I78: =TEXT(C78,"MM/YYYY") -> 01/2025 | J78: =IF(C78="","",CONCATENATE("CXG-",TEXT(C78,"MMYY"))) -> CXG-0125
A79: 7f998ccb | B79: 11258044 | C79: 45988 | D79: José Laelcio - MT | E79: 600 | F79: S.Grão - Sicredi | H79: AT170125124 | I79: =TEXT(C79,"MM/YYYY") -> 11/2025 | J79: =IF(C79="","",CONCATENATE("CXG-",TEXT(C79,"MMYY"))) -> CXG-1125
A80: e6303287 | B80: 11258193 | C80: 45988 | D80: Nielson Matias - MT | E80: 600 | F80: S.Grão - Sicredi | H80: AT170125124 | I80: =TEXT(C80,"MM/YYYY") -> 11/2025 | J80: =IF(C80="","",CONCATENATE("CXG-",TEXT(C80,"MMYY"))) -> CXG-1125
A81: 342bd8d8 | B81: 11258186 | C81: 45988 | D81: Amaury - MT | E81: 600 | F81: S.Grão - Sicredi | H81: AT170125124 | I81: =TEXT(C81,"MM/YYYY") -> 11/2025 | J81: =IF(C81="","",CONCATENATE("CXG-",TEXT(C81,"MMYY"))) -> CXG-1125
A82: 4c436ebd | B82: 11258349 | C82: 45988 | D82: Valdemir - MT | E82: 601.8 | F82: S.Grão - Sicredi | H82: AT170125124 | I82: =TEXT(C82,"MM/YYYY") -> 11/2025 | J82: =IF(C82="","",CONCATENATE("CXG-",TEXT(C82,"MMYY"))) -> CXG-1125
A83: e12225b9 | B83: 0125937 | C83: 45688 | D83: Luciano | E83: 606.2 | F83: N.Nordeste - B.Brasil | H83: AT170125124 | I83: =TEXT(C83,"MM/YYYY") -> 01/2025 | J83: =IF(C83="","",CONCATENATE("CXG-",TEXT(C83,"MMYY"))) -> CXG-0125
A84: c224959e | B84: 2480b2ad | C84: 45673 | D84: Carlos Henrique | E84: 626.8 | F84: Branco - B.Brasil | H84: AT170125124 | I84: =TEXT(C84,"MM/YYYY") -> 01/2025 | J84: =IF(C84="","",CONCATENATE("CXG-",TEXT(C84,"MMYY"))) -> CXG-0125
A85: 69355494 | B85: 05253283 | C85: 45810 | D85: Leandro - Santa Fé | E85: 633 | F85: N.Nordeste - B.Brasil | H85: AT170125124 | I85: =TEXT(C85,"MM/YYYY") -> 06/2025 | J85: =IF(C85="","",CONCATENATE("CXG-",TEXT(C85,"MMYY"))) -> CXG-0625
A86: 1d1f7656 | B86: 10256931 | C86: 45950 | D86: Pedro | E86: 644 | F86: S.Grão - Sicredi | H86: AT170125124 | I86: =TEXT(C86,"MM/YYYY") -> 10/2025 | J86: =IF(C86="","",CONCATENATE("CXG-",TEXT(C86,"MMYY"))) -> CXG-1025
A87: 51d67bd5 | B87: 12258641 | C87: 45996 | D87: Francinaldo | E87: 668 | F87: S.Grão - Sicredi | H87: AT170125124 | I87: =TEXT(C87,"MM/YYYY") -> 12/2025 | J87: =IF(C87="","",CONCATENATE("CXG-",TEXT(C87,"MMYY"))) -> CXG-1225
A88: 13fae403 | B88: 10257151 | C88: 45957 | D88: André Inacio | E88: 707.8 | F88: S.Grão - Sicredi | H88: AT170125124 | I88: =TEXT(C88,"MM/YYYY") -> 10/2025 | J88: =IF(C88="","",CONCATENATE("CXG-",TEXT(C88,"MMYY"))) -> CXG-1025
A89: 5af10752 | B89: 10256451 | C89: 45936 | D89: Marcos | E89: 729 | F89: S.Grão - Sicredi | H89: AT170125124 | I89: =TEXT(C89,"MM/YYYY") -> 10/2025 | J89: =IF(C89="","",CONCATENATE("CXG-",TEXT(C89,"MMYY"))) -> CXG-1025
A90: 62b886cf | B90: 96612447 | C90: 45685 | D90: Roberto - TW | E90: 2000 | F90: S.Grão - Bradesco | G90: Pagou e precisa descontar do valor total | H90: TW15012521 | I90: =TEXT(C90,"MM/YYYY") -> 01/2025 | J90: =IF(C90="","",CONCATENATE("CXG-",TEXT(C90,"MMYY"))) -> CXG-0125
A91: 8475565a | B91: 12258931 | C91: 46002 | D91: Edvaldo Cirino | E91: 750 | F91: S.Grão - Sicredi | H91: AT170125124 | I91: =TEXT(C91,"MM/YYYY") -> 12/2025 | J91: =IF(C91="","",CONCATENATE("CXG-",TEXT(C91,"MMYY"))) -> CXG-1225
A92: 781934cc | B92: 12258757 | C92: 45996 | D92: Vitor | E92: 758.4 | F92: S.Grão - Sicredi | H92: AT170125124 | I92: =TEXT(C92,"MM/YYYY") -> 12/2025 | J92: =IF(C92="","",CONCATENATE("CXG-",TEXT(C92,"MMYY"))) -> CXG-1225
A93: f769f380 | B93: 0125659 | C93: 45686 | D93: Zarloni - SR | E93: 13459.6 | F93: N.Nordeste - B.Brasil | G93: Comprovante de 43.022,00 | H93: SR16012556 | I93: =TEXT(C93,"MM/YYYY") -> 01/2025 | J93: =IF(C93="","",CONCATENATE("CXG-",TEXT(C93,"MMYY"))) -> CXG-0125
A94: a2f0083a | B94: 0125614 | C94: 45686 | D94: José Adeilson - SR | E94: 15941.2 | F94: N.Nordeste - B.Brasil | G94: Comprovante de 43.022,00 | H94: SR16012556 | I94: =TEXT(C94,"MM/YYYY") -> 01/2025 | J94: =IF(C94="","",CONCATENATE("CXG-",TEXT(C94,"MMYY"))) -> CXG-0125
A95: 82e071d2 | B95: 0125779 | C95: 45686 | D95: Geudo - SR | E95: 13823.2 | F95: N.Nordeste - B.Brasil | G95: Comprovante de 43.022,00 | H95: SR16012556 | I95: =TEXT(C95,"MM/YYYY") -> 01/2025 | J95: =IF(C95="","",CONCATENATE("CXG-",TEXT(C95,"MMYY"))) -> CXG-0125
A96: 8639a826 | B96: 0125779 | C96: 45686 | D96: Geudo - SR | E96: 1.6 | F96: Descontos | H96: SR16012556 | I96: =TEXT(C96,"MM/YYYY") -> 01/2025 | J96: =IF(C96="","",CONCATENATE("CXG-",TEXT(C96,"MMYY"))) -> CXG-0125
A97: 49956033 | B97: 09255700 | C97: 45910 | D97: Carlos Alberto | E97: 761.11 | F97: Descontos | G97: DIFERENÇA DE PESO | H97: AT170125124 | I97: =TEXT(C97,"MM/YYYY") -> 09/2025 | J97: =IF(C97="","",CONCATENATE("CXG-",TEXT(C97,"MMYY"))) -> CXG-0925
A98: fa45ab96 | B98: 12258802 | C98: 46003 | D98: José Carlos | E98: 768.4 | F98: S.Grão - Sicredi | H98: AT170125124 | I98: =TEXT(C98,"MM/YYYY") -> 12/2025 | J98: =IF(C98="","",CONCATENATE("CXG-",TEXT(C98,"MMYY"))) -> CXG-1225
A99: e8d6f010 | B99: 12258957 | C99: 46002 | D99: Cochilo | E99: 786 | F99: S.Grão - Sicredi | H99: AT170125124 | I99: =TEXT(C99,"MM/YYYY") -> 12/2025 | J99: =IF(C99="","",CONCATENATE("CXG-",TEXT(C99,"MMYY"))) -> CXG-1225
A100: 0840be6c | B100: 04252712 | C100: 45764 | D100: Erik | E100: 791.8 | F100: S.Grão - Sicredi | H100: AT170125124 | I100: =TEXT(C100,"MM/YYYY") -> 04/2025 | J100: =IF(C100="","",CONCATENATE("CXG-",TEXT(C100,"MMYY"))) -> CXG-0425
A101: 4753df47 | B101: 12258929 | C101: 46002 | D101: Bruno Cirino | E101: 798.7 | F101: S.Grão - Sicredi | H101: AT170125124 | I101: =TEXT(C101,"MM/YYYY") -> 12/2025 | J101: =IF(C101="","",CONCATENATE("CXG-",TEXT(C101,"MMYY"))) -> CXG-1225
A102: 0d5e3f36 | B102: 11257592 | C102: 45973 | D102: Cicero - MT | E102: 803 | F102: S.Grão - Sicredi | H102: AT170125124 | I102: =TEXT(C102,"MM/YYYY") -> 11/2025 | J102: =IF(C102="","",CONCATENATE("CXG-",TEXT(C102,"MMYY"))) -> CXG-1125
A103: 7e7cf8f0 | B103: 11258352 | C103: 45985 | D103: Anderson | E103: 803.2 | F103: S.Grão - Sicredi | H103: AT170125124 | I103: =TEXT(C103,"MM/YYYY") -> 11/2025 | J103: =IF(C103="","",CONCATENATE("CXG-",TEXT(C103,"MMYY"))) -> CXG-1125
A104: fe5049a8 | B104: b8499e43 | C104: 45678 | D104: Robson | E104: 835.2 | F104: S.Grão - Sicredi | H104: AT170125124 | I104: =TEXT(C104,"MM/YYYY") -> 01/2025 | J104: =IF(C104="","",CONCATENATE("CXG-",TEXT(C104,"MMYY"))) -> CXG-0125
A105: a6982eac | B105: 0125802 | C105: 45688 | D105: Tadeu | E105: 886 | F105: N.Nordeste - B.Brasil | H105: AT170125124 | I105: =TEXT(C105,"MM/YYYY") -> 01/2025 | J105: =IF(C105="","",CONCATENATE("CXG-",TEXT(C105,"MMYY"))) -> CXG-0125
A106: 6ce3f33a | B106: 06253379 | C106: 45826 | D106: FRETE - George | E106: 900 | F106: Terceiros | H106: AT170125124 | I106: =TEXT(C106,"MM/YYYY") -> 06/2025 | J106: =IF(C106="","",CONCATENATE("CXG-",TEXT(C106,"MMYY"))) -> CXG-0625
A107: 78fc13c3 | B107: 11258235 | C107: 45986 | D107: Paulo Teixeira | E107: 914 | F107: S.Grão - Banco C6 | H107: AT170125124 | I107: =TEXT(C107,"MM/YYYY") -> 11/2025 | J107: =IF(C107="","",CONCATENATE("CXG-",TEXT(C107,"MMYY"))) -> CXG-1125
A108: a12e3cda | B108: 12258730 | C108: 45999 | D108: Edivando | E108: 920.4 | F108: S.Grão - Sicredi | H108: AT170125124 | I108: =TEXT(C108,"MM/YYYY") -> 12/2025 | J108: =IF(C108="","",CONCATENATE("CXG-",TEXT(C108,"MMYY"))) -> CXG-1225
A109: de1c5959 | B109: 09256171 | C109: 45958 | D109: Carlos Alberto | E109: 968.96 | F109: Descontos | H109: AT170125124 | I109: =TEXT(C109,"MM/YYYY") -> 10/2025 | J109: =IF(C109="","",CONCATENATE("CXG-",TEXT(C109,"MMYY"))) -> CXG-1025
... A130: b72395b8 | B130: 0125543 | C130: 45681 | D130: Adriano Zanetti | E130: 1112.8 | F130: S.Grão - Sicredi | H130: AT170125124 | I130: =TEXT(C130,"MM/YYYY") -> 01/2025 | J130: =IF(C130="","",CONCATENATE("CXG-",TEXT(C130,"MMYY"))) -> CXG-0125
A131: adc625ac | B131: 11258485 | C131: 45992 | D131: Edevan | E131: 1117.6 | F131: S.Grão - Sicredi | G131: Comprovante de 6530,00 | H131: AT170125124 | I131: =TEXT(C131,"MM/YYYY") -> 12/2025 | J131: =IF(C131="","",CONCATENATE("CXG-",TEXT(C131,"MMYY"))) -> CXG-1225
A132: 4f7802dc | B132: 09256171 | C132: 45940 | D132: Carlos Alberto | E132: 1129.24 | F132: S.Grão - Sicredi | H132: AT170125124 | I132: =TEXT(C132,"MM/YYYY") -> 10/2025 | J132: =IF(C132="","",CONCATENATE("CXG-",TEXT(C132,"MMYY"))) -> CXG-1025
A133: e090d161 | B133: 10256727 | C133: 45943 | D133: Edilson | E133: 1138 | F133: S.Grão - Sicredi | H133: AT170125124 | I133: =TEXT(C133,"MM/YYYY") -> 10/2025 | J133: =IF(C133="","",CONCATENATE("CXG-",TEXT(C133,"MMYY"))) -> CXG-1025
A134: 779299d0 | B134: 11257808 | C134: 45982 | D134: Nailson | E134: 1159 | F134: S.Grão - Sicredi | H134: AT170125124 | I134: =TEXT(C134,"MM/YYYY") -> 11/2025 | J134: =IF(C134="","",CONCATENATE("CXG-",TEXT(C134,"MMYY"))) -> CXG-1125
A135: e5623ae9 | B135: 07254101 | C135: 45847 | D135: Josemar Andre | E135: 1193.1 | F135: S.Grão - Sicredi | H135: AT170125124 | I135: =TEXT(C135,"MM/YYYY") -> 07/2025 | J135: =IF(C135="","",CONCATENATE("CXG-",TEXT(C135,"MMYY"))) -> CXG-0725
A136: 4a67c58d | B136: 12258709 | C136: 45999 | D136: José Ariclecio | E136: 1230.2 | F136: S.Grão - Sicredi | H136: AT170125124 | I136: =TEXT(C136,"MM/YYYY") -> 12/2025 | J136: =IF(C136="","",CONCATENATE("CXG-",TEXT(C136,"MMYY"))) -> CXG-1225
A137: 2e36461a | B137: 02251069 | C137: 45698 | D137: Carlos Aguiar - MA | E137: 2999 | F137: N.Nordeste - B.Brasil | H137: MA30012584 | I137: =TEXT(C137,"MM/YYYY") -> 02/2025 | J137: =IF(C137="","",CONCATENATE("CXG-",TEXT(C137,"MMYY"))) -> CXG-0225
A138: 3de0be5a | B138: 12258663 | C138: 45999 | D138: Lucas | E138: 1231.55 | F138: S.Grão - Sicredi | H138: AT170125124 | I138: =TEXT(C138,"MM/YYYY") -> 12/2025 | J138: =IF(C138="","",CONCATENATE("CXG-",TEXT(C138,"MMYY"))) -> CXG-1225
A139: 689bde23 | B139: 11258325 | C139: 45985 | D139: Vinicius | E139: 1246.4 | F139: S.Grão - Sicredi | H139: AT170125124 | I139: =TEXT(C139,"MM/YYYY") -> 11/2025 | J139: =IF(C139="","",CONCATENATE("CXG-",TEXT(C139,"MMYY"))) -> CXG-1125
A140: 84dee431 | B140: 11258064 | C140: 45982 | D140: Hiago - Silvio | E140: 1259.8 | F140: S.Grão - Sicredi | H140: AT170125124 | I140: =TEXT(C140,"MM/YYYY") -> 11/2025 | J140: =IF(C140="","",CONCATENATE("CXG-",TEXT(C140,"MMYY"))) -> CXG-1125
A141: 1bd20843 | B141: 02251159 | C141: 45695 | D141: Luciano | E141: 1261.4 | F141: N.Nordeste - B.Brasil | H141: AT170125124 | I141: =TEXT(C141,"MM/YYYY") -> 02/2025 | J141: =IF(C141="","",CONCATENATE("CXG-",TEXT(C141,"MMYY"))) -> CXG-0225
A142: ce2b59eb | B142: 02251038 | C142: 45693 | D142: Luciano | E142: 1267.7 | F142: S.Grão - Sicredi | G142: Comprovante de 5267,70 | H142: AT170125124 | I142: =TEXT(C142,"MM/YYYY") -> 02/2025 | J142: =IF(C142="","",CONCATENATE("CXG-",TEXT(C142,"MMYY"))) -> CXG-0225
A143: cfcc604c | B143: 06253333 | C143: 45817 | D143: Pertubado | E143: 1290 | F143: N.Nordeste - B.Brasil | H143: AT170125124 | I143: =TEXT(C143,"MM/YYYY") -> 06/2025 | J143: =IF(C143="","",CONCATENATE("CXG-",TEXT(C143,"MMYY"))) -> CXG-0625
A144: 01fcdb3f | B144: 15aef9ac | C144: 45678 | D144: Wesley | E144: 1306.8 | F144: S.Grão - Sicredi | H144: AT170125124 | I144: =TEXT(C144,"MM/YYYY") -> 01/2025 | J144: =IF(C144="","",CONCATENATE("CXG-",TEXT(C144,"MMYY"))) -> CXG-0125
A145: 3a506bc0 | B145: 11258264 | C145: 45985 | D145: Vinicius | E145: 1369.6 | F145: S.Grão - Sicredi | H145: AT170125124 | I145: =TEXT(C145,"MM/YYYY") -> 11/2025 | J145: =IF(C145="","",CONCATENATE("CXG-",TEXT(C145,"MMYY"))) -> CXG-1125
A146: d050de44 | B146: c256b61c | C146: 45671 | D146: Carlos Henrique | E146: 1380.6 | F146: Branco - B.Brasil | H146: AT170125124 | I146: =TEXT(C146,"MM/YYYY") -> 01/2025 | J146: =IF(C146="","",CONCATENATE("CXG-",TEXT(C146,"MMYY"))) -> CXG-0125
A147: 5135a69b | B147: f3866f7f | C147: 45677 | D147: José Hilton | E147: 1438.4 | F147: N.Nordeste - B.Brasil | H147: AT170125124 | I147: =TEXT(C147,"MM/YYYY") -> 01/2025 | J147: =IF(C147="","",CONCATENATE("CXG-",TEXT(C147,"MMYY"))) -> CXG-0125
A148: 47327924 | B148: 02251047 | C148: 45689 | D148: Rogerio - SR | E148: 12394.2 | F148: N.Nordeste - B.Brasil | G148: Comprovante de 20.000,00 do Adiantamento | H148: SR30012567 | I148: =TEXT(C148,"MM/YYYY") -> 02/2025 | J148: =IF(C148="","",CONCATENATE("CXG-",TEXT(C148,"MMYY"))) -> CXG-0225
A149: 65d0a0b7 | B149: 04252639 | C149: 45758 | D149: André Luiz | E149: 1461 | F149: N.Nordeste - B.Brasil | H149: AT170125124 | I149: =TEXT(C149,"MM/YYYY") -> 04/2025 | J149: =IF(C149="","",CONCATENATE("CXG-",TEXT(C149,"MMYY"))) -> CXG-0425
A150: c7c7e4b3 | B150: 2a9cad0a | C150: 45671 | D150: Carlos Henrique | E150: 1487.2 | F150: Branco - B.Brasil | H150: AT170125124 | I150: =TEXT(C150,"MM/YYYY") -> 01/2025 | J150: =IF(C150="","",CONCATENATE("CXG-",TEXT(C150,"MMYY"))) -> CXG-0125
A151: 37bcfa8a | B151: 04252574 | C151: 45754 | D151: Erik | E151: 1496 | F151: S.Grão - Sicredi | H151: AT170125124 | I151: =TEXT(C151,"MM/YYYY") -> 04/2025 | J151: =IF(C151="","",CONCATENATE("CXG-",TEXT(C151,"MMYY"))) -> CXG-0425
A152: 3ad3c5f7 | B152: 02251125 | C152: 45695 | D152: José Claudio | E152: 1523.3 | F152: N.Nordeste - B.Brasil | H152: AT170125124 | I152: =TEXT(C152,"MM/YYYY") -> 02/2025 | J152: =IF(C152="","",CONCATENATE("CXG-",TEXT(C152,"MMYY"))) -> CXG-0225
A153: 99c7bb4d | B153: 11258511 | C153: 45993 | D153: Gabriel | E153: 1647.9 | F153: S.Grão - Sicredi | H153: AT170125124 | I153: =TEXT(C153,"MM/YYYY") -> 12/2025 | J153: =IF(C153="","",CONCATENATE("CXG-",TEXT(C153,"MMYY"))) -> CXG-1225
A154: 9332f98d | B154: 04252501 | C154: 45754 | D154: Thiago Araujo | E154: 1652 | F154: S.Grão - Sicredi | H154: AT170125124 | I154: =TEXT(C154,"MM/YYYY") -> 04/2025 | J154: =IF(C154="","",CONCATENATE("CXG-",TEXT(C154,"MMYY"))) -> CXG-0425
A155: 7f84cac2 | B155: 10256879 | C155: 45947 | D155: Marcelo | E155: 1657.55 | F155: S.Grão - Sicredi | H155: AT170125124 | I155: =TEXT(C155,"MM/YYYY") -> 10/2025 | J155: =IF(C155="","",CONCATENATE("CXG-",TEXT(C155,"MMYY"))) -> CXG-1025
A156: 7ef24b12 | B156: 06253307 | C156: 45814 | D156: Ls 4 Eixo Santa Fé | E156: 1688 | F156: N.Nordeste - B.Brasil | H156: AT170125124 | I156: =TEXT(C156,"MM/YYYY") -> 06/2025 | J156: =IF(C156="","",CONCATENATE("CXG-",TEXT(C156,"MMYY"))) -> CXG-0625
A157: a16b905b | B157: 07254110 | C157: 45847 | D157: Edinaldo Andre | E157: 1691 | F157: S.Grão - Sicredi | H157: AT170125124 | I157: =TEXT(C157,"MM/YYYY") -> 07/2025 | J157: =IF(C157="","",CONCATENATE("CXG-",TEXT(C157,"MMYY"))) -> CXG-0725
A158: 1af29be8 | B158: 09255700 | C158: 45907 | D158: Carlos Alberto | E158: 1700 | F158: S.Grão - Sicredi | H158: AT170125124 | I158: =TEXT(C158,"MM/YYYY") -> 09/2025 | J158: =IF(C158="","",CONCATENATE("CXG-",TEXT(C158,"MMYY"))) -> CXG-0925
...

Sheet CarrinhoFretes
A1: id | B1: data | C1: PedidoFrete | D1: Quantidade Kg | E1: Quantidade Sc | F1: Valor Custo SC | G1: SubTotal Milho | H1: Valor NF Sc | I1: Valor Total NF Sc | J1: Motorista | K1: Valor Frete | L1: SubTotal Frete | M1: Manifesto | N1: Cliente | O1: PedidodeVenda | P1: Valor Venda SC | Q1: Valor Total de Venda | R1: Anotações NF | S1: PedCxMensal | T1: MesAno | U1: PedidodeCompra | V1: Peso Descarrego | W1: Sc Descarrego | X1: Quebra de Peso | Y1: Transito | Z1: Transportadora | AA1: Valor Pago | AB1: Valor Pendente | AC1: TransportePagp
A2: 12259130 | B2: 46002 | C2: AT170125124 | D2: 73680 | E2: 1228 | F2: 67.5 | G2: 82890 | H2: 0 | I2: 0 | J2: Robson - TW | K2: 100 | L2: 7368 | M2: Encerrado | N2: Rodrigo Gargamel | O2: P1225NEW75190 | P2: 75 | Q2: 92100 | R2: REP. SAO BRAZ BAHIA | S2: =IF(B2="","",CONCATENATE("CXG-",TEXT(B2,"MMYY"))) -> CXG-1225 | T2: =TEXT(B2,"MM/YYYY") -> 12/2025 | U2: 12122514251 | V2: 73680 | W2: 1228 | X2: 0 | Y2: =IF(OR(V2="",V2=0),"Em Trânsito","Descarregado") -> Descarregado | Z2: AT - Autônomo | AA2: =SUMIFS(PagFreteIndividal!E:E,PagFreteIndividal!B:B,A:A)+AC2 -> 7368 | AB2: =L2-AA2 -> 0 | AC2: 0
A3: 0125761 | B3: 45682 | C3: AT170125124 | D3: 68310 | E3: 1138.5 | F3: 67 | G3: 76279.5 | H3: 0 | I3: 0 | J3: Tacio André | K3: 150 | L3: 10246.5 | M3: Encerrado | N3: André Canguaretama | O3: P0125RON834 | P3: 82.5 | Q3: 93926.25 | S3: =IF(B3="","",CONCATENATE("CXG-",TEXT(B3,"MMYY"))) -> CXG-0125 | T3: =TEXT(B3,"MM/YYYY") -> 01/2025 | U3: 2001251545 | V3: 68310 | W3: 1138.5 | X3: 0 | Y3: =IF(OR(V3="",V3=0),"Em Trânsito","Descarregado") -> Descarregado | Z3: AT - Autônomo | AA3: =SUMIFS(PagFreteIndividal!E:E,PagFreteIndividal!B:B,A:A)+AC3 -> 10246.5 | AB3: =L3-AA3 -> 0 | AC3: 0
A4: 02251401 | B4: 45708 | C4: AT170125124 | D4: 63220 | E4: 1053.67 | F4: 70 | G4: 73756.9 | H4: 0 | I4: 0 | J4: Adilson de Castro | K4: 150 | L4: 9483 | M4: Encerrado | N4: Três Corações | O4: P0125NEW8325 | P4: 83 | Q4: 87496.11 | S4: =IF(B4="","",CONCATENATE("CXG-",TEXT(B4,"MMYY"))) -> CXG-0225 | T4: =TEXT(B4,"MM/YYYY") -> 02/2025 | U4: 1902252793 | V4: 63250 | W4: 1054.17 | X4: 0.5 | Y4: =IF(OR(V4="",V4=0),"Em Trânsito","Descarregado") -> Descarregado | Z4: AT - Autônomo | AA4: =SUMIFS(PagFreteIndividal!E:E,PagFreteIndividal!B:B,A:A)+AC4 -> 9483 | AB4: =L4-AA4 -> 0 | AC4: 0
A5: 9bb58ff3 | B5: 45668 | C5: TW15012521 | D5: 32060 | E5: 534.33 | F5: 70.25 | G5: 37536.68 | H5: 0 | I5: 0 | J5: Heder - TW | K5: 90 | L5: 2885.4 | M5: Encerrado | N5: Frei Damião | O5: PED0125NEW773 | P5: 77 | Q5: 40964 | S5: =IF(B5="","",CONCATENATE("CXG-",TEXT(B5,"MMYY"))) -> CXG-0125 | T5: =TEXT(B5,"MM/YYYY") -> 01/2025 | U5: 150125254 | V5: 31920 | W5: 532 | X5: -2.33 | Y5: =IF(OR(V5="",V5=0),"Em Trânsito","Descarregado") -> Descarregado | Z5: TW - Suporte Agrícola | AA5: =SUMIFS(PagFreteIndividal!E:E,PagFreteIndividal!B:B,A:A)+AC5 -> 2885.4 | AB5: =L5-AA5 -> 0 | AC5: 2885.4
A6: 10256607 | B6: 45939 | C6: AT170125124 | D6: 50580 | E6: 843 | F6: 60 | G6: 50580 | H6: 0 | I6: 0 | J6: Celso - Andre | K6: 320 | L6: 16185.6 | M6: Encerrado | N6: São Braz S/A Industria E Comercio De Alimentos | O6: P1025NEW83152 | P6: 83 | Q6: 69803 | S6: =IF(B6="","",CONCATENATE("CXG-",TEXT(B6,"MMYY"))) -> CXG-1025 | T6: =TEXT(B6,"MM/YYYY") -> 10/2025 | U6: 0310258023 | V6: 50460 | W6: 841 | X6: -2 | Y6: =IF(OR(V6="",V6=0),"Em Trânsito","Descarregado") -> Descarregado | Z6: AT - Autônomo | AA6: =SUMIFS(PagFreteIndividal!E:E,PagFreteIndividal!B:B,A:A)+AC6 -> 16185.6 | AB6: =L6-AA6 -> 0 | AC6: 0
A7: 10256613 | B7: 45939 | C7: AT170125124 | D7: 41880 | E7: 698 | F7: 60 | G7: 41880 | H7: 0 | I7: 0 | J7: Michel - Andre | K7: 320 | L7: 13401.6 | M7: Encerrado | N7: São Braz S/A Industria E Comercio De Alimentos | O7: P1025NEW83152 | P7: 83 | Q7: 58127.39 | S7: =IF(B7="","",CONCATENATE("CXG-",TEXT(B7,"MMYY"))) -> CXG-1025 | T7: =TEXT(B7,"MM/YYYY") -> 10/2025 | U7: 0310258023 | V7: 42020 | W7: 700.33 | X7: 2.33 | Y7: =IF(OR(V7="",V7=0),"Em Trânsito","Descarregado") -> Descarregado | Z7: AT - Autônomo | AA7: =SUMIFS(PagFreteIndividal!E:E,PagFreteIndividal!B:B,A:A)+AC7 -> 13401.6 | AB7: =L7-AA7 -> 0 | AC7: 0
A8: 9d8efcc8 | B8: 45667 | C8: TW15012521 | D8: 79080 | E8: 1318 | F8: 70.25 | G8: 92589.5 | H8: 1 | I8: 1318 | J8: Gustavo - TW | K8: 130 | L8: 10280.4 | M8: Encerrado | N8: André Timbauba | O8: P0125RON836 | P8: 83 | Q8: 109172.39 | S8: =IF(B8="","",CONCATENATE("CXG-",TEXT(B8,"MMYY"))) -> CXG-0125 | T8: =TEXT(B8,"MM/YYYY") -> 01/2025 | U8: 150125254 | V8: 78920 | W8: 1315.33 | X8: -2.67 | Y8: =IF(OR(V8="",V8=0),"Em Trânsito","Descarregado") -> Descarregado | Z8: TW - Suporte Agrícola | AA8: =SUMIFS(PagFreteIndividal!E:E,PagFreteIndividal!B:B,A:A)+AC8 -> 10280.4 | AB8: =L8-AA8 -> 0 | AC8: 10280.4
A9: 0da6cb2b | B9: 45667 | C9: TW15012521 | D9: 67140 | E9: 1119 | F9: 70.25 | G9: 78609.75 | H9: 0.8 | I9: 895.2 | J9: André - TW | K9: 130 | L9: 8728.2 | M9: Encerrado | N9: André Timbauba | O9: P0125RON836 | P9: 82 | Q9: 91771.94 | S9: =IF(B9="","",CONCATENATE("CXG-",TEXT(B9,"MMYY"))) -> CXG-0125 | T9: =TEXT(B9,"MM/YYYY") -> 01/2025 | U9: 150125254 | V9: 67150 | W9: 1119.17 | X9: 0.17 | Y9: =IF(OR(V9="",V9=0),"Em Trânsito","Descarregado") -> Descarregado | Z9: TW - Suporte Agrícola | AA9: =SUMIFS(PagFreteIndividal!E:E,PagFreteIndividal!B:B,A:A)+AC9 -> 8728.2 | AB9: =L9-AA9 -> 0 | AC9: 8728.2
A10: 96612447 | B10: 45666 | C10: TW15012521 | D10: 71340 | E10: 1189 | F10: 69 | G10: 82041 | H10: 0.8 | I10: 951.2 | J10: Roberto - TW | K10: 150 | L10: 10701 | M10: Encerrado | N10: Santa Cruz - RN | O10: P0125RON827 | P10: 82 | Q10: 97498 | S10: =IF(B10="","",CONCATENATE("CXG-",TEXT(B10,"MMYY"))) -> CXG-0125 | T10: =TEXT(B10,"MM/YYYY") -> 01/2025 | U10: 160125346 | V10: 71340 | W10: 1189 | X10: 0 | Y10: =IF(OR(V10="",V10=0),"Em Trânsito","Descarregado") -> Descarregado | Z10: TW - Suporte Agrícola | AA10: =SUMIFS(PagFreteIndividal!E:E,PagFreteIndividal!B:B,A:A)+AC10 -> 10701 | AB10: =L10-AA10 -> 0 | AC10: 8701
A11: b4fc34bc | B11: 45672 | C11: SR16012556 | D11: 60000 | E11: 1000 | F11: 65.5 | G11: 65500 | H11: 1 | I11: 1000 | J11: Rogerio - SR | K11: 230 | L11: 13800 | M11: Encerrado | N11: Ilario Campina Grande | O11: P0125RON8316 | P11: 83 | Q11: 83000 | S11: =IF(B11="","",CONCATENATE("CXG-",TEXT(B11,"MMYY"))) -> CXG-0125 | T11: =TEXT(B11,"MM/YYYY") -> 01/2025 | U11: 160125786 | V11: 60000 | W11: 1000 | X11: 0 | Y11: =IF(OR(V11="",V11=0),"Em Trânsito","Descarregado") -> Descarregado | Z11: SR - Sergio Rocha | AA11: =SUMIFS(PagFreteIndividal!E:E,PagFreteIndividal!B:B,A:A)+AC11 -> 13800 | AB11: =L11-AA11 -> 0 | AC11: 0
A12: 796941eb | B12: 45672 | C12: SR16012556 | D12: 62140 | E12: 1035.67 | F12: 65.5 | G12: 67836.38 | H12: 1 | I12: 1035.67 | J12: Geudo - SR | K12: 230 | L12: 14292.2 | M12: Encerrado | N12: Michel Campina Grande / Azevem | O12: P0125NEW8315 | P12: 82 | Q12: 84924.94 | R12: Reprovado / Descarregado Michel Curiem | S12: =IF(B12="","",CONCATENATE("CXG-",TEXT(B12,"MMYY"))) -> CXG-0125 | T12: =TEXT(B12,"MM/YYYY") -> 01/2025 | U12: 160125786 | V12: 62140 | W12: 1035.67 | X12: 0 | Y12: =IF(OR(V12="",V12=0),"Em Trânsito","Descarregado") -> Descarregado | Z12: SR - Sergio Rocha | AA12: =SUMIFS(PagFreteIndividal!E:E,PagFreteIndividal!B:B,A:A)+AC12 -> 14292.2 | AB12: =L12-AA12 -> 0 | AC12: 0
A13: 11258569 | B13: 45991 | C13: AT170125124 | D13: 53440 | E13: 890.67 | F13: 67 | G13: 59674.89 | H13: 0 | I13: 0 | J13: Edevan | K13: 120 | L13: 6412.8 | M13: Encerrado | N13: Rildo Roque Ferraz | O13: P1125RON77175 | P13: 77 | Q13: 68401.41 | S13: =IF(B13="","",CONCATENATE("CXG-",TEXT(B13,"MMYY"))) -> CXG-1125 | T13: =TEXT(B13,"MM/YYYY") -> 11/2025 | U13: 17112511988 | V13: 53300 | W13: 888.33 | X13: -2.34 | Y13: =IF(OR(V13="",V13=0),"Em Trânsito","Descarregado") -> Descarregado | Z13: AT - Autônomo | AA13: =SUMIFS(PagFreteIndividal!E:E,PagFreteIndividal!B:B,A:A)+AC13 -> 6412.8 | AB13: =L13-AA13 -> 0 | AC13: 0
A14: 8064ec07 | B14: 45668 | C14: AT170125124 | D14: 71260 | E14: 1187.67 | F14: 70.25 | G14: 83433.82 | H14: 0.8 | I14: 950.14 | J14: Gabriel | K14: 150 | L14: 10689 | M14: Encerrado | N14: André Canguaretama | O14: P0125RON834 | P14: 82.75 | Q14: 98279.69 | S14: =IF(B14="","",CONCATENATE("CXG-",TEXT(B14,"MMYY"))) -> CXG-0125 | T14: =TEXT(B14,"MM/YYYY") -> 01/2025 | U14: 150125254 | V14: 71260 | W14: 1187.67 | X14: 0 | Y14: =IF(OR(V14="",V14=0),"Em Trânsito","Descarregado") -> Descarregado | Z14: AT - Autônomo | AA14: =SUMIFS(PagFreteIndividal!E:E,PagFreteIndividal!B:B,A:A)+AC14 -> 10689 | AB14: =L14-AA14 -> 0 | AC14: 0
A15: 2dd2ff9e | B15: 45672 | C15: TW15012521 | D15: 67840 | E15: 1130.67 | F15: 70 | G15: 79146.9 | H15: 1 | I15: 1130.67 | J15: André - TW | K15: 90 | L15: 6105.6 | M15: Encerrado | N15: Natto Alimentos | O15: P0125RON789 | P15: 78 | Q15: 91858.26 | S15: =IF(B15="","",CONCATENATE("CXG-",TEXT(B15,"MMYY"))) -> CXG-0125 | T15: =TEXT(B15,"MM/YYYY") -> 01/2025 | U15: 160125657 | V15: 70660 | W15: 1177.67 | X15: 47 | Y15: =IF(OR(V15="",V15=0),"Em Trânsito","Descarregado") -> Descarregado | Z15: TW - Suporte Agrícola | AA15: =SUMIFS(PagFreteIndividal!E:E,PagFreteIndividal!B:B,A:A)+AC15 -> 6105.6 | AB15: =L15-AA15 -> 0 | AC15: 6105.6
A16: 3497e51c | B16: 45672 | C16: TW15012521 | D16: 78580 | E16: 1309.67 | F16: 70 | G16: 91676.9 | H16: 0.8 | I16: 1047.74 | J16: Gustavo - TW | K16: 90 | L16: 7072.2 | M16: Encerrado | N16: Natto Alimentos | O16: P0125RON789 | P16: 78 | Q16: 102726 | S16: =IF(B16="","",CONCATENATE("CXG-",TEXT(B16,"MMYY"))) -> CXG-0125 | T16: =TEXT(B16,"MM/YYYY") -> 01/2025 | U16: 160125657 | V16: 79020 | W16: 1317 | X16: 7.33 | Y16: =IF(OR(V16="",V16=0),"Em Trânsito","Descarregado") -> Descarregado | Z16: TW - Suporte Agrícola | AA16: =SUMIFS(PagFreteIndividal!E:E,PagFreteIndividal!B:B,A:A)+AC16 -> 7072.2 | AB16: =L16-AA16 -> 0 | AC16: 7072.2
A17: 2a9cad0a | B17: 45668 | C17: AT170125124 | D17: 11440 | E17: 190.67 | F17: 70.25 | G17: 13394.57 | H17: 0.8 | I17: 152.54 | J17: Carlos Henrique | K17: 130 | L17: 1487.2 | M17: Encerrado | N17: Ana Maria Laroche | O17: P0125RON825 | P17: 82 | Q17: 15634.94 | S17: =IF(B17="","",CONCATENATE("CXG-",TEXT(B17,"MMYY"))) -> CXG-0125 | T17: =TEXT(B17,"MM/YYYY") -> 01/2025 | U17: 150125254 | V17: 11440 | W17: 190.67 | X17: 0 | Y17: =IF(OR(V17="",V17=0),"Em Trânsito","Descarregado") -> Descarregado | Z17: AT - Autônomo | AA17: =SUMIFS(PagFreteIndividal!E:E,PagFreteIndividal!B:B,A:A)+AC17 -> 1487.2 | AB17: =L17-AA17 -> 0 | AC17: 0
A18: c256b61c | B18: 45671 | C18: AT170125124 | D18: 10620 | E18: 177 | F18: 70.5 | G18: 12478.5 | H18: 1 | I18: 177 | J18: Carlos Henrique | K18: 130 | L18: 1380.6 | M18: Encerrado | N18: Ana Maria Laroche | O18: P0125RON825 | P18: 82 | Q18: 14514 | S18: =IF(B18="","",CONCATENATE("CXG-",TEXT(B18,"MMYY"))) -> CXG-0125 | T18: =TEXT(B18,"MM/YYYY") -> 01/2025 | U18: 160125555 | V18: 10620 | W18: 177 | X18: 0 | Y18: =IF(OR(V18="",V18=0),"Em Trânsito","Descarregado") -> Descarregado | Z18: AT - Autônomo | AA18: =SUMIFS(PagFreteIndividal!E:E,PagFreteIndividal!B:B,A:A)+AC18 -> 1380.6 | AB18: =L18-AA18 -> 0 | AC18: 0
A19: 2480b2ad | B19: 45671 | C19: AT170125124 | D19: 19300 | E19: 321.67 | F19: 70 | G19: 22516.9 | H19: 0.8 | I19: 257.34 | J19: Carlos Henrique | K19: 130 | L19: 2509 | M19: Encerrado | N19: Ana Maria Laroche | O19: P0125RON825 | P19: 82 | Q19: 26431.06 | S19: =IF(B19="","",CONCATENATE("CXG-",TEXT(B19,"MMYY"))) -> CXG-0125 | T19: =TEXT(B19,"MM/YYYY") -> 01/2025 | U19: 160125657 | V19: 19340 | W19: 322.33 | X19: 0.66 | Y19: =IF(OR(V19="",V19=0),"Em Trânsito","Descarregado") -> Descarregado | Z19: AT - Autônomo | AA19: =SUMIFS(PagFreteIndividal!E:E,PagFreteIndividal!B:B,A:A)+AC19 -> 2509 | AB19: =L19-AA19 -> 0 | AC19: 0
A20: 15aef9ac | B20: 45673 | C20: AT170125124 | D20: 14520 | E20: 242 | F20: 70 | G20: 16940 | H20: 0.8 | I20: 193.6 | J20: Wesley | K20: 90 | L20: 1306.8 | M20: Encerrado | N20: Natto Branco | O20: P0125RON789 | P20: 78 | Q20: 18876 | S20: =IF(B20="","",CONCATENATE("CXG-",TEXT(B20,"MMYY"))) -> CXG-0125 | T20: =TEXT(B20,"MM/YYYY") -> 01/2025 | U20: 160125657 | V20: 14520 | W20: 242 | X20: 0 | Y20: =IF(OR(V20="",V20=0),"Em Trânsito","Descarregado") -> Descarregado | Z20: AT - Autônomo | AA20: =SUMIFS(PagFreteIndividal!E:E,PagFreteIndividal!B:B,A:A)+AC20 -> 1306.8 | AB20: =L20-AA20 -> 0 | AC20: 0
A21: 7c5d1545 | B21: 45673 | C21: AT170125124 | D21: 70680 | E21: 1178 | F21: 70 | G21: 82460 | H21: 0.8 | I21: 942.4 | J21: Bruno Vinicius | K21: 90 | L21: 6361.2 | M21: Encerrado | N21: Natto Alimentos | O21: P0125RON789 | P21: 78 | Q21: 92170.26 | S21: =IF(B21="","",CONCATENATE("CXG-",TEXT(B21,"MMYY"))) -> CXG-0125 | T21: =TEXT(B21,"MM/YYYY") -> 01/2025 | U21: 160125657 | V21: 70900 | W21: 1181.67 | X21: 3.67 | Y21: =IF(OR(V21="",V21=0),"Em Trânsito","Descarregado") -> Descarregado | Z21: AT - Autônomo | AA21: =SUMIFS(PagFreteIndividal!E:E,PagFreteIndividal!B:B,A:A)+AC21 -> 6361.2 | AB21: =L21-AA21 -> 0 | AC21: 0
A22: 721aded7 | B22: 45671 | C22: AT170125124 | D22: 71900 | E22: 1198.33 | F22: 70 | G22: 83883.1 | H22: 0.8 | I22: 958.66 | J22: Renato Xavier | K22: 150 | L22: 10785 | M22: Encerrado | N22: Ovos Sao Tome | O22: P0125NEW8210 | P22: 82.5 | Q22: 98862.23 | S22: =IF(B22="","",CONCATENATE("CXG-",TEXT(B22,"MMYY"))) -> CXG-0125 | T22: =TEXT(B22,"MM/YYYY") -> 01/2025 | U22: 160125470 | V22: 71900 | W22: 1198.33 | X22: 0 | Y22: =IF(OR(V22="",V22=0),"Em Trânsito","Descarregado") -> Descarregado | Z22: AT - Autônomo | AA22: =SUMIFS(PagFreteIndividal!E:E,PagFreteIndividal!B:B,A:A)+AC22 -> 10785 | AB22: =L22-AA22 -> 0 | AC22: 0
A23: 238fbb0c | B23: 45671 | C23: AT170125124 | D23: 51240 | E23: 854 | F23: 70 | G23: 59780 | H23: 0.8 | I23: 683.2 | J23: Manfred | K23: 140 | L23: 7173.6 | M23: Encerrado | N23: André Pombal | O23: P0125NEW8311 | P23: 83 | Q23: 70882 | S23: =IF(B23="","",CONCATENATE("CXG-",TEXT(B23,"MMYY"))) -> CXG-0125 | T23: =TEXT(B23,"MM/YYYY") -> 01/2025 | U23: 160125470 | V23: 51240 | W23: 854 | X23: 0 | Y23: =IF(OR(V23="",V23=0),"Em Trânsito","Descarregado") -> Descarregado | Z23: AT - Autônomo | AA23: =SUMIFS(PagFreteIndividal!E:E,PagFreteIndividal!B:B,A:A)+AC23 -> 7173.6 | AB23: =L23-AA23 -> 0 | AC23: 0
A24: e05cf712 | B24: 45666 | C24: SR16012556 | D24: 71160 | E24: 1186 | F24: 65.5 | G24: 77683 | H24: 1 | I24: 1186 | J24: José Adelson - SR | K24: 220 | L24: 15655.2 | M24: Encerrado | N24: André Timbauba | O24: P0125RON836 | P24: 82 | Q24: 97593.94 | S24: =IF(B24="","",CONCATENATE("CXG-",TEXT(B24,"MMYY"))) -> CXG-0125 | T24: =TEXT(B24,"MM/YYYY") -> 01/2025 | U24: 170125830 | V24: 71410 | W24: 1190.17 | X24: 4.17 | Y24: =IF(OR(V24="",V24=0),"Em Trânsito","Descarregado") -> Descarregado | Z24: SR - Sergio Rocha | AA24: =SUMIFS(PagFreteIndividal!E:E,PagFreteIndividal!B:B,A:A)+AC24 -> 15655.2 | AB24: =L24-AA24 -> 0 | AC24: 0
... A86: 0125855 | B86: 45685 | C86: TW15012521 | D86: 67260 | E86: 1121 | F86: 68 | G86: 76228 | H86: 0 | I86: 0 | J86: Douglas - TW | K86: 120 | L86: 8071.2 | M86: Encerrado | N86: Japones | O86: P0125RON8414 | P86: 84 | Q86: 94779.72 | S86: =IF(B86="","",CONCATENATE("CXG-",TEXT(B86,"MMYY"))) -> CXG-0125 | T86: =TEXT(B86,"MM/YYYY") -> 01/2025 | U86: 2801251960 | V86: 67700 | W86: 1128.33 | X86: 7.33 | Y86: =IF(OR(V86="",V86=0),"Em Trânsito","Descarregado") -> Descarregado | Z86: TW - Suporte Agrícola | AA86: =SUMIFS(PagFreteIndividal!E:E,PagFreteIndividal!B:B,A:A)+AC86 -> 8071.2 | AB86: =L86-AA86 -> 0 | AC86: 8071.2
A87: 0125815 | B87: 45684 | C87: AT170125124 | D87: 70540 | E87: 1175.67 | F87: 65.5 | G87: 77006.38 | H87: 0 | I87: 0 | J87: Hallan | K87: 210 | L87: 14813.4 | M87: Encerrado | N87: Fabio Mossoró | O87: P0225NEW7937 | P87: 80 | Q87: 94040 | R87: Reprovando em 3 Corações | S87: =IF(B87="","",CONCATENATE("CXG-",TEXT(B87,"MMYY"))) -> CXG-0125 | T87: =TEXT(B87,"MM/YYYY") -> 01/2025 | U87: 200125137 | V87: 70530 | W87: 1175.5 | X87: -0.17 | Y87: =IF(OR(V87="",V87=0),"Em Trânsito","Descarregado") -> Descarregado | Z87: AT - Autônomo | AA87: =SUMIFS(PagFreteIndividal!E:E,PagFreteIndividal!B:B,A:A)+AC87 -> 14813.4 | AB87: =L87-AA87 -> 0 | AC87: 0
